Workbook

Sheet Matriz_por_área
A1: Matriz didácticas × Área SWEBOK (agregada, sin subáreas) — leyenda de colores
A3: 1 | C3: 2 | E3: 3 a 5 | G3: 6 o más | I3: Fila extra (sin equivalente) / columna Sin área SWEBOK | L3: Encabezado de nivel/área
A5: Nivel taxonómico | B5: Técnica didáctica (código y nombre) | C5: REQUIREMENTS | D5: ARCHITECTURE | E5: DESIGN | F5: CONSTRUCTION | G5: SOFTWARE TESTING | H5: SOFTWARE ENG. OPERATIONS | I5: MAINTENANCE | J5: SOFTWARE CONFIG. MGMT. | K5: SOFTWARE ENG. PROCESS | L5: SOFTWARE ENG. MODELS/METH. | M5: SOFTWARE QUALITY | N5: SOFTWARE SECURITY | O5: PROFESSIONAL PRACTICE | P5: SOFTWARE ENG. ECONOMICS | Q5: SOFTWARE ENG. MANAGEMENT | R5: Sin área SWEBOK | S5: Total fila
A6: RECORDAR | B6: T001 Diario de aprendizaje | C6: =COUNTIFS('Prácticas_Revisiones'!$S$2:$S$282,"T001",'Prácticas_Revisiones'!$T$2:$T$282,"REQUIREMENTS > *")+COUNTIFS('Prácticas_Snowballing'!$AB$2:$AB$281,"T001",'Prácticas_Snowballing'!$AC$2:$AC$281,"REQUIREMENTS > *") -> 0 | D6: =COUNTIFS('Prácticas_Revisiones'!$S$2:$S$282,"T001",'Prácticas_Revisiones'!$T$2:$T$282,"ARCHITECTURE > *")+COUNTIFS('Prácticas_Snowballing'!$AB$2:$AB$281,"T001",'Prácticas_Snowballing'!$AC$2:$AC$281,"ARCHITECTURE > *") -> 0 | E6: =COUNTIFS('Prácticas_Revisiones'!$S$2:$S$282,"T001",'Prácticas_Revisiones'!$T$2:$T$282,"DESIGN > *")+COUNTIFS('Prácticas_Snowballing'!$AB$2:$AB$281,"T001",'Prácticas_Snowballing'!$AC$2:$AC$281,"DESIGN > *") -> 1 | F6: =COUNTIFS('Prácticas_Revisiones'!$S$2:$S$282,"T001",'Prácticas_Revisiones'!$T$2:$T$282,"CONSTRUCTION > *")+COUNTIFS('Prácticas_Snowballing'!$AB$2:$AB$281,"T001",'Prácticas_Snowballing'!$AC$2:$AC$281,"CONSTRUCTION > *") -> 5 | G6: =COUNTIFS('Prácticas_Revisiones'!$S$2:$S$282,"T001",'Prácticas_Revisiones'!$T$2:$T$282,"SOFTWARE TESTING > *")+COUNTIFS('Prácticas_Snowballing'!$AB$2:$AB$281,"T001",'Prácticas_Snowballing'!$AC$2:$AC$281,"SOFTWARE TESTING > *") -> 0 | H6: =COUNTIFS('Prácticas_Revisiones'!$S$2:$S$282,"T001",'Prácticas_Revisiones'!$T$2:$T$282,"SOFTWARE ENG. OPERATIONS > *")+COUNTIFS('Prácticas_Snowballing'!$AB$2:$AB$281,"T001",'Prácticas_Snowballing'!$AC$2:$AC$281,"SOFTWARE ENG. OPERATIONS > *") -> 0 | I6: =COUNTIFS('Prácticas_Revisiones'!$S$2:$S$282,"T001",'Prácticas_Revisiones'!$T$2:$T$282,"MAINTENANCE > *")+COUNTIFS('Prácticas_Snowballing'!$AB$2:$AB$281,"T001",'Prácticas_Snowballing'!$AC$2:$AC$281,"MAINTENANCE > *") -> 0 | J6: =COUNTIFS('Prácticas_Revisiones'!$S$2:$S$282,"T001",'Prácticas_Revisiones'!$T$2:$T$282,"SOFTWARE CONFIG. MGMT. > *")+COUNTIFS('Prácticas_Snowballing'!$AB$2:$AB$281,"T001",'Prácticas_Snowballing'!$AC$2:$AC$281,"SOFTWARE CONFIG. MGMT. > *") -> 0 | K6: =COUNTIFS('Prácticas_Revisiones'!$S$2:$S$282,"T001",'Prácticas_Revisiones'!$T$2:$T$282,"SOFTWARE ENG. PROCESS > *")+COUNTIFS('Prácticas_Snowballing'!$AB$2:$AB$281,"T001",'Prácticas_Snowballing'!$AC$2:$AC$281,"SOFTWARE ENG. PROCESS > *") -> 0 | L6: =COUNTIFS('Prácticas_Revisiones'!$S$2:$S$282,"T001",'Prácticas_Revisiones'!$T$2:$T$282,"SOFTWARE ENG. MODELS/METH. > *")+COUNTIFS('Prácticas_Snowballing'!$AB$2:$AB$281,"T001",'Prácticas_Snowballing'!$AC$2:$AC$281,"SOFTWARE ENG. MODELS/METH. > *") -> 0 | M6: =COUNTIFS('Prácticas_Revisiones'!$S$2:$S$282,"T001",'Prácticas_Revisiones'!$T$2:$T$282,"SOFTWARE QUALITY > *")+COUNTIFS('Prácticas_Snowballing'!$AB$2:$AB$281,"T001",'Prácticas_Snowballing'!$AC$2:$AC$281,"SOFTWARE QUALITY > *") -> 0 | N6: =COUNTIFS('Prácticas_Revisiones'!$S$2:$S$282,"T001",'Prácticas_Revisiones'!$T$2:$T$282,"SOFTWARE SECURITY > *")+COUNTIFS('Prácticas_Snowballing'!$AB$2:$AB$281,"T001",'Prácticas_Snowballing'!$AC$2:$AC$281,"SOFTWARE SECURITY > *") -> 0 | O6: =COUNTIFS('Prácticas_Revisiones'!$S$2:$S$282,"T001",'Prácticas_Revisiones'!$T$2:$T$282,"PROFESSIONAL PRACTICE > *")+COUNTIFS('Prácticas_Snowballing'!$AB$2:$AB$281,"T001",'Prácticas_Snowballing'!$AC$2:$AC$281,"PROFESSIONAL PRACTICE > *") -> 0 | P6: =COUNTIFS('Prácticas_Revisiones'!$S$2:$S$282,"T001",'Prácticas_Revisiones'!$T$2:$T$282,"SOFTWARE ENG. ECONOMICS > *")+COUNTIFS('Prácticas_Snowballing'!$AB$2:$AB$281,"T001",'Prácticas_Snowballing'!$AC$2:$AC$281,"SOFTWARE ENG. ECONOMICS > *") -> 0 | Q6: =COUNTIFS('Prácticas_Revisiones'!$S$2:$S$282,"T001",'Prácticas_Revisiones'!$T$2:$T$282,"SOFTWARE ENG. MANAGEMENT > *")+COUNTIFS('Prácticas_Snowballing'!$AB$2:$AB$281,"T001",'Prácticas_Snowballing'!$AC$2:$AC$281,"SOFTWARE ENG. MANAGEMENT > *") -> 0 | R6: =COUNTIFS('Prácticas_Revisiones'!$S$2:$S$282,"T001",'Prácticas_Revisiones'!$T$2:$T$282,"Sin área SWEBOK")+COUNTIFS('Prácticas_Snowballing'!$AB$2:$AB$281,"T001",'Prácticas_Snowballing'!$AC$2:$AC$281,"Sin área SWEBOK") -> 1 | S6: =SUM(C6:R6) -> 7
B7: T002 Exegética | C7: =COUNTIFS('Prácticas_Revisiones'!$S$2:$S$282,"T002",'Prácticas_Revisiones'!$T$2:$T$282,"REQUIREMENTS > *")+COUNTIFS('Prácticas_Snowballing'!$AB$2:$AB$281,"T002",'Prácticas_Snowballing'!$AC$2:$AC$281,"REQUIREMENTS > *") -> 0 | D7: =COUNTIFS('Prácticas_Revisiones'!$S$2:$S$282,"T002",'Prácticas_Revisiones'!$T$2:$T$282,"ARCHITECTURE > *")+COUNTIFS('Prácticas_Snowballing'!$AB$2:$AB$281,"T002",'Prácticas_Snowballing'!$AC$2:$AC$281,"ARCHITECTURE > *") -> 0 | E7: =COUNTIFS('Prácticas_Revisiones'!$S$2:$S$282,"T002",'Prácticas_Revisiones'!$T$2:$T$282,"DESIGN > *")+COUNTIFS('Prácticas_Snowballing'!$AB$2:$AB$281,"T002",'Prácticas_Snowballing'!$AC$2:$AC$281,"DESIGN > *") -> 0 | F7: =COUNTIFS('Prácticas_Revisiones'!$S$2:$S$282,"T002",'Prácticas_Revisiones'!$T$2:$T$282,"CONSTRUCTION > *")+COUNTIFS('Prácticas_Snowballing'!$AB$2:$AB$281,"T002",'Prácticas_Snowballing'!$AC$2:$AC$281,"CONSTRUCTION > *") -> 0 | G7: =COUNTIFS('Prácticas_Revisiones'!$S$2:$S$282,"T002",'Prácticas_Revisiones'!$T$2:$T$282,"SOFTWARE TESTING > *")+COUNTIFS('Prácticas_Snowballing'!$AB$2:$AB$281,"T002",'Prácticas_Snowballing'!$AC$2:$AC$281,"SOFTWARE TESTING > *") -> 0 | H7: =COUNTIFS('Prácticas_Revisiones'!$S$2:$S$282,"T002",'Prácticas_Revisiones'!$T$2:$T$282,"SOFTWARE ENG. OPERATIONS > *")+COUNTIFS('Prácticas_Snowballing'!$AB$2:$AB$281,"T002",'Prácticas_Snowballing'!$AC$2:$AC$281,"SOFTWARE ENG. OPERATIONS > *") -> 0 | I7: =COUNTIFS('Prácticas_Revisiones'!$S$2:$S$282,"T002",'Prácticas_Revisiones'!$T$2:$T$282,"MAINTENANCE > *")+COUNTIFS('Prácticas_Snowballing'!$AB$2:$AB$281,"T002",'Prácticas_Snowballing'!$AC$2:$AC$281,"MAINTENANCE > *") -> 0 | J7: =COUNTIFS('Prácticas_Revisiones'!$S$2:$S$282,"T002",'Prácticas_Revisiones'!$T$2:$T$282,"SOFTWARE CONFIG. MGMT. > *")+COUNTIFS('Prácticas_Snowballing'!$AB$2:$AB$281,"T002",'Prácticas_Snowballing'!$AC$2:$AC$281,"SOFTWARE CONFIG. MGMT. > *") -> 0 | K7: =COUNTIFS('Prácticas_Revisiones'!$S$2:$S$282,"T002",'Prácticas_Revisiones'!$T$2:$T$282,"SOFTWARE ENG. PROCESS > *")+COUNTIFS('Prácticas_Snowballing'!$AB$2:$AB$281,"T002",'Prácticas_Snowballing'!$AC$2:$AC$281,"SOFTWARE ENG. PROCESS > *") -> 0 | L7: =COUNTIFS('Prácticas_Revisiones'!$S$2:$S$282,"T002",'Prácticas_Revisiones'!$T$2:$T$282,"SOFTWARE ENG. MODELS/METH. > *")+COUNTIFS('Prácticas_Snowballing'!$AB$2:$AB$281,"T002",'Prácticas_Snowballing'!$AC$2:$AC$281,"SOFTWARE ENG. MODELS/METH. > *") -> 0 | M7: =COUNTIFS('Prácticas_Revisiones'!$S$2:$S$282,"T002",'Prácticas_Revisiones'!$T$2:$T$282,"SOFTWARE QUALITY > *")+COUNTIFS('Prácticas_Snowballing'!$AB$2:$AB$281,"T002",'Prácticas_Snowballing'!$AC$2:$AC$281,"SOFTWARE QUALITY > *") -> 0 | N7: =COUNTIFS('Prácticas_Revisiones'!$S$2:$S$282,"T002",'Prácticas_Revisiones'!$T$2:$T$282,"SOFTWARE SECURITY > *")+COUNTIFS('Prácticas_Snowballing'!$AB$2:$AB$281,"T002",'Prácticas_Snowballing'!$AC$2:$AC$281,"SOFTWARE SECURITY > *") -> 0 | O7: =COUNTIFS('Prácticas_Revisiones'!$S$2:$S$282,"T002",'Prácticas_Revisiones'!$T$2:$T$282,"PROFESSIONAL PRACTICE > *")+COUNTIFS('Prácticas_Snowballing'!$AB$2:$AB$281,"T002",'Prácticas_Snowballing'!$AC$2:$AC$281,"PROFESSIONAL PRACTICE > *") -> 0 | P7: =COUNTIFS('Prácticas_Revisiones'!$S$2:$S$282,"T002",'Prácticas_Revisiones'!$T$2:$T$282,"SOFTWARE ENG. ECONOMICS > *")+COUNTIFS('Prácticas_Snowballing'!$AB$2:$AB$281,"T002",'Prácticas_Snowballing'!$AC$2:$AC$281,"SOFTWARE ENG. ECONOMICS > *") -> 0 | Q7: =COUNTIFS('Prácticas_Revisiones'!$S$2:$S$282,"T002",'Prácticas_Revisiones'!$T$2:$T$282,"SOFTWARE ENG. MANAGEMENT > *")+COUNTIFS('Prácticas_Snowballing'!$AB$2:$AB$281,"T002",'Prácticas_Snowballing'!$AC$2:$AC$281,"SOFTWARE ENG. MANAGEMENT > *") -> 0 | R7: =COUNTIFS('Prácticas_Revisiones'!$S$2:$S$282,"T002",'Prácticas_Revisiones'!$T$2:$T$282,"Sin área SWEBOK")+COUNTIFS('Prácticas_Snowballing'!$AB$2:$AB$281,"T002",'Prácticas_Snowballing'!$AC$2:$AC$281,"Sin área SWEBOK") -> 0 | S7: =SUM(C7:R7) -> 0
B8: T003 Fábula | C8: =COUNTIFS('Prácticas_Revisiones'!$S$2:$S$282,"T003",'Prácticas_Revisiones'!$T$2:$T$282,"REQUIREMENTS > *")+COUNTIFS('Prácticas_Snowballing'!$AB$2:$AB$281,"T003",'Prácticas_Snowballing'!$AC$2:$AC$281,"REQUIREMENTS > *") -> 0 | D8: =COUNTIFS('Prácticas_Revisiones'!$S$2:$S$282,"T003",'Prácticas_Revisiones'!$T$2:$T$282,"ARCHITECTURE > *")+COUNTIFS('Prácticas_Snowballing'!$AB$2:$AB$281,"T003",'Prácticas_Snowballing'!$AC$2:$AC$281,"ARCHITECTURE > *") -> 0 | E8: =COUNTIFS('Prácticas_Revisiones'!$S$2:$S$282,"T003",'Prácticas_Revisiones'!$T$2:$T$282,"DESIGN > *")+COUNTIFS('Prácticas_Snowballing'!$AB$2:$AB$281,"T003",'Prácticas_Snowballing'!$AC$2:$AC$281,"DESIGN > *") -> 0 | F8: =COUNTIFS('Prácticas_Revisiones'!$S$2:$S$282,"T003",'Prácticas_Revisiones'!$T$2:$T$282,"CONSTRUCTION > *")+COUNTIFS('Prácticas_Snowballing'!$AB$2:$AB$281,"T003",'Prácticas_Snowballing'!$AC$2:$AC$281,"CONSTRUCTION > *") -> 0 | G8: =COUNTIFS('Prácticas_Revisiones'!$S$2:$S$282,"T003",'Prácticas_Revisiones'!$T$2:$T$282,"SOFTWARE TESTING > *")+COUNTIFS('Prácticas_Snowballing'!$AB$2:$AB$281,"T003",'Prácticas_Snowballing'!$AC$2:$AC$281,"SOFTWARE TESTING > *") -> 0 | H8: =COUNTIFS('Prácticas_Revisiones'!$S$2:$S$282,"T003",'Prácticas_Revisiones'!$T$2:$T$282,"SOFTWARE ENG. OPERATIONS > *")+COUNTIFS('Prácticas_Snowballing'!$AB$2:$AB$281,"T003",'Prácticas_Snowballing'!$AC$2:$AC$281,"SOFTWARE ENG. OPERATIONS > *") -> 0 | I8: =COUNTIFS('Prácticas_Revisiones'!$S$2:$S$282,"T003",'Prácticas_Revisiones'!$T$2:$T$282,"MAINTENANCE > *")+COUNTIFS('Prácticas_Snowballing'!$AB$2:$AB$281,"T003",'Prácticas_Snowballing'!$AC$2:$AC$281,"MAINTENANCE > *") -> 0 | J8: =COUNTIFS('Prácticas_Revisiones'!$S$2:$S$282,"T003",'Prácticas_Revisiones'!$T$2:$T$282,"SOFTWARE CONFIG. MGMT. > *")+COUNTIFS('Prácticas_Snowballing'!$AB$2:$AB$281,"T003",'Prácticas_Snowballing'!$AC$2:$AC$281,"SOFTWARE CONFIG. MGMT. > *") -> 0 | K8: =COUNTIFS('Prácticas_Revisiones'!$S$2:$S$282,"T003",'Prácticas_Revisiones'!$T$2:$T$282,"SOFTWARE ENG. PROCESS > *")+COUNTIFS('Prácticas_Snowballing'!$AB$2:$AB$281,"T003",'Prácticas_Snowballing'!$AC$2:$AC$281,"SOFTWARE ENG. PROCESS > *") -> 0 | L8: =COUNTIFS('Prácticas_Revisiones'!$S$2:$S$282,"T003",'Prácticas_Revisiones'!$T$2:$T$282,"SOFTWARE ENG. MODELS/METH. > *")+COUNTIFS('Prácticas_Snowballing'!$AB$2:$AB$281,"T003",'Prácticas_Snowballing'!$AC$2:$AC$281,"SOFTWARE ENG. MODELS/METH. > *") -> 0 | M8: =COUNTIFS('Prácticas_Revisiones'!$S$2:$S$282,"T003",'Prácticas_Revisiones'!$T$2:$T$282,"SOFTWARE QUALITY > *")+COUNTIFS('Prácticas_Snowballing'!$AB$2:$AB$281,"T003",'Prácticas_Snowballing'!$AC$2:$AC$281,"SOFTWARE QUALITY > *") -> 0 | N8: =COUNTIFS('Prácticas_Revisiones'!$S$2:$S$282,"T003",'Prácticas_Revisiones'!$T$2:$T$282,"SOFTWARE SECURITY > *")+COUNTIFS('Prácticas_Snowballing'!$AB$2:$AB$281,"T003",'Prácticas_Snowballing'!$AC$2:$AC$281,"SOFTWARE SECURITY > *") -> 0 | O8: =COUNTIFS('Prácticas_Revisiones'!$S$2:$S$282,"T003",'Prácticas_Revisiones'!$T$2:$T$282,"PROFESSIONAL PRACTICE > *")+COUNTIFS('Prácticas_Snowballing'!$AB$2:$AB$281,"T003",'Prácticas_Snowballing'!$AC$2:$AC$281,"PROFESSIONAL PRACTICE > *") -> 0 | P8: =COUNTIFS('Prácticas_Revisiones'!$S$2:$S$282,"T003",'Prácticas_Revisiones'!$T$2:$T$282,"SOFTWARE ENG. ECONOMICS > *")+COUNTIFS('Prácticas_Snowballing'!$AB$2:$AB$281,"T003",'Prácticas_Snowballing'!$AC$2:$AC$281,"SOFTWARE ENG. ECONOMICS > *") -> 0 | Q8: =COUNTIFS('Prácticas_Revisiones'!$S$2:$S$282,"T003",'Prácticas_Revisiones'!$T$2:$T$282,"SOFTWARE ENG. MANAGEMENT > *")+COUNTIFS('Prácticas_Snowballing'!$AB$2:$AB$281,"T003",'Prácticas_Snowballing'!$AC$2:$AC$281,"SOFTWARE ENG. MANAGEMENT > *") -> 0 | R8: =COUNTIFS('Prácticas_Revisiones'!$S$2:$S$282,"T003",'Prácticas_Revisiones'!$T$2:$T$282,"Sin área SWEBOK")+COUNTIFS('Prácticas_Snowballing'!$AB$2:$AB$281,"T003",'Prácticas_Snowballing'!$AC$2:$AC$281,"Sin área SWEBOK") -> 0 | S8: =SUM(C8:R8) -> 0
B9: T004 Mapa mental | C9: =COUNTIFS('Prácticas_Revisiones'!$S$2:$S$282,"T004",'Prácticas_Revisiones'!$T$2:$T$282,"REQUIREMENTS > *")+COUNTIFS('Prácticas_Snowballing'!$AB$2:$AB$281,"T004",'Prácticas_Snowballing'!$AC$2:$AC$281,"REQUIREMENTS > *") -> 0 | D9: =COUNTIFS('Prácticas_Revisiones'!$S$2:$S$282,"T004",'Prácticas_Revisiones'!$T$2:$T$282,"ARCHITECTURE > *")+COUNTIFS('Prácticas_Snowballing'!$AB$2:$AB$281,"T004",'Prácticas_Snowballing'!$AC$2:$AC$281,"ARCHITECTURE > *") -> 0 | E9: =COUNTIFS('Prácticas_Revisiones'!$S$2:$S$282,"T004",'Prácticas_Revisiones'!$T$2:$T$282,"DESIGN > *")+COUNTIFS('Prácticas_Snowballing'!$AB$2:$AB$281,"T004",'Prácticas_Snowballing'!$AC$2:$AC$281,"DESIGN > *") -> 0 | F9: =COUNTIFS('Prácticas_Revisiones'!$S$2:$S$282,"T004",'Prácticas_Revisiones'!$T$2:$T$282,"CONSTRUCTION > *")+COUNTIFS('Prácticas_Snowballing'!$AB$2:$AB$281,"T004",'Prácticas_Snowballing'!$AC$2:$AC$281,"CONSTRUCTION > *") -> 2 | G9: =COUNTIFS('Prácticas_Revisiones'!$S$2:$S$282,"T004",'Prácticas_Revisiones'!$T$2:$T$282,"SOFTWARE TESTING > *")+COUNTIFS('Prácticas_Snowballing'!$AB$2:$AB$281,"T004",'Prácticas_Snowballing'!$AC$2:$AC$281,"SOFTWARE TESTING > *") -> 0 | H9: =COUNTIFS('Prácticas_Revisiones'!$S$2:$S$282,"T004",'Prácticas_Revisiones'!$T$2:$T$282,"SOFTWARE ENG. OPERATIONS > *")+COUNTIFS('Prácticas_Snowballing'!$AB$2:$AB$281,"T004",'Prácticas_Snowballing'!$AC$2:$AC$281,"SOFTWARE ENG. OPERATIONS > *") -> 0 | I9: =COUNTIFS('Prácticas_Revisiones'!$S$2:$S$282,"T004",'Prácticas_Revisiones'!$T$2:$T$282,"MAINTENANCE > *")+COUNTIFS('Prácticas_Snowballing'!$AB$2:$AB$281,"T004",'Prácticas_Snowballing'!$AC$2:$AC$281,"MAINTENANCE > *") -> 0 | J9: =COUNTIFS('Prácticas_Revisiones'!$S$2:$S$282,"T004",'Prácticas_Revisiones'!$T$2:$T$282,"SOFTWARE CONFIG. MGMT. > *")+COUNTIFS('Prácticas_Snowballing'!$AB$2:$AB$281,"T004",'Prácticas_Snowballing'!$AC$2:$AC$281,"SOFTWARE CONFIG. MGMT. > *") -> 0 | K9: =COUNTIFS('Prácticas_Revisiones'!$S$2:$S$282,"T004",'Prácticas_Revisiones'!$T$2:$T$282,"SOFTWARE ENG. PROCESS > *")+COUNTIFS('Prácticas_Snowballing'!$AB$2:$AB$281,"T004",'Prácticas_Snowballing'!$AC$2:$AC$281,"SOFTWARE ENG. PROCESS > *") -> 0 | L9: =COUNTIFS('Prácticas_Revisiones'!$S$2:$S$282,"T004",'Prácticas_Revisiones'!$T$2:$T$282,"SOFTWARE ENG. MODELS/METH. > *")+COUNTIFS('Prácticas_Snowballing'!$AB$2:$AB$281,"T004",'Prácticas_Snowballing'!$AC$2:$AC$281,"SOFTWARE ENG. MODELS/METH. > *") -> 0 | M9: =COUNTIFS('Prácticas_Revisiones'!$S$2:$S$282,"T004",'Prácticas_Revisiones'!$T$2:$T$282,"SOFTWARE QUALITY > *")+COUNTIFS('Prácticas_Snowballing'!$AB$2:$AB$281,"T004",'Prácticas_Snowballing'!$AC$2:$AC$281,"SOFTWARE QUALITY > *") -> 0 | N9: =COUNTIFS('Prácticas_Revisiones'!$S$2:$S$282,"T004",'Prácticas_Revisiones'!$T$2:$T$282,"SOFTWARE SECURITY > *")+COUNTIFS('Prácticas_Snowballing'!$AB$2:$AB$281,"T004",'Prácticas_Snowballing'!$AC$2:$AC$281,"SOFTWARE SECURITY > *") -> 0 | O9: =COUNTIFS('Prácticas_Revisiones'!$S$2:$S$282,"T004",'Prácticas_Revisiones'!$T$2:$T$282,"PROFESSIONAL PRACTICE > *")+COUNTIFS('Prácticas_Snowballing'!$AB$2:$AB$281,"T004",'Prácticas_Snowballing'!$AC$2:$AC$281,"PROFESSIONAL PRACTICE > *") -> 0 | P9: =COUNTIFS('Prácticas_Revisiones'!$S$2:$S$282,"T004",'Prácticas_Revisiones'!$T$2:$T$282,"SOFTWARE ENG. ECONOMICS > *")+COUNTIFS('Prácticas_Snowballing'!$AB$2:$AB$281,"T004",'Prácticas_Snowballing'!$AC$2:$AC$281,"SOFTWARE ENG. ECONOMICS > *") -> 0 | Q9: =COUNTIFS('Prácticas_Revisiones'!$S$2:$S$282,"T004",'Prácticas_Revisiones'!$T$2:$T$282,"SOFTWARE ENG. MANAGEMENT > *")+COUNTIFS('Prácticas_Snowballing'!$AB$2:$AB$281,"T004",'Prácticas_Snowballing'!$AC$2:$AC$281,"SOFTWARE ENG. MANAGEMENT > *") -> 0 | R9: =COUNTIFS('Prácticas_Revisiones'!$S$2:$S$282,"T004",'Prácticas_Revisiones'!$T$2:$T$282,"Sin área SWEBOK")+COUNTIFS('Prácticas_Snowballing'!$AB$2:$AB$281,"T004",'Prácticas_Snowballing'!$AC$2:$AC$281,"Sin área SWEBOK") -> 0 | S9: =SUM(C9:R9) -> 2
B10: T005 Mnemotecnia | C10: =COUNTIFS('Prácticas_Revisiones'!$S$2:$S$282,"T005",'Prácticas_Revisiones'!$T$2:$T$282,"REQUIREMENTS > *")+COUNTIFS('Prácticas_Snowballing'!$AB$2:$AB$281,"T005",'Prácticas_Snowballing'!$AC$2:$AC$281,"REQUIREMENTS > *") -> 0 | D10: =COUNTIFS('Prácticas_Revisiones'!$S$2:$S$282,"T005",'Prácticas_Revisiones'!$T$2:$T$282,"ARCHITECTURE > *")+COUNTIFS('Prácticas_Snowballing'!$AB$2:$AB$281,"T005",'Prácticas_Snowballing'!$AC$2:$AC$281,"ARCHITECTURE > *") -> 0 | E10: =COUNTIFS('Prácticas_Revisiones'!$S$2:$S$282,"T005",'Prácticas_Revisiones'!$T$2:$T$282,"DESIGN > *")+COUNTIFS('Prácticas_Snowballing'!$AB$2:$AB$281,"T005",'Prácticas_Snowballing'!$AC$2:$AC$281,"DESIGN > *") -> 0 | F10: =COUNTIFS('Prácticas_Revisiones'!$S$2:$S$282,"T005",'Prácticas_Revisiones'!$T$2:$T$282,"CONSTRUCTION > *")+COUNTIFS('Prácticas_Snowballing'!$AB$2:$AB$281,"T005",'Prácticas_Snowballing'!$AC$2:$AC$281,"CONSTRUCTION > *") -> 0 | G10: =COUNTIFS('Prácticas_Revisiones'!$S$2:$S$282,"T005",'Prácticas_Revisiones'!$T$2:$T$282,"SOFTWARE TESTING > *")+COUNTIFS('Prácticas_Snowballing'!$AB$2:$AB$281,"T005",'Prácticas_Snowballing'!$AC$2:$AC$281,"SOFTWARE TESTING > *") -> 0 | H10: =COUNTIFS('Prácticas_Revisiones'!$S$2:$S$282,"T005",'Prácticas_Revisiones'!$T$2:$T$282,"SOFTWARE ENG. OPERATIONS > *")+COUNTIFS('Prácticas_Snowballing'!$AB$2:$AB$281,"T005",'Prácticas_Snowballing'!$AC$2:$AC$281,"SOFTWARE ENG. OPERATIONS > *") -> 0 | I10: =COUNTIFS('Prácticas_Revisiones'!$S$2:$S$282,"T005",'Prácticas_Revisiones'!$T$2:$T$282,"MAINTENANCE > *")+COUNTIFS('Prácticas_Snowballing'!$AB$2:$AB$281,"T005",'Prácticas_Snowballing'!$AC$2:$AC$281,"MAINTENANCE > *") -> 0 | J10: =COUNTIFS('Prácticas_Revisiones'!$S$2:$S$282,"T005",'Prácticas_Revisiones'!$T$2:$T$282,"SOFTWARE CONFIG. MGMT. > *")+COUNTIFS('Prácticas_Snowballing'!$AB$2:$AB$281,"T005",'Prácticas_Snowballing'!$AC$2:$AC$281,"SOFTWARE CONFIG. MGMT. > *") -> 0 | K10: =COUNTIFS('Prácticas_Revisiones'!$S$2:$S$282,"T005",'Prácticas_Revisiones'!$T$2:$T$282,"SOFTWARE ENG. PROCESS > *")+COUNTIFS('Prácticas_Snowballing'!$AB$2:$AB$281,"T005",'Prácticas_Snowballing'!$AC$2:$AC$281,"SOFTWARE ENG. PROCESS > *") -> 0 | L10: =COUNTIFS('Prácticas_Revisiones'!$S$2:$S$282,"T005",'Prácticas_Revisiones'!$T$2:$T$282,"SOFTWARE ENG. MODELS/METH. > *")+COUNTIFS('Prácticas_Snowballing'!$AB$2:$AB$281,"T005",'Prácticas_Snowballing'!$AC$2:$AC$281,"SOFTWARE ENG. MODELS/METH. > *") -> 0 | M10: =COUNTIFS('Prácticas_Revisiones'!$S$2:$S$282,"T005",'Prácticas_Revisiones'!$T$2:$T$282,"SOFTWARE QUALITY > *")+COUNTIFS('Prácticas_Snowballing'!$AB$2:$AB$281,"T005",'Prácticas_Snowballing'!$AC$2:$AC$281,"SOFTWARE QUALITY > *") -> 0 | N10: =COUNTIFS('Prácticas_Revisiones'!$S$2:$S$282,"T005",'Prácticas_Revisiones'!$T$2:$T$282,"SOFTWARE SECURITY > *")+COUNTIFS('Prácticas_Snowballing'!$AB$2:$AB$281,"T005",'Prácticas_Snowballing'!$AC$2:$AC$281,"SOFTWARE SECURITY > *") -> 0 | O10: =COUNTIFS('Prácticas_Revisiones'!$S$2:$S$282,"T005",'Prácticas_Revisiones'!$T$2:$T$282,"PROFESSIONAL PRACTICE > *")+COUNTIFS('Prácticas_Snowballing'!$AB$2:$AB$281,"T005",'Prácticas_Snowballing'!$AC$2:$AC$281,"PROFESSIONAL PRACTICE > *") -> 0 | P10: =COUNTIFS('Prácticas_Revisiones'!$S$2:$S$282,"T005",'Prácticas_Revisiones'!$T$2:$T$282,"SOFTWARE ENG. ECONOMICS > *")+COUNTIFS('Prácticas_Snowballing'!$AB$2:$AB$281,"T005",'Prácticas_Snowballing'!$AC$2:$AC$281,"SOFTWARE ENG. ECONOMICS > *") -> 0 | Q10: =COUNTIFS('Prácticas_Revisiones'!$S$2:$S$282,"T005",'Prácticas_Revisiones'!$T$2:$T$282,"SOFTWARE ENG. MANAGEMENT > *")+COUNTIFS('Prácticas_Snowballing'!$AB$2:$AB$281,"T005",'Prácticas_Snowballing'!$AC$2:$AC$281,"SOFTWARE ENG. MANAGEMENT > *") -> 0 | R10: =COUNTIFS('Prácticas_Revisiones'!$S$2:$S$282,"T005",'Prácticas_Revisiones'!$T$2:$T$282,"Sin área SWEBOK")+COUNTIFS('Prácticas_Snowballing'!$AB$2:$AB$281,"T005",'Prácticas_Snowballing'!$AC$2:$AC$281,"Sin área SWEBOK") -> 0 | S10: =SUM(C10:R10) -> 0
B11: T006 Pensamiento de diseño | C11: =COUNTIFS('Prácticas_Revisiones'!$S$2:$S$282,"T006",'Prácticas_Revisiones'!$T$2:$T$282,"REQUIREMENTS > *")+COUNTIFS('Prácticas_Snowballing'!$AB$2:$AB$281,"T006",'Prácticas_Snowballing'!$AC$2:$AC$281,"REQUIREMENTS > *") -> 0 | D11: =COUNTIFS('Prácticas_Revisiones'!$S$2:$S$282,"T006",'Prácticas_Revisiones'!$T$2:$T$282,"ARCHITECTURE > *")+COUNTIFS('Prácticas_Snowballing'!$AB$2:$AB$281,"T006",'Prácticas_Snowballing'!$AC$2:$AC$281,"ARCHITECTURE > *") -> 0 | E11: =COUNTIFS('Prácticas_Revisiones'!$S$2:$S$282,"T006",'Prácticas_Revisiones'!$T$2:$T$282,"DESIGN > *")+COUNTIFS('Prácticas_Snowballing'!$AB$2:$AB$281,"T006",'Prácticas_Snowballing'!$AC$2:$AC$281,"DESIGN > *") -> 1 | F11: =COUNTIFS('Prácticas_Revisiones'!$S$2:$S$282,"T006",'Prácticas_Revisiones'!$T$2:$T$282,"CONSTRUCTION > *")+COUNTIFS('Prácticas_Snowballing'!$AB$2:$AB$281,"T006",'Prácticas_Snowballing'!$AC$2:$AC$281,"CONSTRUCTION > *") -> 0 | G11: =COUNTIFS('Prácticas_Revisiones'!$S$2:$S$282,"T006",'Prácticas_Revisiones'!$T$2:$T$282,"SOFTWARE TESTING > *")+COUNTIFS('Prácticas_Snowballing'!$AB$2:$AB$281,"T006",'Prácticas_Snowballing'!$AC$2:$AC$281,"SOFTWARE TESTING > *") -> 0 | H11: =COUNTIFS('Prácticas_Revisiones'!$S$2:$S$282,"T006",'Prácticas_Revisiones'!$T$2:$T$282,"SOFTWARE ENG. OPERATIONS > *")+COUNTIFS('Prácticas_Snowballing'!$AB$2:$AB$281,"T006",'Prácticas_Snowballing'!$AC$2:$AC$281,"SOFTWARE ENG. OPERATIONS > *") -> 0 | I11: =COUNTIFS('Prácticas_Revisiones'!$S$2:$S$282,"T006",'Prácticas_Revisiones'!$T$2:$T$282,"MAINTENANCE > *")+COUNTIFS('Prácticas_Snowballing'!$AB$2:$AB$281,"T006",'Prácticas_Snowballing'!$AC$2:$AC$281,"MAINTENANCE > *") -> 0 | J11: =COUNTIFS('Prácticas_Revisiones'!$S$2:$S$282,"T006",'Prácticas_Revisiones'!$T$2:$T$282,"SOFTWARE CONFIG. MGMT. > *")+COUNTIFS('Prácticas_Snowballing'!$AB$2:$AB$281,"T006",'Prácticas_Snowballing'!$AC$2:$AC$281,"SOFTWARE CONFIG. MGMT. > *") -> 0 | K11: =COUNTIFS('Prácticas_Revisiones'!$S$2:$S$282,"T006",'Prácticas_Revisiones'!$T$2:$T$282,"SOFTWARE ENG. PROCESS > *")+COUNTIFS('Prácticas_Snowballing'!$AB$2:$AB$281,"T006",'Prácticas_Snowballing'!$AC$2:$AC$281,"SOFTWARE ENG. PROCESS > *") -> 0 | L11: =COUNTIFS('Prácticas_Revisiones'!$S$2:$S$282,"T006",'Prácticas_Revisiones'!$T$2:$T$282,"SOFTWARE ENG. MODELS/METH. > *")+COUNTIFS('Prácticas_Snowballing'!$AB$2:$AB$281,"T006",'Prácticas_Snowballing'!$AC$2:$AC$281,"SOFTWARE ENG. MODELS/METH. > *") -> 0 | M11: =COUNTIFS('Prácticas_Revisiones'!$S$2:$S$282,"T006",'Prácticas_Revisiones'!$T$2:$T$282,"SOFTWARE QUALITY > *")+COUNTIFS('Prácticas_Snowballing'!$AB$2:$AB$281,"T006",'Prácticas_Snowballing'!$AC$2:$AC$281,"SOFTWARE QUALITY > *") -> 0 | N11: =COUNTIFS('Prácticas_Revisiones'!$S$2:$S$282,"T006",'Prácticas_Revisiones'!$T$2:$T$282,"SOFTWARE SECURITY > *")+COUNTIFS('Prácticas_Snowballing'!$AB$2:$AB$281,"T006",'Prácticas_Snowballing'!$AC$2:$AC$281,"SOFTWARE SECURITY > *") -> 0 | O11: =COUNTIFS('Prácticas_Revisiones'!$S$2:$S$282,"T006",'Prácticas_Revisiones'!$T$2:$T$282,"PROFESSIONAL PRACTICE > *")+COUNTIFS('Prácticas_Snowballing'!$AB$2:$AB$281,"T006",'Prácticas_Snowballing'!$AC$2:$AC$281,"PROFESSIONAL PRACTICE > *") -> 0 | P11: =COUNTIFS('Prácticas_Revisiones'!$S$2:$S$282,"T006",'Prácticas_Revisiones'!$T$2:$T$282,"SOFTWARE ENG. ECONOMICS > *")+COUNTIFS('Prácticas_Snowballing'!$AB$2:$AB$281,"T006",'Prácticas_Snowballing'!$AC$2:$AC$281,"SOFTWARE ENG. ECONOMICS > *") -> 0 | Q11: =COUNTIFS('Prácticas_Revisiones'!$S$2:$S$282,"T006",'Prácticas_Revisiones'!$T$2:$T$282,"SOFTWARE ENG. MANAGEMENT > *")+COUNTIFS('Prácticas_Snowballing'!$AB$2:$AB$281,"T006",'Prácticas_Snowballing'!$AC$2:$AC$281,"SOFTWARE ENG. MANAGEMENT > *") -> 0 | R11: =COUNTIFS('Prácticas_Revisiones'!$S$2:$S$282,"T006",'Prácticas_Revisiones'!$T$2:$T$282,"Sin área SWEBOK")+COUNTIFS('Prácticas_Snowballing'!$AB$2:$AB$281,"T006",'Prácticas_Snowballing'!$AC$2:$AC$281,"Sin área SWEBOK") -> 0 | S11: =SUM(C11:R11) -> 1
B12: T007 Preguntas y premios | C12: =COUNTIFS('Prácticas_Revisiones'!$S$2:$S$282,"T007",'Prácticas_Revisiones'!$T$2:$T$282,"REQUIREMENTS > *")+COUNTIFS('Prácticas_Snowballing'!$AB$2:$AB$281,"T007",'Prácticas_Snowballing'!$AC$2:$AC$281,"REQUIREMENTS > *") -> 0 | D12: =COUNTIFS('Prácticas_Revisiones'!$S$2:$S$282,"T007",'Prácticas_Revisiones'!$T$2:$T$282,"ARCHITECTURE > *")+COUNTIFS('Prácticas_Snowballing'!$AB$2:$AB$281,"T007",'Prácticas_Snowballing'!$AC$2:$AC$281,"ARCHITECTURE > *") -> 0 | E12: =COUNTIFS('Prácticas_Revisiones'!$S$2:$S$282,"T007",'Prácticas_Revisiones'!$T$2:$T$282,"DESIGN > *")+COUNTIFS('Prácticas_Snowballing'!$AB$2:$AB$281,"T007",'Prácticas_Snowballing'!$AC$2:$AC$281,"DESIGN > *") -> 0 | F12: =COUNTIFS('Prácticas_Revisiones'!$S$2:$S$282,"T007",'Prácticas_Revisiones'!$T$2:$T$282,"CONSTRUCTION > *")+COUNTIFS('Prácticas_Snowballing'!$AB$2:$AB$281,"T007",'Prácticas_Snowballing'!$AC$2:$AC$281,"CONSTRUCTION > *") -> 1 | G12: =COUNTIFS('Prácticas_Revisiones'!$S$2:$S$282,"T007",'Prácticas_Revisiones'!$T$2:$T$282,"SOFTWARE TESTING > *")+COUNTIFS('Prácticas_Snowballing'!$AB$2:$AB$281,"T007",'Prácticas_Snowballing'!$AC$2:$AC$281,"SOFTWARE TESTING > *") -> 0 | H12: =COUNTIFS('Prácticas_Revisiones'!$S$2:$S$282,"T007",'Prácticas_Revisiones'!$T$2:$T$282,"SOFTWARE ENG. OPERATIONS > *")+COUNTIFS('Prácticas_Snowballing'!$AB$2:$AB$281,"T007",'Prácticas_Snowballing'!$AC$2:$AC$281,"SOFTWARE ENG. OPERATIONS > *") -> 0 | I12: =COUNTIFS('Prácticas_Revisiones'!$S$2:$S$282,"T007",'Prácticas_Revisiones'!$T$2:$T$282,"MAINTENANCE > *")+COUNTIFS('Prácticas_Snowballing'!$AB$2:$AB$281,"T007",'Prácticas_Snowballing'!$AC$2:$AC$281,"MAINTENANCE > *") -> 0 | J12: =COUNTIFS('Prácticas_Revisiones'!$S$2:$S$282,"T007",'Prácticas_Revisiones'!$T$2:$T$282,"SOFTWARE CONFIG. MGMT. > *")+COUNTIFS('Prácticas_Snowballing'!$AB$2:$AB$281,"T007",'Prácticas_Snowballing'!$AC$2:$AC$281,"SOFTWARE CONFIG. MGMT. > *") -> 0 | K12: =COUNTIFS('Prácticas_Revisiones'!$S$2:$S$282,"T007",'Prácticas_Revisiones'!$T$2:$T$282,"SOFTWARE ENG. PROCESS > *")+COUNTIFS('Prácticas_Snowballing'!$AB$2:$AB$281,"T007",'Prácticas_Snowballing'!$AC$2:$AC$281,"SOFTWARE ENG. PROCESS > *") -> 0 | L12: =COUNTIFS('Prácticas_Revisiones'!$S$2:$S$282,"T007",'Prácticas_Revisiones'!$T$2:$T$282,"SOFTWARE ENG. MODELS/METH. > *")+COUNTIFS('Prácticas_Snowballing'!$AB$2:$AB$281,"T007",'Prácticas_Snowballing'!$AC$2:$AC$281,"SOFTWARE ENG. MODELS/METH. > *") -> 0 | M12: =COUNTIFS('Prácticas_Revisiones'!$S$2:$S$282,"T007",'Prácticas_Revisiones'!$T$2:$T$282,"SOFTWARE QUALITY > *")+COUNTIFS('Prácticas_Snowballing'!$AB$2:$AB$281,"T007",'Prácticas_Snowballing'!$AC$2:$AC$281,"SOFTWARE QUALITY > *") -> 0 | N12: =COUNTIFS('Prácticas_Revisiones'!$S$2:$S$282,"T007",'Prácticas_Revisiones'!$T$2:$T$282,"SOFTWARE SECURITY > *")+COUNTIFS('Prácticas_Snowballing'!$AB$2:$AB$281,"T007",'Prácticas_Snowballing'!$AC$2:$AC$281,"SOFTWARE SECURITY > *") -> 0 | O12: =COUNTIFS('Prácticas_Revisiones'!$S$2:$S$282,"T007",'Prácticas_Revisiones'!$T$2:$T$282,"PROFESSIONAL PRACTICE > *")+COUNTIFS('Prácticas_Snowballing'!$AB$2:$AB$281,"T007",'Prácticas_Snowballing'!$AC$2:$AC$281,"PROFESSIONAL PRACTICE > *") -> 0 | P12: =COUNTIFS('Prácticas_Revisiones'!$S$2:$S$282,"T007",'Prácticas_Revisiones'!$T$2:$T$282,"SOFTWARE ENG. ECONOMICS > *")+COUNTIFS('Prácticas_Snowballing'!$AB$2:$AB$281,"T007",'Prácticas_Snowballing'!$AC$2:$AC$281,"SOFTWARE ENG. ECONOMICS > *") -> 0 | Q12: =COUNTIFS('Prácticas_Revisiones'!$S$2:$S$282,"T007",'Prácticas_Revisiones'!$T$2:$T$282,"SOFTWARE ENG. MANAGEMENT > *")+COUNTIFS('Prácticas_Snowballing'!$AB$2:$AB$281,"T007",'Prácticas_Snowballing'!$AC$2:$AC$281,"SOFTWARE ENG. MANAGEMENT > *") -> 0 | R12: =COUNTIFS('Prácticas_Revisiones'!$S$2:$S$282,"T007",'Prácticas_Revisiones'!$T$2:$T$282,"Sin área SWEBOK")+COUNTIFS('Prácticas_Snowballing'!$AB$2:$AB$281,"T007",'Prácticas_Snowballing'!$AC$2:$AC$281,"Sin área SWEBOK") -> 0 | S12: =SUM(C12:R12) -> 1
B13: T008 Resumen | C13: =COUNTIFS('Prácticas_Revisiones'!$S$2:$S$282,"T008",'Prácticas_Revisiones'!$T$2:$T$282,"REQUIREMENTS > *")+COUNTIFS('Prácticas_Snowballing'!$AB$2:$AB$281,"T008",'Prácticas_Snowballing'!$AC$2:$AC$281,"REQUIREMENTS > *") -> 0 | D13: =COUNTIFS('Prácticas_Revisiones'!$S$2:$S$282,"T008",'Prácticas_Revisiones'!$T$2:$T$282,"ARCHITECTURE > *")+COUNTIFS('Prácticas_Snowballing'!$AB$2:$AB$281,"T008",'Prácticas_Snowballing'!$AC$2:$AC$281,"ARCHITECTURE > *") -> 0 | E13: =COUNTIFS('Prácticas_Revisiones'!$S$2:$S$282,"T008",'Prácticas_Revisiones'!$T$2:$T$282,"DESIGN > *")+COUNTIFS('Prácticas_Snowballing'!$AB$2:$AB$281,"T008",'Prácticas_Snowballing'!$AC$2:$AC$281,"DESIGN > *") -> 0 | F13: =COUNTIFS('Prácticas_Revisiones'!$S$2:$S$282,"T008",'Prácticas_Revisiones'!$T$2:$T$282,"CONSTRUCTION > *")+COUNTIFS('Prácticas_Snowballing'!$AB$2:$AB$281,"T008",'Prácticas_Snowballing'!$AC$2:$AC$281,"CONSTRUCTION > *") -> 1 | G13: =COUNTIFS('Prácticas_Revisiones'!$S$2:$S$282,"T008",'Prácticas_Revisiones'!$T$2:$T$282,"SOFTWARE TESTING > *")+COUNTIFS('Prácticas_Snowballing'!$AB$2:$AB$281,"T008",'Prácticas_Snowballing'!$AC$2:$AC$281,"SOFTWARE TESTING > *") -> 0 | H13: =COUNTIFS('Prácticas_Revisiones'!$S$2:$S$282,"T008",'Prácticas_Revisiones'!$T$2:$T$282,"SOFTWARE ENG. OPERATIONS > *")+COUNTIFS('Prácticas_Snowballing'!$AB$2:$AB$281,"T008",'Prácticas_Snowballing'!$AC$2:$AC$281,"SOFTWARE ENG. OPERATIONS > *") -> 0 | I13: =COUNTIFS('Prácticas_Revisiones'!$S$2:$S$282,"T008",'Prácticas_Revisiones'!$T$2:$T$282,"MAINTENANCE > *")+COUNTIFS('Prácticas_Snowballing'!$AB$2:$AB$281,"T008",'Prácticas_Snowballing'!$AC$2:$AC$281,"MAINTENANCE > *") -> 0 | J13: =COUNTIFS('Prácticas_Revisiones'!$S$2:$S$282,"T008",'Prácticas_Revisiones'!$T$2:$T$282,"SOFTWARE CONFIG. MGMT. > *")+COUNTIFS('Prácticas_Snowballing'!$AB$2:$AB$281,"T008",'Prácticas_Snowballing'!$AC$2:$AC$281,"SOFTWARE CONFIG. MGMT. > *") -> 0 | K13: =COUNTIFS('Prácticas_Revisiones'!$S$2:$S$282,"T008",'Prácticas_Revisiones'!$T$2:$T$282,"SOFTWARE ENG. PROCESS > *")+COUNTIFS('Prácticas_Snowballing'!$AB$2:$AB$281,"T008",'Prácticas_Snowballing'!$AC$2:$AC$281,"SOFTWARE ENG. PROCESS > *") -> 0 | L13: =COUNTIFS('Prácticas_Revisiones'!$S$2:$S$282,"T008",'Prácticas_Revisiones'!$T$2:$T$282,"SOFTWARE ENG. MODELS/METH. > *")+COUNTIFS('Prácticas_Snowballing'!$AB$2:$AB$281,"T008",'Prácticas_Snowballing'!$AC$2:$AC$281,"SOFTWARE ENG. MODELS/METH. > *") -> 0 | M13: =COUNTIFS('Prácticas_Revisiones'!$S$2:$S$282,"T008",'Prácticas_Revisiones'!$T$2:$T$282,"SOFTWARE QUALITY > *")+COUNTIFS('Prácticas_Snowballing'!$AB$2:$AB$281,"T008",'Prácticas_Snowballing'!$AC$2:$AC$281,"SOFTWARE QUALITY > *") -> 0 | N13: =COUNTIFS('Prácticas_Revisiones'!$S$2:$S$282,"T008",'Prácticas_Revisiones'!$T$2:$T$282,"SOFTWARE SECURITY > *")+COUNTIFS('Prácticas_Snowballing'!$AB$2:$AB$281,"T008",'Prácticas_Snowballing'!$AC$2:$AC$281,"SOFTWARE SECURITY > *") -> 0 | O13: =COUNTIFS('Prácticas_Revisiones'!$S$2:$S$282,"T008",'Prácticas_Revisiones'!$T$2:$T$282,"PROFESSIONAL PRACTICE > *")+COUNTIFS('Prácticas_Snowballing'!$AB$2:$AB$281,"T008",'Prácticas_Snowballing'!$AC$2:$AC$281,"PROFESSIONAL PRACTICE > *") -> 0 | P13: =COUNTIFS('Prácticas_Revisiones'!$S$2:$S$282,"T008",'Prácticas_Revisiones'!$T$2:$T$282,"SOFTWARE ENG. ECONOMICS > *")+COUNTIFS('Prácticas_Snowballing'!$AB$2:$AB$281,"T008",'Prácticas_Snowballing'!$AC$2:$AC$281,"SOFTWARE ENG. ECONOMICS > *") -> 0 | Q13: =COUNTIFS('Prácticas_Revisiones'!$S$2:$S$282,"T008",'Prácticas_Revisiones'!$T$2:$T$282,"SOFTWARE ENG. MANAGEMENT > *")+COUNTIFS('Prácticas_Snowballing'!$AB$2:$AB$281,"T008",'Prácticas_Snowballing'!$AC$2:$AC$281,"SOFTWARE ENG. MANAGEMENT > *") -> 0 | R13: =COUNTIFS('Prácticas_Revisiones'!$S$2:$S$282,"T008",'Prácticas_Revisiones'!$T$2:$T$282,"Sin área SWEBOK")+COUNTIFS('Prácticas_Snowballing'!$AB$2:$AB$281,"T008",'Prácticas_Snowballing'!$AC$2:$AC$281,"Sin área SWEBOK") -> 1 | S13: =SUM(C13:R13) -> 2
B14: T009 SCAMPER | C14: =COUNTIFS('Prácticas_Revisiones'!$S$2:$S$282,"T009",'Prácticas_Revisiones'!$T$2:$T$282,"REQUIREMENTS > *")+COUNTIFS('Prácticas_Snowballing'!$AB$2:$AB$281,"T009",'Prácticas_Snowballing'!$AC$2:$AC$281,"REQUIREMENTS > *") -> 0 | D14: =COUNTIFS('Prácticas_Revisiones'!$S$2:$S$282,"T009",'Prácticas_Revisiones'!$T$2:$T$282,"ARCHITECTURE > *")+COUNTIFS('Prácticas_Snowballing'!$AB$2:$AB$281,"T009",'Prácticas_Snowballing'!$AC$2:$AC$281,"ARCHITECTURE > *") -> 0 | E14: =COUNTIFS('Prácticas_Revisiones'!$S$2:$S$282,"T009",'Prácticas_Revisiones'!$T$2:$T$282,"DESIGN > *")+COUNTIFS('Prácticas_Snowballing'!$AB$2:$AB$281,"T009",'Prácticas_Snowballing'!$AC$2:$AC$281,"DESIGN > *") -> 0 | F14: =COUNTIFS('Prácticas_Revisiones'!$S$2:$S$282,"T009",'Prácticas_Revisiones'!$T$2:$T$282,"CONSTRUCTION > *")+COUNTIFS('Prácticas_Snowballing'!$AB$2:$AB$281,"T009",'Prácticas_Snowballing'!$AC$2:$AC$281,"CONSTRUCTION > *") -> 1 | G14: =COUNTIFS('Prácticas_Revisiones'!$S$2:$S$282,"T009",'Prácticas_Revisiones'!$T$2:$T$282,"SOFTWARE TESTING > *")+COUNTIFS('Prácticas_Snowballing'!$AB$2:$AB$281,"T009",'Prácticas_Snowballing'!$AC$2:$AC$281,"SOFTWARE TESTING > *") -> 0 | H14: =COUNTIFS('Prácticas_Revisiones'!$S$2:$S$282,"T009",'Prácticas_Revisiones'!$T$2:$T$282,"SOFTWARE ENG. OPERATIONS > *")+COUNTIFS('Prácticas_Snowballing'!$AB$2:$AB$281,"T009",'Prácticas_Snowballing'!$AC$2:$AC$281,"SOFTWARE ENG. OPERATIONS > *") -> 0 | I14: =COUNTIFS('Prácticas_Revisiones'!$S$2:$S$282,"T009",'Prácticas_Revisiones'!$T$2:$T$282,"MAINTENANCE > *")+COUNTIFS('Prácticas_Snowballing'!$AB$2:$AB$281,"T009",'Prácticas_Snowballing'!$AC$2:$AC$281,"MAINTENANCE > *") -> 0 | J14: =COUNTIFS('Prácticas_Revisiones'!$S$2:$S$282,"T009",'Prácticas_Revisiones'!$T$2:$T$282,"SOFTWARE CONFIG. MGMT. > *")+COUNTIFS('Prácticas_Snowballing'!$AB$2:$AB$281,"T009",'Prácticas_Snowballing'!$AC$2:$AC$281,"SOFTWARE CONFIG. MGMT. > *") -> 0 | K14: =COUNTIFS('Prácticas_Revisiones'!$S$2:$S$282,"T009",'Prácticas_Revisiones'!$T$2:$T$282,"SOFTWARE ENG. PROCESS > *")+COUNTIFS('Prácticas_Snowballing'!$AB$2:$AB$281,"T009",'Prácticas_Snowballing'!$AC$2:$AC$281,"SOFTWARE ENG. PROCESS > *") -> 0 | L14: =COUNTIFS('Prácticas_Revisiones'!$S$2:$S$282,"T009",'Prácticas_Revisiones'!$T$2:$T$282,"SOFTWARE ENG. MODELS/METH. > *")+COUNTIFS('Prácticas_Snowballing'!$AB$2:$AB$281,"T009",'Prácticas_Snowballing'!$AC$2:$AC$281,"SOFTWARE ENG. MODELS/METH. > *") -> 0 | M14: =COUNTIFS('Prácticas_Revisiones'!$S$2:$S$282,"T009",'Prácticas_Revisiones'!$T$2:$T$282,"SOFTWARE QUALITY > *")+COUNTIFS('Prácticas_Snowballing'!$AB$2:$AB$281,"T009",'Prácticas_Snowballing'!$AC$2:$AC$281,"SOFTWARE QUALITY > *") -> 0 | N14: =COUNTIFS('Prácticas_Revisiones'!$S$2:$S$282,"T009",'Prácticas_Revisiones'!$T$2:$T$282,"SOFTWARE SECURITY > *")+COUNTIFS('Prácticas_Snowballing'!$AB$2:$AB$281,"T009",'Prácticas_Snowballing'!$AC$2:$AC$281,"SOFTWARE SECURITY > *") -> 0 | O14: =COUNTIFS('Prácticas_Revisiones'!$S$2:$S$282,"T009",'Prácticas_Revisiones'!$T$2:$T$282,"PROFESSIONAL PRACTICE > *")+COUNTIFS('Prácticas_Snowballing'!$AB$2:$AB$281,"T009",'Prácticas_Snowballing'!$AC$2:$AC$281,"PROFESSIONAL PRACTICE > *") -> 0 | P14: =COUNTIFS('Prácticas_Revisiones'!$S$2:$S$282,"T009",'Prácticas_Revisiones'!$T$2:$T$282,"SOFTWARE ENG. ECONOMICS > *")+COUNTIFS('Prácticas_Snowballing'!$AB$2:$AB$281,"T009",'Prácticas_Snowballing'!$AC$2:$AC$281,"SOFTWARE ENG. ECONOMICS > *") -> 0 | Q14: =COUNTIFS('Prácticas_Revisiones'!$S$2:$S$282,"T009",'Prácticas_Revisiones'!$T$2:$T$282,"SOFTWARE ENG. MANAGEMENT > *")+COUNTIFS('Prácticas_Snowballing'!$AB$2:$AB$281,"T009",'Prácticas_Snowballing'!$AC$2:$AC$281,"SOFTWARE ENG. MANAGEMENT > *") -> 0 | R14: =COUNTIFS('Prácticas_Revisiones'!$S$2:$S$282,"T009",'Prácticas_Revisiones'!$T$2:$T$282,"Sin área SWEBOK")+COUNTIFS('Prácticas_Snowballing'!$AB$2:$AB$281,"T009",'Prácticas_Snowballing'!$AC$2:$AC$281,"Sin área SWEBOK") -> 0 | S14: =SUM(C14:R14) -> 1
B15: T010 SQA | C15: =COUNTIFS('Prácticas_Revisiones'!$S$2:$S$282,"T010",'Prácticas_Revisiones'!$T$2:$T$282,"REQUIREMENTS > *")+COUNTIFS('Prácticas_Snowballing'!$AB$2:$AB$281,"T010",'Prácticas_Snowballing'!$AC$2:$AC$281,"REQUIREMENTS > *") -> 0 | D15: =COUNTIFS('Prácticas_Revisiones'!$S$2:$S$282,"T010",'Prácticas_Revisiones'!$T$2:$T$282,"ARCHITECTURE > *")+COUNTIFS('Prácticas_Snowballing'!$AB$2:$AB$281,"T010",'Prácticas_Snowballing'!$AC$2:$AC$281,"ARCHITECTURE > *") -> 0 | E15: =COUNTIFS('Prácticas_Revisiones'!$S$2:$S$282,"T010",'Prácticas_Revisiones'!$T$2:$T$282,"DESIGN > *")+COUNTIFS('Prácticas_Snowballing'!$AB$2:$AB$281,"T010",'Prácticas_Snowballing'!$AC$2:$AC$281,"DESIGN > *") -> 0 | F15: =COUNTIFS('Prácticas_Revisiones'!$S$2:$S$282,"T010",'Prácticas_Revisiones'!$T$2:$T$282,"CONSTRUCTION > *")+COUNTIFS('Prácticas_Snowballing'!$AB$2:$AB$281,"T010",'Prácticas_Snowballing'!$AC$2:$AC$281,"CONSTRUCTION > *") -> 0 | G15: =COUNTIFS('Prácticas_Revisiones'!$S$2:$S$282,"T010",'Prácticas_Revisiones'!$T$2:$T$282,"SOFTWARE TESTING > *")+COUNTIFS('Prácticas_Snowballing'!$AB$2:$AB$281,"T010",'Prácticas_Snowballing'!$AC$2:$AC$281,"SOFTWARE TESTING > *") -> 0 | H15: =COUNTIFS('Prácticas_Revisiones'!$S$2:$S$282,"T010",'Prácticas_Revisiones'!$T$2:$T$282,"SOFTWARE ENG. OPERATIONS > *")+COUNTIFS('Prácticas_Snowballing'!$AB$2:$AB$281,"T010",'Prácticas_Snowballing'!$AC$2:$AC$281,"SOFTWARE ENG. OPERATIONS > *") -> 0 | I15: =COUNTIFS('Prácticas_Revisiones'!$S$2:$S$282,"T010",'Prácticas_Revisiones'!$T$2:$T$282,"MAINTENANCE > *")+COUNTIFS('Prácticas_Snowballing'!$AB$2:$AB$281,"T010",'Prácticas_Snowballing'!$AC$2:$AC$281,"MAINTENANCE > *") -> 0 | J15: =COUNTIFS('Prácticas_Revisiones'!$S$2:$S$282,"T010",'Prácticas_Revisiones'!$T$2:$T$282,"SOFTWARE CONFIG. MGMT. > *")+COUNTIFS('Prácticas_Snowballing'!$AB$2:$AB$281,"T010",'Prácticas_Snowballing'!$AC$2:$AC$281,"SOFTWARE CONFIG. MGMT. > *") -> 0 | K15: =COUNTIFS('Prácticas_Revisiones'!$S$2:$S$282,"T010",'Prácticas_Revisiones'!$T$2:$T$282,"SOFTWARE ENG. PROCESS > *")+COUNTIFS('Prácticas_Snowballing'!$AB$2:$AB$281,"T010",'Prácticas_Snowballing'!$AC$2:$AC$281,"SOFTWARE ENG. PROCESS > *") -> 0 | L15: =COUNTIFS('Prácticas_Revisiones'!$S$2:$S$282,"T010",'Prácticas_Revisiones'!$T$2:$T$282,"SOFTWARE ENG. MODELS/METH. > *")+COUNTIFS('Prácticas_Snowballing'!$AB$2:$AB$281,"T010",'Prácticas_Snowballing'!$AC$2:$AC$281,"SOFTWARE ENG. MODELS/METH. > *") -> 0 | M15: =COUNTIFS('Prácticas_Revisiones'!$S$2:$S$282,"T010",'Prácticas_Revisiones'!$T$2:$T$282,"SOFTWARE QUALITY > *")+COUNTIFS('Prácticas_Snowballing'!$AB$2:$AB$281,"T010",'Prácticas_Snowballing'!$AC$2:$AC$281,"SOFTWARE QUALITY > *") -> 0 | N15: =COUNTIFS('Prácticas_Revisiones'!$S$2:$S$282,"T010",'Prácticas_Revisiones'!$T$2:$T$282,"SOFTWARE SECURITY > *")+COUNTIFS('Prácticas_Snowballing'!$AB$2:$AB$281,"T010",'Prácticas_Snowballing'!$AC$2:$AC$281,"SOFTWARE SECURITY > *") -> 0 | O15: =COUNTIFS('Prácticas_Revisiones'!$S$2:$S$282,"T010",'Prácticas_Revisiones'!$T$2:$T$282,"PROFESSIONAL PRACTICE > *")+COUNTIFS('Prácticas_Snowballing'!$AB$2:$AB$281,"T010",'Prácticas_Snowballing'!$AC$2:$AC$281,"PROFESSIONAL PRACTICE > *") -> 0 | P15: =COUNTIFS('Prácticas_Revisiones'!$S$2:$S$282,"T010",'Prácticas_Revisiones'!$T$2:$T$282,"SOFTWARE ENG. ECONOMICS > *")+COUNTIFS('Prácticas_Snowballing'!$AB$2:$AB$281,"T010",'Prácticas_Snowballing'!$AC$2:$AC$281,"SOFTWARE ENG. ECONOMICS > *") -> 0 | Q15: =COUNTIFS('Prácticas_Revisiones'!$S$2:$S$282,"T010",'Prácticas_Revisiones'!$T$2:$T$282,"SOFTWARE ENG. MANAGEMENT > *")+COUNTIFS('Prácticas_Snowballing'!$AB$2:$AB$281,"T010",'Prácticas_Snowballing'!$AC$2:$AC$281,"SOFTWARE ENG. MANAGEMENT > *") -> 0 | R15: =COUNTIFS('Prácticas_Revisiones'!$S$2:$S$282,"T010",'Prácticas_Revisiones'!$T$2:$T$282,"Sin área SWEBOK")+COUNTIFS('Prácticas_Snowballing'!$AB$2:$AB$281,"T010",'Prácticas_Snowballing'!$AC$2:$AC$281,"Sin área SWEBOK") -> 0 | S15: =SUM(C15:R15) -> 0
B16: T011 Taxonomía | C16: =COUNTIFS('Prácticas_Revisiones'!$S$2:$S$282,"T011",'Prácticas_Revisiones'!$T$2:$T$282,"REQUIREMENTS > *")+COUNTIFS('Prácticas_Snowballing'!$AB$2:$AB$281,"T011",'Prácticas_Snowballing'!$AC$2:$AC$281,"REQUIREMENTS > *") -> 0 | D16: =COUNTIFS('Prácticas_Revisiones'!$S$2:$S$282,"T011",'Prácticas_Revisiones'!$T$2:$T$282,"ARCHITECTURE > *")+COUNTIFS('Prácticas_Snowballing'!$AB$2:$AB$281,"T011",'Prácticas_Snowballing'!$AC$2:$AC$281,"ARCHITECTURE > *") -> 0 | E16: =COUNTIFS('Prácticas_Revisiones'!$S$2:$S$282,"T011",'Prácticas_Revisiones'!$T$2:$T$282,"DESIGN > *")+COUNTIFS('Prácticas_Snowballing'!$AB$2:$AB$281,"T011",'Prácticas_Snowballing'!$AC$2:$AC$281,"DESIGN > *") -> 0 | F16: =COUNTIFS('Prácticas_Revisiones'!$S$2:$S$282,"T011",'Prácticas_Revisiones'!$T$2:$T$282,"CONSTRUCTION > *")+COUNTIFS('Prácticas_Snowballing'!$AB$2:$AB$281,"T011",'Prácticas_Snowballing'!$AC$2:$AC$281,"CONSTRUCTION > *") -> 0 | G16: =COUNTIFS('Prácticas_Revisiones'!$S$2:$S$282,"T011",'Prácticas_Revisiones'!$T$2:$T$282,"SOFTWARE TESTING > *")+COUNTIFS('Prácticas_Snowballing'!$AB$2:$AB$281,"T011",'Prácticas_Snowballing'!$AC$2:$AC$281,"SOFTWARE TESTING > *") -> 0 | H16: =COUNTIFS('Prácticas_Revisiones'!$S$2:$S$282,"T011",'Prácticas_Revisiones'!$T$2:$T$282,"SOFTWARE ENG. OPERATIONS > *")+COUNTIFS('Prácticas_Snowballing'!$AB$2:$AB$281,"T011",'Prácticas_Snowballing'!$AC$2:$AC$281,"SOFTWARE ENG. OPERATIONS > *") -> 0 | I16: =COUNTIFS('Prácticas_Revisiones'!$S$2:$S$282,"T011",'Prácticas_Revisiones'!$T$2:$T$282,"MAINTENANCE > *")+COUNTIFS('Prácticas_Snowballing'!$AB$2:$AB$281,"T011",'Prácticas_Snowballing'!$AC$2:$AC$281,"MAINTENANCE > *") -> 0 | J16: =COUNTIFS('Prácticas_Revisiones'!$S$2:$S$282,"T011",'Prácticas_Revisiones'!$T$2:$T$282,"SOFTWARE CONFIG. MGMT. > *")+COUNTIFS('Prácticas_Snowballing'!$AB$2:$AB$281,"T011",'Prácticas_Snowballing'!$AC$2:$AC$281,"SOFTWARE CONFIG. MGMT. > *") -> 0 | K16: =COUNTIFS('Prácticas_Revisiones'!$S$2:$S$282,"T011",'Prácticas_Revisiones'!$T$2:$T$282,"SOFTWARE ENG. PROCESS > *")+COUNTIFS('Prácticas_Snowballing'!$AB$2:$AB$281,"T011",'Prácticas_Snowballing'!$AC$2:$AC$281,"SOFTWARE ENG. PROCESS > *") -> 0 | L16: =COUNTIFS('Prácticas_Revisiones'!$S$2:$S$282,"T011",'Prácticas_Revisiones'!$T$2:$T$282,"SOFTWARE ENG. MODELS/METH. > *")+COUNTIFS('Prácticas_Snowballing'!$AB$2:$AB$281,"T011",'Prácticas_Snowballing'!$AC$2:$AC$281,"SOFTWARE ENG. MODELS/METH. > *") -> 0 | M16: =COUNTIFS('Prácticas_Revisiones'!$S$2:$S$282,"T011",'Prácticas_Revisiones'!$T$2:$T$282,"SOFTWARE QUALITY > *")+COUNTIFS('Prácticas_Snowballing'!$AB$2:$AB$281,"T011",'Prácticas_Snowballing'!$AC$2:$AC$281,"SOFTWARE QUALITY > *") -> 0 | N16: =COUNTIFS('Prácticas_Revisiones'!$S$2:$S$282,"T011",'Prácticas_Revisiones'!$T$2:$T$282,"SOFTWARE SECURITY > *")+COUNTIFS('Prácticas_Snowballing'!$AB$2:$AB$281,"T011",'Prácticas_Snowballing'!$AC$2:$AC$281,"SOFTWARE SECURITY > *") -> 0 | O16: =COUNTIFS('Prácticas_Revisiones'!$S$2:$S$282,"T011",'Prácticas_Revisiones'!$T$2:$T$282,"PROFESSIONAL PRACTICE > *")+COUNTIFS('Prácticas_Snowballing'!$AB$2:$AB$281,"T011",'Prácticas_Snowballing'!$AC$2:$AC$281,"PROFESSIONAL PRACTICE > *") -> 0 | P16: =COUNTIFS('Prácticas_Revisiones'!$S$2:$S$282,"T011",'Prácticas_Revisiones'!$T$2:$T$282,"SOFTWARE ENG. ECONOMICS > *")+COUNTIFS('Prácticas_Snowballing'!$AB$2:$AB$281,"T011",'Prácticas_Snowballing'!$AC$2:$AC$281,"SOFTWARE ENG. ECONOMICS > *") -> 0 | Q16: =COUNTIFS('Prácticas_Revisiones'!$S$2:$S$282,"T011",'Prácticas_Revisiones'!$T$2:$T$282,"SOFTWARE ENG. MANAGEMENT > *")+COUNTIFS('Prácticas_Snowballing'!$AB$2:$AB$281,"T011",'Prácticas_Snowballing'!$AC$2:$AC$281,"SOFTWARE ENG. MANAGEMENT > *") -> 0 | R16: =COUNTIFS('Prácticas_Revisiones'!$S$2:$S$282,"T011",'Prácticas_Revisiones'!$T$2:$T$282,"Sin área SWEBOK")+COUNTIFS('Prácticas_Snowballing'!$AB$2:$AB$281,"T011",'Prácticas_Snowballing'!$AC$2:$AC$281,"Sin área SWEBOK") -> 0 | S16: =SUM(C16:R16) -> 0
B17: Sin equivalente en catálogo | C17: =COUNTIFS('Prácticas_Revisiones'!$S$2:$S$282,"Sin equivalente en catálogo (RECORDAR)",'Prácticas_Revisiones'!$T$2:$T$282,"REQUIREMENTS > *")+COUNTIFS('Prácticas_Snowballing'!$AB$2:$AB$281,"Sin equivalente en catálogo (RECORDAR)",'Prácticas_Snowballing'!$AC$2:$AC$281,"REQUIREMENTS > *") -> 0 | D17: =COUNTIFS('Prácticas_Revisiones'!$S$2:$S$282,"Sin equivalente en catálogo (RECORDAR)",'Prácticas_Revisiones'!$T$2:$T$282,"ARCHITECTURE > *")+COUNTIFS('Prácticas_Snowballing'!$AB$2:$AB$281,"Sin equivalente en catálogo (RECORDAR)",'Prácticas_Snowballing'!$AC$2:$AC$281,"ARCHITECTURE > *") -> 0 | E17: =COUNTIFS('Prácticas_Revisiones'!$S$2:$S$282,"Sin equivalente en catálogo (RECORDAR)",'Prácticas_Revisiones'!$T$2:$T$282,"DESIGN > *")+COUNTIFS('Prácticas_Snowballing'!$AB$2:$AB$281,"Sin equivalente en catálogo (RECORDAR)",'Prácticas_Snowballing'!$AC$2:$AC$281,"DESIGN > *") -> 0 | F17: =COUNTIFS('Prácticas_Revisiones'!$S$2:$S$282,"Sin equivalente en catálogo (RECORDAR)",'Prácticas_Revisiones'!$T$2:$T$282,"CONSTRUCTION > *")+COUNTIFS('Prácticas_Snowballing'!$AB$2:$AB$281,"Sin equivalente en catálogo (RECORDAR)",'Prácticas_Snowballing'!$AC$2:$AC$281,"CONSTRUCTION > *") -> 0 | G17: =COUNTIFS('Prácticas_Revisiones'!$S$2:$S$282,"Sin equivalente en catálogo (RECORDAR)",'Prácticas_Revisiones'!$T$2:$T$282,"SOFTWARE TESTING > *")+COUNTIFS('Prácticas_Snowballing'!$AB$2:$AB$281,"Sin equivalente en catálogo (RECORDAR)",'Prácticas_Snowballing'!$AC$2:$AC$281,"SOFTWARE TESTING > *") -> 0 | H17: =COUNTIFS('Prácticas_Revisiones'!$S$2:$S$282,"Sin equivalente en catálogo (RECORDAR)",'Prácticas_Revisiones'!$T$2:$T$282,"SOFTWARE ENG. OPERATIONS > *")+COUNTIFS('Prácticas_Snowballing'!$AB$2:$AB$281,"Sin equivalente en catálogo (RECORDAR)",'Prácticas_Snowballing'!$AC$2:$AC$281,"SOFTWARE ENG. OPERATIONS > *") -> 0 | I17: =COUNTIFS('Prácticas_Revisiones'!$S$2:$S$282,"Sin equivalente en catálogo (RECORDAR)",'Prácticas_Revisiones'!$T$2:$T$282,"MAINTENANCE > *")+COUNTIFS('Prácticas_Snowballing'!$AB$2:$AB$281,"Sin equivalente en catálogo (RECORDAR)",'Prácticas_Snowballing'!$AC$2:$AC$281,"MAINTENANCE > *") -> 0 | J17: =COUNTIFS('Prácticas_Revisiones'!$S$2:$S$282,"Sin equivalente en catálogo (RECORDAR)",'Prácticas_Revisiones'!$T$2:$T$282,"SOFTWARE CONFIG. MGMT. > *")+COUNTIFS('Prácticas_Snowballing'!$AB$2:$AB$281,"Sin equivalente en catálogo (RECORDAR)",'Prácticas_Snowballing'!$AC$2:$AC$281,"SOFTWARE CONFIG. MGMT. > *") -> 0 | K17: =COUNTIFS('Prácticas_Revisiones'!$S$2:$S$282,"Sin equivalente en catálogo (RECORDAR)",'Prácticas_Revisiones'!$T$2:$T$282,"SOFTWARE ENG. PROCESS > *")+COUNTIFS('Prácticas_Snowballing'!$AB$2:$AB$281,"Sin equivalente en catálogo (RECORDAR)",'Prácticas_Snowballing'!$AC$2:$AC$281,"SOFTWARE ENG. PROCESS > *") -> 0 | L17: =COUNTIFS('Prácticas_Revisiones'!$S$2:$S$282,"Sin equivalente en catálogo (RECORDAR)",'Prácticas_Revisiones'!$T$2:$T$282,"SOFTWARE ENG. MODELS/METH. > *")+COUNTIFS('Prácticas_Snowballing'!$AB$2:$AB$281,"Sin equivalente en catálogo (RECORDAR)",'Prácticas_Snowballing'!$AC$2:$AC$281,"SOFTWARE ENG. MODELS/METH. > *") -> 0 | M17: =COUNTIFS('Prácticas_Revisiones'!$S$2:$S$282,"Sin equivalente en catálogo (RECORDAR)",'Prácticas_Revisiones'!$T$2:$T$282,"SOFTWARE QUALITY > *")+COUNTIFS('Prácticas_Snowballing'!$AB$2:$AB$281,"Sin equivalente en catálogo (RECORDAR)",'Prácticas_Snowballing'!$AC$2:$AC$281,"SOFTWARE QUALITY > *") -> 0 | N17: =COUNTIFS('Prácticas_Revisiones'!$S$2:$S$282,"Sin equivalente en catálogo (RECORDAR)",'Prácticas_Revisiones'!$T$2:$T$282,"SOFTWARE SECURITY > *")+COUNTIFS('Prácticas_Snowballing'!$AB$2:$AB$281,"Sin equivalente en catálogo (RECORDAR)",'Prácticas_Snowballing'!$AC$2:$AC$281,"SOFTWARE SECURITY > *") -> 0 | O17: =COUNTIFS('Prácticas_Revisiones'!$S$2:$S$282,"Sin equivalente en catálogo (RECORDAR)",'Prácticas_Revisiones'!$T$2:$T$282,"PROFESSIONAL PRACTICE > *")+COUNTIFS('Prácticas_Snowballing'!$AB$2:$AB$281,"Sin equivalente en catálogo (RECORDAR)",'Prácticas_Snowballing'!$AC$2:$AC$281,"PROFESSIONAL PRACTICE > *") -> 0 | P17: =COUNTIFS('Prácticas_Revisiones'!$S$2:$S$282,"Sin equivalente en catálogo (RECORDAR)",'Prácticas_Revisiones'!$T$2:$T$282,"SOFTWARE ENG. ECONOMICS > *")+COUNTIFS('Prácticas_Snowballing'!$AB$2:$AB$281,"Sin equivalente en catálogo (RECORDAR)",'Prácticas_Snowballing'!$AC$2:$AC$281,"SOFTWARE ENG. ECONOMICS > *") -> 0 | Q17: =COUNTIFS('Prácticas_Revisiones'!$S$2:$S$282,"Sin equivalente en catálogo (RECORDAR)",'Prácticas_Revisiones'!$T$2:$T$282,"SOFTWARE ENG. MANAGEMENT > *")+COUNTIFS('Prácticas_Snowballing'!$AB$2:$AB$281,"Sin equivalente en catálogo (RECORDAR)",'Prácticas_Snowballing'!$AC$2:$AC$281,"SOFTWARE ENG. MANAGEMENT > *") -> 0 | R17: =COUNTIFS('Prácticas_Revisiones'!$S$2:$S$282,"Sin equivalente en catálogo (RECORDAR)",'Prácticas_Revisiones'!$T$2:$T$282,"Sin área SWEBOK")+COUNTIFS('Prácticas_Snowballing'!$AB$2:$AB$281,"Sin equivalente en catálogo (RECORDAR)",'Prácticas_Snowballing'!$AC$2:$AC$281,"Sin área SWEBOK") -> 0 | S17: =SUM(C17:R17) -> 0
A18: Subtotal RECORDAR | C18: =SUM(C6:C17) -> 0 | D18: =SUM(D6:D17) -> 0 | E18: =SUM(E6:E17) -> 2 | F18: =SUM(F6:F17) -> 10 | G18: =SUM(G6:G17) -> 0 | H18: =SUM(H6:H17) -> 0 | I18: =SUM(I6:I17) -> 0 | J18: =SUM(J6:J17) -> 0 | ... S18: =SUM(S6:S17) -> 14
A19: EXPLICAR | B19: T012 Afiche | C19: =COUNTIFS('Prácticas_Revisiones'!$S$2:$S$282,"T012",'Prácticas_Revisiones'!$T$2:$T$282,"REQUIREMENTS > *")+COUNTIFS('Prácticas_Snowballing'!$AB$2:$AB$281,"T012",'Prácticas_Snowballing'!$AC$2:$AC$281,"REQUIREMENTS > *") -> 0 | D19: =COUNTIFS('Prácticas_Revisiones'!$S$2:$S$282,"T012",'Prácticas_Revisiones'!$T$2:$T$282,"ARCHITECTURE > *")+COUNTIFS('Prácticas_Snowballing'!$AB$2:$AB$281,"T012",'Prácticas_Snowballing'!$AC$2:$AC$281,"ARCHITECTURE > *") -> 0 | E19: =COUNTIFS('Prácticas_Revisiones'!$S$2:$S$282,"T012",'Prácticas_Revisiones'!$T$2:$T$282,"DESIGN > *")+COUNTIFS('Prácticas_Snowballing'!$AB$2:$AB$281,"T012",'Prácticas_Snowballing'!$AC$2:$AC$281,"DESIGN > *") -> 0 | F19: =COUNTIFS('Prácticas_Revisiones'!$S$2:$S$282,"T012",'Prácticas_Revisiones'!$T$2:$T$282,"CONSTRUCTION > *")+COUNTIFS('Prácticas_Snowballing'!$AB$2:$AB$281,"T012",'Prácticas_Snowballing'!$AC$2:$AC$281,"CONSTRUCTION > *") -> 0 | G19: =COUNTIFS('Prácticas_Revisiones'!$S$2:$S$282,"T012",'Prácticas_Revisiones'!$T$2:$T$282,"SOFTWARE TESTING > *")+COUNTIFS('Prácticas_Snowballing'!$AB$2:$AB$281,"T012",'Prácticas_Snowballing'!$AC$2:$AC$281,"SOFTWARE TESTING > *") -> 0 | H19: =COUNTIFS('Prácticas_Revisiones'!$S$2:$S$282,"T012",'Prácticas_Revisiones'!$T$2:$T$282,"SOFTWARE ENG. OPERATIONS > *")+COUNTIFS('Prácticas_Snowballing'!$AB$2:$AB$281,"T012",'Prácticas_Snowballing'!$AC$2:$AC$281,"SOFTWARE ENG. OPERATIONS > *") -> 0 | I19: =COUNTIFS('Prácticas_Revisiones'!$S$2:$S$282,"T012",'Prácticas_Revisiones'!$T$2:$T$282,"MAINTENANCE > *")+COUNTIFS('Prácticas_Snowballing'!$AB$2:$AB$281,"T012",'Prácticas_Snowballing'!$AC$2:$AC$281,"MAINTENANCE > *") -> 0 | J19: =COUNTIFS('Prácticas_Revisiones'!$S$2:$S$282,"T012",'Prácticas_Revisiones'!$T$2:$T$282,"SOFTWARE CONFIG. MGMT. > *")+COUNTIFS('Prácticas_Snowballing'!$AB$2:$AB$281,"T012",'Prácticas_Snowballing'!$AC$2:$AC$281,"SOFTWARE CONFIG. MGMT. > *") -> 0 | K19: =COUNTIFS('Prácticas_Revisiones'!$S$2:$S$282,"T012",'Prácticas_Revisiones'!$T$2:$T$282,"SOFTWARE ENG. PROCESS > *")+COUNTIFS('Prácticas_Snowballing'!$AB$2:$AB$281,"T012",'Prácticas_Snowballing'!$AC$2:$AC$281,"SOFTWARE ENG. PROCESS > *") -> 0 | L19: =COUNTIFS('Prácticas_Revisiones'!$S$2:$S$282,"T012",'Prácticas_Revisiones'!$T$2:$T$282,"SOFTWARE ENG. MODELS/METH. > *")+COUNTIFS('Prácticas_Snowballing'!$AB$2:$AB$281,"T012",'Prácticas_Snowballing'!$AC$2:$AC$281,"SOFTWARE ENG. MODELS/METH. > *") -> 0 | M19: =COUNTIFS('Prácticas_Revisiones'!$S$2:$S$282,"T012",'Prácticas_Revisiones'!$T$2:$T$282,"SOFTWARE QUALITY > *")+COUNTIFS('Prácticas_Snowballing'!$AB$2:$AB$281,"T012",'Prácticas_Snowballing'!$AC$2:$AC$281,"SOFTWARE QUALITY > *") -> 0 | N19: =COUNTIFS('Prácticas_Revisiones'!$S$2:$S$282,"T012",'Prácticas_Revisiones'!$T$2:$T$282,"SOFTWARE SECURITY > *")+COUNTIFS('Prácticas_Snowballing'!$AB$2:$AB$281,"T012",'Prácticas_Snowballing'!$AC$2:$AC$281,"SOFTWARE SECURITY > *") -> 0 | O19: =COUNTIFS('Prácticas_Revisiones'!$S$2:$S$282,"T012",'Prácticas_Revisiones'!$T$2:$T$282,"PROFESSIONAL PRACTICE > *")+COUNTIFS('Prácticas_Snowballing'!$AB$2:$AB$281,"T012",'Prácticas_Snowballing'!$AC$2:$AC$281,"PROFESSIONAL PRACTICE > *") -> 0 | P19: =COUNTIFS('Prácticas_Revisiones'!$S$2:$S$282,"T012",'Prácticas_Revisiones'!$T$2:$T$282,"SOFTWARE ENG. ECONOMICS > *")+COUNTIFS('Prácticas_Snowballing'!$AB$2:$AB$281,"T012",'Prácticas_Snowballing'!$AC$2:$AC$281,"SOFTWARE ENG. ECONOMICS > *") -> 0 | Q19: =COUNTIFS('Prácticas_Revisiones'!$S$2:$S$282,"T012",'Prácticas_Revisiones'!$T$2:$T$282,"SOFTWARE ENG. MANAGEMENT > *")+COUNTIFS('Prácticas_Snowballing'!$AB$2:$AB$281,"T012",'Prácticas_Snowballing'!$AC$2:$AC$281,"SOFTWARE ENG. MANAGEMENT > *") -> 0 | R19: =COUNTIFS('Prácticas_Revisiones'!$S$2:$S$282,"T012",'Prácticas_Revisiones'!$T$2:$T$282,"Sin área SWEBOK")+COUNTIFS('Prácticas_Snowballing'!$AB$2:$AB$281,"T012",'Prácticas_Snowballing'!$AC$2:$AC$281,"Sin área SWEBOK") -> 0 | S19: =SUM(C19:R19) -> 0
B20: T013 Anuncio publicitario | C20: =COUNTIFS('Prácticas_Revisiones'!$S$2:$S$282,"T013",'Prácticas_Revisiones'!$T$2:$T$282,"REQUIREMENTS > *")+COUNTIFS('Prácticas_Snowballing'!$AB$2:$AB$281,"T013",'Prácticas_Snowballing'!$AC$2:$AC$281,"REQUIREMENTS > *") -> 0 | D20: =COUNTIFS('Prácticas_Revisiones'!$S$2:$S$282,"T013",'Prácticas_Revisiones'!$T$2:$T$282,"ARCHITECTURE > *")+COUNTIFS('Prácticas_Snowballing'!$AB$2:$AB$281,"T013",'Prácticas_Snowballing'!$AC$2:$AC$281,"ARCHITECTURE > *") -> 0 | E20: =COUNTIFS('Prácticas_Revisiones'!$S$2:$S$282,"T013",'Prácticas_Revisiones'!$T$2:$T$282,"DESIGN > *")+COUNTIFS('Prácticas_Snowballing'!$AB$2:$AB$281,"T013",'Prácticas_Snowballing'!$AC$2:$AC$281,"DESIGN > *") -> 0 | F20: =COUNTIFS('Prácticas_Revisiones'!$S$2:$S$282,"T013",'Prácticas_Revisiones'!$T$2:$T$282,"CONSTRUCTION > *")+COUNTIFS('Prácticas_Snowballing'!$AB$2:$AB$281,"T013",'Prácticas_Snowballing'!$AC$2:$AC$281,"CONSTRUCTION > *") -> 0 | G20: =COUNTIFS('Prácticas_Revisiones'!$S$2:$S$282,"T013",'Prácticas_Revisiones'!$T$2:$T$282,"SOFTWARE TESTING > *")+COUNTIFS('Prácticas_Snowballing'!$AB$2:$AB$281,"T013",'Prácticas_Snowballing'!$AC$2:$AC$281,"SOFTWARE TESTING > *") -> 0 | H20: =COUNTIFS('Prácticas_Revisiones'!$S$2:$S$282,"T013",'Prácticas_Revisiones'!$T$2:$T$282,"SOFTWARE ENG. OPERATIONS > *")+COUNTIFS('Prácticas_Snowballing'!$AB$2:$AB$281,"T013",'Prácticas_Snowballing'!$AC$2:$AC$281,"SOFTWARE ENG. OPERATIONS > *") -> 0 | I20: =COUNTIFS('Prácticas_Revisiones'!$S$2:$S$282,"T013",'Prácticas_Revisiones'!$T$2:$T$282,"MAINTENANCE > *")+COUNTIFS('Prácticas_Snowballing'!$AB$2:$AB$281,"T013",'Prácticas_Snowballing'!$AC$2:$AC$281,"MAINTENANCE > *") -> 0 | J20: =COUNTIFS('Prácticas_Revisiones'!$S$2:$S$282,"T013",'Prácticas_Revisiones'!$T$2:$T$282,"SOFTWARE CONFIG. MGMT. > *")+COUNTIFS('Prácticas_Snowballing'!$AB$2:$AB$281,"T013",'Prácticas_Snowballing'!$AC$2:$AC$281,"SOFTWARE CONFIG. MGMT. > *") -> 0 | K20: =COUNTIFS('Prácticas_Revisiones'!$S$2:$S$282,"T013",'Prácticas_Revisiones'!$T$2:$T$282,"SOFTWARE ENG. PROCESS > *")+COUNTIFS('Prácticas_Snowballing'!$AB$2:$AB$281,"T013",'Prácticas_Snowballing'!$AC$2:$AC$281,"SOFTWARE ENG. PROCESS > *") -> 0 | L20: =COUNTIFS('Prácticas_Revisiones'!$S$2:$S$282,"T013",'Prácticas_Revisiones'!$T$2:$T$282,"SOFTWARE ENG. MODELS/METH. > *")+COUNTIFS('Prácticas_Snowballing'!$AB$2:$AB$281,"T013",'Prácticas_Snowballing'!$AC$2:$AC$281,"SOFTWARE ENG. MODELS/METH. > *") -> 0 | M20: =COUNTIFS('Prácticas_Revisiones'!$S$2:$S$282,"T013",'Prácticas_Revisiones'!$T$2:$T$282,"SOFTWARE QUALITY > *")+COUNTIFS('Prácticas_Snowballing'!$AB$2:$AB$281,"T013",'Prácticas_Snowballing'!$AC$2:$AC$281,"SOFTWARE QUALITY > *") -> 0 | N20: =COUNTIFS('Prácticas_Revisiones'!$S$2:$S$282,"T013",'Prácticas_Revisiones'!$T$2:$T$282,"SOFTWARE SECURITY > *")+COUNTIFS('Prácticas_Snowballing'!$AB$2:$AB$281,"T013",'Prácticas_Snowballing'!$AC$2:$AC$281,"SOFTWARE SECURITY > *") -> 0 | O20: =COUNTIFS('Prácticas_Revisiones'!$S$2:$S$282,"T013",'Prácticas_Revisiones'!$T$2:$T$282,"PROFESSIONAL PRACTICE > *")+COUNTIFS('Prácticas_Snowballing'!$AB$2:$AB$281,"T013",'Prácticas_Snowballing'!$AC$2:$AC$281,"PROFESSIONAL PRACTICE > *") -> 0 | P20: =COUNTIFS('Prácticas_Revisiones'!$S$2:$S$282,"T013",'Prácticas_Revisiones'!$T$2:$T$282,"SOFTWARE ENG. ECONOMICS > *")+COUNTIFS('Prácticas_Snowballing'!$AB$2:$AB$281,"T013",'Prácticas_Snowballing'!$AC$2:$AC$281,"SOFTWARE ENG. ECONOMICS > *") -> 0 | Q20: =COUNTIFS('Prácticas_Revisiones'!$S$2:$S$282,"T013",'Prácticas_Revisiones'!$T$2:$T$282,"SOFTWARE ENG. MANAGEMENT > *")+COUNTIFS('Prácticas_Snowballing'!$AB$2:$AB$281,"T013",'Prácticas_Snowballing'!$AC$2:$AC$281,"SOFTWARE ENG. MANAGEMENT > *") -> 0 | R20: =COUNTIFS('Prácticas_Revisiones'!$S$2:$S$282,"T013",'Prácticas_Revisiones'!$T$2:$T$282,"Sin área SWEBOK")+COUNTIFS('Prácticas_Snowballing'!$AB$2:$AB$281,"T013",'Prácticas_Snowballing'!$AC$2:$AC$281,"Sin área SWEBOK") -> 0 | S20: =SUM(C20:R20) -> 0
B21: T014 Artículo | C21: =COUNTIFS('Prácticas_Revisiones'!$S$2:$S$282,"T014",'Prácticas_Revisiones'!$T$2:$T$282,"REQUIREMENTS > *")+COUNTIFS('Prácticas_Snowballing'!$AB$2:$AB$281,"T014",'Prácticas_Snowballing'!$AC$2:$AC$281,"REQUIREMENTS > *") -> 0 | D21: =COUNTIFS('Prácticas_Revisiones'!$S$2:$S$282,"T014",'Prácticas_Revisiones'!$T$2:$T$282,"ARCHITECTURE > *")+COUNTIFS('Prácticas_Snowballing'!$AB$2:$AB$281,"T014",'Prácticas_Snowballing'!$AC$2:$AC$281,"ARCHITECTURE > *") -> 0 | E21: =COUNTIFS('Prácticas_Revisiones'!$S$2:$S$282,"T014",'Prácticas_Revisiones'!$T$2:$T$282,"DESIGN > *")+COUNTIFS('Prácticas_Snowballing'!$AB$2:$AB$281,"T014",'Prácticas_Snowballing'!$AC$2:$AC$281,"DESIGN > *") -> 0 | F21: =COUNTIFS('Prácticas_Revisiones'!$S$2:$S$282,"T014",'Prácticas_Revisiones'!$T$2:$T$282,"CONSTRUCTION > *")+COUNTIFS('Prácticas_Snowballing'!$AB$2:$AB$281,"T014",'Prácticas_Snowballing'!$AC$2:$AC$281,"CONSTRUCTION > *") -> 0 | G21: =COUNTIFS('Prácticas_Revisiones'!$S$2:$S$282,"T014",'Prácticas_Revisiones'!$T$2:$T$282,"SOFTWARE TESTING > *")+COUNTIFS('Prácticas_Snowballing'!$AB$2:$AB$281,"T014",'Prácticas_Snowballing'!$AC$2:$AC$281,"SOFTWARE TESTING > *") -> 0 | H21: =COUNTIFS('Prácticas_Revisiones'!$S$2:$S$282,"T014",'Prácticas_Revisiones'!$T$2:$T$282,"SOFTWARE ENG. OPERATIONS > *")+COUNTIFS('Prácticas_Snowballing'!$AB$2:$AB$281,"T014",'Prácticas_Snowballing'!$AC$2:$AC$281,"SOFTWARE ENG. OPERATIONS > *") -> 0 | I21: =COUNTIFS('Prácticas_Revisiones'!$S$2:$S$282,"T014",'Prácticas_Revisiones'!$T$2:$T$282,"MAINTENANCE > *")+COUNTIFS('Prácticas_Snowballing'!$AB$2:$AB$281,"T014",'Prácticas_Snowballing'!$AC$2:$AC$281,"MAINTENANCE > *") -> 0 | J21: =COUNTIFS('Prácticas_Revisiones'!$S$2:$S$282,"T014",'Prácticas_Revisiones'!$T$2:$T$282,"SOFTWARE CONFIG. MGMT. > *")+COUNTIFS('Prácticas_Snowballing'!$AB$2:$AB$281,"T014",'Prácticas_Snowballing'!$AC$2:$AC$281,"SOFTWARE CONFIG. MGMT. > *") -> 0 | K21: =COUNTIFS('Prácticas_Revisiones'!$S$2:$S$282,"T014",'Prácticas_Revisiones'!$T$2:$T$282,"SOFTWARE ENG. PROCESS > *")+COUNTIFS('Prácticas_Snowballing'!$AB$2:$AB$281,"T014",'Prácticas_Snowballing'!$AC$2:$AC$281,"SOFTWARE ENG. PROCESS > *") -> 0 | L21: =COUNTIFS('Prácticas_Revisiones'!$S$2:$S$282,"T014",'Prácticas_Revisiones'!$T$2:$T$282,"SOFTWARE ENG. MODELS/METH. > *")+COUNTIFS('Prácticas_Snowballing'!$AB$2:$AB$281,"T014",'Prácticas_Snowballing'!$AC$2:$AC$281,"SOFTWARE ENG. MODELS/METH. > *") -> 0 | M21: =COUNTIFS('Prácticas_Revisiones'!$S$2:$S$282,"T014",'Prácticas_Revisiones'!$T$2:$T$282,"SOFTWARE QUALITY > *")+COUNTIFS('Prácticas_Snowballing'!$AB$2:$AB$281,"T014",'Prácticas_Snowballing'!$AC$2:$AC$281,"SOFTWARE QUALITY > *") -> 0 | N21: =COUNTIFS('Prácticas_Revisiones'!$S$2:$S$282,"T014",'Prácticas_Revisiones'!$T$2:$T$282,"SOFTWARE SECURITY > *")+COUNTIFS('Prácticas_Snowballing'!$AB$2:$AB$281,"T014",'Prácticas_Snowballing'!$AC$2:$AC$281,"SOFTWARE SECURITY > *") -> 0 | O21: =COUNTIFS('Prácticas_Revisiones'!$S$2:$S$282,"T014",'Prácticas_Revisiones'!$T$2:$T$282,"PROFESSIONAL PRACTICE > *")+COUNTIFS('Prácticas_Snowballing'!$AB$2:$AB$281,"T014",'Prácticas_Snowballing'!$AC$2:$AC$281,"PROFESSIONAL PRACTICE > *") -> 0 | P21: =COUNTIFS('Prácticas_Revisiones'!$S$2:$S$282,"T014",'Prácticas_Revisiones'!$T$2:$T$282,"SOFTWARE ENG. ECONOMICS > *")+COUNTIFS('Prácticas_Snowballing'!$AB$2:$AB$281,"T014",'Prácticas_Snowballing'!$AC$2:$AC$281,"SOFTWARE ENG. ECONOMICS > *") -> 0 | Q21: =COUNTIFS('Prácticas_Revisiones'!$S$2:$S$282,"T014",'Prácticas_Revisiones'!$T$2:$T$282,"SOFTWARE ENG. MANAGEMENT > *")+COUNTIFS('Prácticas_Snowballing'!$AB$2:$AB$281,"T014",'Prácticas_Snowballing'!$AC$2:$AC$281,"SOFTWARE ENG. MANAGEMENT > *") -> 0 | R21: =COUNTIFS('Prácticas_Revisiones'!$S$2:$S$282,"T014",'Prácticas_Revisiones'!$T$2:$T$282,"Sin área SWEBOK")+COUNTIFS('Prácticas_Snowballing'!$AB$2:$AB$281,"T014",'Prácticas_Snowballing'!$AC$2:$AC$281,"Sin área SWEBOK") -> 0 | S21: =SUM(C21:R21) -> 0
B22: T015 Atributos | C22: =COUNTIFS('Prácticas_Revisiones'!$S$2:$S$282,"T015",'Prácticas_Revisiones'!$T$2:$T$282,"REQUIREMENTS > *")+COUNTIFS('Prácticas_Snowballing'!$AB$2:$AB$281,"T015",'Prácticas_Snowballing'!$AC$2:$AC$281,"REQUIREMENTS > *") -> 0 | D22: =COUNTIFS('Prácticas_Revisiones'!$S$2:$S$282,"T015",'Prácticas_Revisiones'!$T$2:$T$282,"ARCHITECTURE > *")+COUNTIFS('Prácticas_Snowballing'!$AB$2:$AB$281,"T015",'Prácticas_Snowballing'!$AC$2:$AC$281,"ARCHITECTURE > *") -> 0 | E22: =COUNTIFS('Prácticas_Revisiones'!$S$2:$S$282,"T015",'Prácticas_Revisiones'!$T$2:$T$282,"DESIGN > *")+COUNTIFS('Prácticas_Snowballing'!$AB$2:$AB$281,"T015",'Prácticas_Snowballing'!$AC$2:$AC$281,"DESIGN > *") -> 0 | F22: =COUNTIFS('Prácticas_Revisiones'!$S$2:$S$282,"T015",'Prácticas_Revisiones'!$T$2:$T$282,"CONSTRUCTION > *")+COUNTIFS('Prácticas_Snowballing'!$AB$2:$AB$281,"T015",'Prácticas_Snowballing'!$AC$2:$AC$281,"CONSTRUCTION > *") -> 0 | G22: =COUNTIFS('Prácticas_Revisiones'!$S$2:$S$282,"T015",'Prácticas_Revisiones'!$T$2:$T$282,"SOFTWARE TESTING > *")+COUNTIFS('Prácticas_Snowballing'!$AB$2:$AB$281,"T015",'Prácticas_Snowballing'!$AC$2:$AC$281,"SOFTWARE TESTING > *") -> 0 | H22: =COUNTIFS('Prácticas_Revisiones'!$S$2:$S$282,"T015",'Prácticas_Revisiones'!$T$2:$T$282,"SOFTWARE ENG. OPERATIONS > *")+COUNTIFS('Prácticas_Snowballing'!$AB$2:$AB$281,"T015",'Prácticas_Snowballing'!$AC$2:$AC$281,"SOFTWARE ENG. OPERATIONS > *") -> 0 | I22: =COUNTIFS('Prácticas_Revisiones'!$S$2:$S$282,"T015",'Prácticas_Revisiones'!$T$2:$T$282,"MAINTENANCE > *")+COUNTIFS('Prácticas_Snowballing'!$AB$2:$AB$281,"T015",'Prácticas_Snowballing'!$AC$2:$AC$281,"MAINTENANCE > *") -> 0 | J22: =COUNTIFS('Prácticas_Revisiones'!$S$2:$S$282,"T015",'Prácticas_Revisiones'!$T$2:$T$282,"SOFTWARE CONFIG. MGMT. > *")+COUNTIFS('Prácticas_Snowballing'!$AB$2:$AB$281,"T015",'Prácticas_Snowballing'!$AC$2:$AC$281,"SOFTWARE CONFIG. MGMT. > *") -> 0 | K22: =COUNTIFS('Prácticas_Revisiones'!$S$2:$S$282,"T015",'Prácticas_Revisiones'!$T$2:$T$282,"SOFTWARE ENG. PROCESS > *")+COUNTIFS('Prácticas_Snowballing'!$AB$2:$AB$281,"T015",'Prácticas_Snowballing'!$AC$2:$AC$281,"SOFTWARE ENG. PROCESS > *") -> 0 | L22: =COUNTIFS('Prácticas_Revisiones'!$S$2:$S$282,"T015",'Prácticas_Revisiones'!$T$2:$T$282,"SOFTWARE ENG. MODELS/METH. > *")+COUNTIFS('Prácticas_Snowballing'!$AB$2:$AB$281,"T015",'Prácticas_Snowballing'!$AC$2:$AC$281,"SOFTWARE ENG. MODELS/METH. > *") -> 0 | M22: =COUNTIFS('Prácticas_Revisiones'!$S$2:$S$282,"T015",'Prácticas_Revisiones'!$T$2:$T$282,"SOFTWARE QUALITY > *")+COUNTIFS('Prácticas_Snowballing'!$AB$2:$AB$281,"T015",'Prácticas_Snowballing'!$AC$2:$AC$281,"SOFTWARE QUALITY > *") -> 0 | N22: =COUNTIFS('Prácticas_Revisiones'!$S$2:$S$282,"T015",'Prácticas_Revisiones'!$T$2:$T$282,"SOFTWARE SECURITY > *")+COUNTIFS('Prácticas_Snowballing'!$AB$2:$AB$281,"T015",'Prácticas_Snowballing'!$AC$2:$AC$281,"SOFTWARE SECURITY > *") -> 0 | O22: =COUNTIFS('Prácticas_Revisiones'!$S$2:$S$282,"T015",'Prácticas_Revisiones'!$T$2:$T$282,"PROFESSIONAL PRACTICE > *")+COUNTIFS('Prácticas_Snowballing'!$AB$2:$AB$281,"T015",'Prácticas_Snowballing'!$AC$2:$AC$281,"PROFESSIONAL PRACTICE > *") -> 0 | P22: =COUNTIFS('Prácticas_Revisiones'!$S$2:$S$282,"T015",'Prácticas_Revisiones'!$T$2:$T$282,"SOFTWARE ENG. ECONOMICS > *")+COUNTIFS('Prácticas_Snowballing'!$AB$2:$AB$281,"T015",'Prácticas_Snowballing'!$AC$2:$AC$281,"SOFTWARE ENG. ECONOMICS > *") -> 0 | Q22: =COUNTIFS('Prácticas_Revisiones'!$S$2:$S$282,"T015",'Prácticas_Revisiones'!$T$2:$T$282,"SOFTWARE ENG. MANAGEMENT > *")+COUNTIFS('Prácticas_Snowballing'!$AB$2:$AB$281,"T015",'Prácticas_Snowballing'!$AC$2:$AC$281,"SOFTWARE ENG. MANAGEMENT > *") -> 0 | R22: =COUNTIFS('Prácticas_Revisiones'!$S$2:$S$282,"T015",'Prácticas_Revisiones'!$T$2:$T$282,"Sin área SWEBOK")+COUNTIFS('Prácticas_Snowballing'!$AB$2:$AB$281,"T015",'Prácticas_Snowballing'!$AC$2:$AC$281,"Sin área SWEBOK") -> 0 | S22: =SUM(C22:R22) -> 0
B23: T016 Auto-explicación | C23: =COUNTIFS('Prácticas_Revisiones'!$S$2:$S$282,"T016",'Prácticas_Revisiones'!$T$2:$T$282,"REQUIREMENTS > *")+COUNTIFS('Prácticas_Snowballing'!$AB$2:$AB$281,"T016",'Prácticas_Snowballing'!$AC$2:$AC$281,"REQUIREMENTS > *") -> 0 | D23: =COUNTIFS('Prácticas_Revisiones'!$S$2:$S$282,"T016",'Prácticas_Revisiones'!$T$2:$T$282,"ARCHITECTURE > *")+COUNTIFS('Prácticas_Snowballing'!$AB$2:$AB$281,"T016",'Prácticas_Snowballing'!$AC$2:$AC$281,"ARCHITECTURE > *") -> 0 | E23: =COUNTIFS('Prácticas_Revisiones'!$S$2:$S$282,"T016",'Prácticas_Revisiones'!$T$2:$T$282,"DESIGN > *")+COUNTIFS('Prácticas_Snowballing'!$AB$2:$AB$281,"T016",'Prácticas_Snowballing'!$AC$2:$AC$281,"DESIGN > *") -> 0 | F23: =COUNTIFS('Prácticas_Revisiones'!$S$2:$S$282,"T016",'Prácticas_Revisiones'!$T$2:$T$282,"CONSTRUCTION > *")+COUNTIFS('Prácticas_Snowballing'!$AB$2:$AB$281,"T016",'Prácticas_Snowballing'!$AC$2:$AC$281,"CONSTRUCTION > *") -> 9 | G23: =COUNTIFS('Prácticas_Revisiones'!$S$2:$S$282,"T016",'Prácticas_Revisiones'!$T$2:$T$282,"SOFTWARE TESTING > *")+COUNTIFS('Prácticas_Snowballing'!$AB$2:$AB$281,"T016",'Prácticas_Snowballing'!$AC$2:$AC$281,"SOFTWARE TESTING > *") -> 0 | H23: =COUNTIFS('Prácticas_Revisiones'!$S$2:$S$282,"T016",'Prácticas_Revisiones'!$T$2:$T$282,"SOFTWARE ENG. OPERATIONS > *")+COUNTIFS('Prácticas_Snowballing'!$AB$2:$AB$281,"T016",'Prácticas_Snowballing'!$AC$2:$AC$281,"SOFTWARE ENG. OPERATIONS > *") -> 0 | I23: =COUNTIFS('Prácticas_Revisiones'!$S$2:$S$282,"T016",'Prácticas_Revisiones'!$T$2:$T$282,"MAINTENANCE > *")+COUNTIFS('Prácticas_Snowballing'!$AB$2:$AB$281,"T016",'Prácticas_Snowballing'!$AC$2:$AC$281,"MAINTENANCE > *") -> 1 | J23: =COUNTIFS('Prácticas_Revisiones'!$S$2:$S$282,"T016",'Prácticas_Revisiones'!$T$2:$T$282,"SOFTWARE CONFIG. MGMT. > *")+COUNTIFS('Prácticas_Snowballing'!$AB$2:$AB$281,"T016",'Prácticas_Snowballing'!$AC$2:$AC$281,"SOFTWARE CONFIG. MGMT. > *") -> 0 | K23: =COUNTIFS('Prácticas_Revisiones'!$S$2:$S$282,"T016",'Prácticas_Revisiones'!$T$2:$T$282,"SOFTWARE ENG. PROCESS > *")+COUNTIFS('Prácticas_Snowballing'!$AB$2:$AB$281,"T016",'Prácticas_Snowballing'!$AC$2:$AC$281,"SOFTWARE ENG. PROCESS > *") -> 0 | L23: =COUNTIFS('Prácticas_Revisiones'!$S$2:$S$282,"T016",'Prácticas_Revisiones'!$T$2:$T$282,"SOFTWARE ENG. MODELS/METH. > *")+COUNTIFS('Prácticas_Snowballing'!$AB$2:$AB$281,"T016",'Prácticas_Snowballing'!$AC$2:$AC$281,"SOFTWARE ENG. MODELS/METH. > *") -> 0 | M23: =COUNTIFS('Prácticas_Revisiones'!$S$2:$S$282,"T016",'Prácticas_Revisiones'!$T$2:$T$282,"SOFTWARE QUALITY > *")+COUNTIFS('Prácticas_Snowballing'!$AB$2:$AB$281,"T016",'Prácticas_Snowballing'!$AC$2:$AC$281,"SOFTWARE QUALITY > *") -> 0 | N23: =COUNTIFS('Prácticas_Revisiones'!$S$2:$S$282,"T016",'Prácticas_Revisiones'!$T$2:$T$282,"SOFTWARE SECURITY > *")+COUNTIFS('Prácticas_Snowballing'!$AB$2:$AB$281,"T016",'Prácticas_Snowballing'!$AC$2:$AC$281,"SOFTWARE SECURITY > *") -> 0 | O23: =COUNTIFS('Prácticas_Revisiones'!$S$2:$S$282,"T016",'Prácticas_Revisiones'!$T$2:$T$282,"PROFESSIONAL PRACTICE > *")+COUNTIFS('Prácticas_Snowballing'!$AB$2:$AB$281,"T016",'Prácticas_Snowballing'!$AC$2:$AC$281,"PROFESSIONAL PRACTICE > *") -> 0 | P23: =COUNTIFS('Prácticas_Revisiones'!$S$2:$S$282,"T016",'Prácticas_Revisiones'!$T$2:$T$282,"SOFTWARE ENG. ECONOMICS > *")+COUNTIFS('Prácticas_Snowballing'!$AB$2:$AB$281,"T016",'Prácticas_Snowballing'!$AC$2:$AC$281,"SOFTWARE ENG. ECONOMICS > *") -> 0 | Q23: =COUNTIFS('Prácticas_Revisiones'!$S$2:$S$282,"T016",'Prácticas_Revisiones'!$T$2:$T$282,"SOFTWARE ENG. MANAGEMENT > *")+COUNTIFS('Prácticas_Snowballing'!$AB$2:$AB$281,"T016",'Prácticas_Snowballing'!$AC$2:$AC$281,"SOFTWARE ENG. MANAGEMENT > *") -> 0 | R23: =COUNTIFS('Prácticas_Revisiones'!$S$2:$S$282,"T016",'Prácticas_Revisiones'!$T$2:$T$282,"Sin área SWEBOK")+COUNTIFS('Prácticas_Snowballing'!$AB$2:$AB$281,"T016",'Prácticas_Snowballing'!$AC$2:$AC$281,"Sin área SWEBOK") -> 0 | S23: =SUM(C23:R23) -> 10
B24: T017 Cartel | C24: =COUNTIFS('Prácticas_Revisiones'!$S$2:$S$282,"T017",'Prácticas_Revisiones'!$T$2:$T$282,"REQUIREMENTS > *")+COUNTIFS('Prácticas_Snowballing'!$AB$2:$AB$281,"T017",'Prácticas_Snowballing'!$AC$2:$AC$281,"REQUIREMENTS > *") -> 0 | D24: =COUNTIFS('Prácticas_Revisiones'!$S$2:$S$282,"T017",'Prácticas_Revisiones'!$T$2:$T$282,"ARCHITECTURE > *")+COUNTIFS('Prácticas_Snowballing'!$AB$2:$AB$281,"T017",'Prácticas_Snowballing'!$AC$2:$AC$281,"ARCHITECTURE > *") -> 0 | E24: =COUNTIFS('Prácticas_Revisiones'!$S$2:$S$282,"T017",'Prácticas_Revisiones'!$T$2:$T$282,"DESIGN > *")+COUNTIFS('Prácticas_Snowballing'!$AB$2:$AB$281,"T017",'Prácticas_Snowballing'!$AC$2:$AC$281,"DESIGN > *") -> 0 | F24: =COUNTIFS('Prácticas_Revisiones'!$S$2:$S$282,"T017",'Prácticas_Revisiones'!$T$2:$T$282,"CONSTRUCTION > *")+COUNTIFS('Prácticas_Snowballing'!$AB$2:$AB$281,"T017",'Prácticas_Snowballing'!$AC$2:$AC$281,"CONSTRUCTION > *") -> 0 | G24: =COUNTIFS('Prácticas_Revisiones'!$S$2:$S$282,"T017",'Prácticas_Revisiones'!$T$2:$T$282,"SOFTWARE TESTING > *")+COUNTIFS('Prácticas_Snowballing'!$AB$2:$AB$281,"T017",'Prácticas_Snowballing'!$AC$2:$AC$281,"SOFTWARE TESTING > *") -> 0 | H24: =COUNTIFS('Prácticas_Revisiones'!$S$2:$S$282,"T017",'Prácticas_Revisiones'!$T$2:$T$282,"SOFTWARE ENG. OPERATIONS > *")+COUNTIFS('Prácticas_Snowballing'!$AB$2:$AB$281,"T017",'Prácticas_Snowballing'!$AC$2:$AC$281,"SOFTWARE ENG. OPERATIONS > *") -> 0 | I24: =COUNTIFS('Prácticas_Revisiones'!$S$2:$S$282,"T017",'Prácticas_Revisiones'!$T$2:$T$282,"MAINTENANCE > *")+COUNTIFS('Prácticas_Snowballing'!$AB$2:$AB$281,"T017",'Prácticas_Snowballing'!$AC$2:$AC$281,"MAINTENANCE > *") -> 0 | J24: =COUNTIFS('Prácticas_Revisiones'!$S$2:$S$282,"T017",'Prácticas_Revisiones'!$T$2:$T$282,"SOFTWARE CONFIG. MGMT. > *")+COUNTIFS('Prácticas_Snowballing'!$AB$2:$AB$281,"T017",'Prácticas_Snowballing'!$AC$2:$AC$281,"SOFTWARE CONFIG. MGMT. > *") -> 0 | K24: =COUNTIFS('Prácticas_Revisiones'!$S$2:$S$282,"T017",'Prácticas_Revisiones'!$T$2:$T$282,"SOFTWARE ENG. PROCESS > *")+COUNTIFS('Prácticas_Snowballing'!$AB$2:$AB$281,"T017",'Prácticas_Snowballing'!$AC$2:$AC$281,"SOFTWARE ENG. PROCESS > *") -> 0 | L24: =COUNTIFS('Prácticas_Revisiones'!$S$2:$S$282,"T017",'Prácticas_Revisiones'!$T$2:$T$282,"SOFTWARE ENG. MODELS/METH. > *")+COUNTIFS('Prácticas_Snowballing'!$AB$2:$AB$281,"T017",'Prácticas_Snowballing'!$AC$2:$AC$281,"SOFTWARE ENG. MODELS/METH. > *") -> 0 | M24: =COUNTIFS('Prácticas_Revisiones'!$S$2:$S$282,"T017",'Prácticas_Revisiones'!$T$2:$T$282,"SOFTWARE QUALITY > *")+COUNTIFS('Prácticas_Snowballing'!$AB$2:$AB$281,"T017",'Prácticas_Snowballing'!$AC$2:$AC$281,"SOFTWARE QUALITY > *") -> 0 | N24: =COUNTIFS('Prácticas_Revisiones'!$S$2:$S$282,"T017",'Prácticas_Revisiones'!$T$2:$T$282,"SOFTWARE SECURITY > *")+COUNTIFS('Prácticas_Snowballing'!$AB$2:$AB$281,"T017",'Prácticas_Snowballing'!$AC$2:$AC$281,"SOFTWARE SECURITY > *") -> 0 | O24: =COUNTIFS('Prácticas_Revisiones'!$S$2:$S$282,"T017",'Prácticas_Revisiones'!$T$2:$T$282,"PROFESSIONAL PRACTICE > *")+COUNTIFS('Prácticas_Snowballing'!$AB$2:$AB$281,"T017",'Prácticas_Snowballing'!$AC$2:$AC$281,"PROFESSIONAL PRACTICE > *") -> 0 | P24: =COUNTIFS('Prácticas_Revisiones'!$S$2:$S$282,"T017",'Prácticas_Revisiones'!$T$2:$T$282,"SOFTWARE ENG. ECONOMICS > *")+COUNTIFS('Prácticas_Snowballing'!$AB$2:$AB$281,"T017",'Prácticas_Snowballing'!$AC$2:$AC$281,"SOFTWARE ENG. ECONOMICS > *") -> 0 | Q24: =COUNTIFS('Prácticas_Revisiones'!$S$2:$S$282,"T017",'Prácticas_Revisiones'!$T$2:$T$282,"SOFTWARE ENG. MANAGEMENT > *")+COUNTIFS('Prácticas_Snowballing'!$AB$2:$AB$281,"T017",'Prácticas_Snowballing'!$AC$2:$AC$281,"SOFTWARE ENG. MANAGEMENT > *") -> 0 | R24: =COUNTIFS('Prácticas_Revisiones'!$S$2:$S$282,"T017",'Prácticas_Revisiones'!$T$2:$T$282,"Sin área SWEBOK")+COUNTIFS('Prácticas_Snowballing'!$AB$2:$AB$281,"T017",'Prácticas_Snowballing'!$AC$2:$AC$281,"Sin área SWEBOK") -> 0 | S24: =SUM(C24:R24) -> 0
B25: T018 Documentales | C25: =COUNTIFS('Prácticas_Revisiones'!$S$2:$S$282,"T018",'Prácticas_Revisiones'!$T$2:$T$282,"REQUIREMENTS > *")+COUNTIFS('Prácticas_Snowballing'!$AB$2:$AB$281,"T018",'Prácticas_Snowballing'!$AC$2:$AC$281,"REQUIREMENTS > *") -> 0 | D25: =COUNTIFS('Prácticas_Revisiones'!$S$2:$S$282,"T018",'Prácticas_Revisiones'!$T$2:$T$282,"ARCHITECTURE > *")+COUNTIFS('Prácticas_Snowballing'!$AB$2:$AB$281,"T018",'Prácticas_Snowballing'!$AC$2:$AC$281,"ARCHITECTURE > *") -> 0 | E25: =COUNTIFS('Prácticas_Revisiones'!$S$2:$S$282,"T018",'Prácticas_Revisiones'!$T$2:$T$282,"DESIGN > *")+COUNTIFS('Prácticas_Snowballing'!$AB$2:$AB$281,"T018",'Prácticas_Snowballing'!$AC$2:$AC$281,"DESIGN > *") -> 0 | F25: =COUNTIFS('Prácticas_Revisiones'!$S$2:$S$282,"T018",'Prácticas_Revisiones'!$T$2:$T$282,"CONSTRUCTION > *")+COUNTIFS('Prácticas_Snowballing'!$AB$2:$AB$281,"T018",'Prácticas_Snowballing'!$AC$2:$AC$281,"CONSTRUCTION > *") -> 0 | G25: =COUNTIFS('Prácticas_Revisiones'!$S$2:$S$282,"T018",'Prácticas_Revisiones'!$T$2:$T$282,"SOFTWARE TESTING > *")+COUNTIFS('Prácticas_Snowballing'!$AB$2:$AB$281,"T018",'Prácticas_Snowballing'!$AC$2:$AC$281,"SOFTWARE TESTING > *") -> 0 | H25: =COUNTIFS('Prácticas_Revisiones'!$S$2:$S$282,"T018",'Prácticas_Revisiones'!$T$2:$T$282,"SOFTWARE ENG. OPERATIONS > *")+COUNTIFS('Prácticas_Snowballing'!$AB$2:$AB$281,"T018",'Prácticas_Snowballing'!$AC$2:$AC$281,"SOFTWARE ENG. OPERATIONS > *") -> 0 | I25: =COUNTIFS('Prácticas_Revisiones'!$S$2:$S$282,"T018",'Prácticas_Revisiones'!$T$2:$T$282,"MAINTENANCE > *")+COUNTIFS('Prácticas_Snowballing'!$AB$2:$AB$281,"T018",'Prácticas_Snowballing'!$AC$2:$AC$281,"MAINTENANCE > *") -> 0 | J25: =COUNTIFS('Prácticas_Revisiones'!$S$2:$S$282,"T018",'Prácticas_Revisiones'!$T$2:$T$282,"SOFTWARE CONFIG. MGMT. > *")+COUNTIFS('Prácticas_Snowballing'!$AB$2:$AB$281,"T018",'Prácticas_Snowballing'!$AC$2:$AC$281,"SOFTWARE CONFIG. MGMT. > *") -> 0 | K25: =COUNTIFS('Prácticas_Revisiones'!$S$2:$S$282,"T018",'Prácticas_Revisiones'!$T$2:$T$282,"SOFTWARE ENG. PROCESS > *")+COUNTIFS('Prácticas_Snowballing'!$AB$2:$AB$281,"T018",'Prácticas_Snowballing'!$AC$2:$AC$281,"SOFTWARE ENG. PROCESS > *") -> 0 | L25: =COUNTIFS('Prácticas_Revisiones'!$S$2:$S$282,"T018",'Prácticas_Revisiones'!$T$2:$T$282,"SOFTWARE ENG. MODELS/METH. > *")+COUNTIFS('Prácticas_Snowballing'!$AB$2:$AB$281,"T018",'Prácticas_Snowballing'!$AC$2:$AC$281,"SOFTWARE ENG. MODELS/METH. > *") -> 0 | M25: =COUNTIFS('Prácticas_Revisiones'!$S$2:$S$282,"T018",'Prácticas_Revisiones'!$T$2:$T$282,"SOFTWARE QUALITY > *")+COUNTIFS('Prácticas_Snowballing'!$AB$2:$AB$281,"T018",'Prácticas_Snowballing'!$AC$2:$AC$281,"SOFTWARE QUALITY > *") -> 0 | N25: =COUNTIFS('Prácticas_Revisiones'!$S$2:$S$282,"T018",'Prácticas_Revisiones'!$T$2:$T$282,"SOFTWARE SECURITY > *")+COUNTIFS('Prácticas_Snowballing'!$AB$2:$AB$281,"T018",'Prácticas_Snowballing'!$AC$2:$AC$281,"SOFTWARE SECURITY > *") -> 0 | O25: =COUNTIFS('Prácticas_Revisiones'!$S$2:$S$282,"T018",'Prácticas_Revisiones'!$T$2:$T$282,"PROFESSIONAL PRACTICE > *")+COUNTIFS('Prácticas_Snowballing'!$AB$2:$AB$281,"T018",'Prácticas_Snowballing'!$AC$2:$AC$281,"PROFESSIONAL PRACTICE > *") -> 0 | P25: =COUNTIFS('Prácticas_Revisiones'!$S$2:$S$282,"T018",'Prácticas_Revisiones'!$T$2:$T$282,"SOFTWARE ENG. ECONOMICS > *")+COUNTIFS('Prácticas_Snowballing'!$AB$2:$AB$281,"T018",'Prácticas_Snowballing'!$AC$2:$AC$281,"SOFTWARE ENG. ECONOMICS > *") -> 0 | Q25: =COUNTIFS('Prácticas_Revisiones'!$S$2:$S$282,"T018",'Prácticas_Revisiones'!$T$2:$T$282,"SOFTWARE ENG. MANAGEMENT > *")+COUNTIFS('Prácticas_Snowballing'!$AB$2:$AB$281,"T018",'Prácticas_Snowballing'!$AC$2:$AC$281,"SOFTWARE ENG. MANAGEMENT > *") -> 0 | R25: =COUNTIFS('Prácticas_Revisiones'!$S$2:$S$282,"T018",'Prácticas_Revisiones'!$T$2:$T$282,"Sin área SWEBOK")+COUNTIFS('Prácticas_Snowballing'!$AB$2:$AB$281,"T018",'Prácticas_Snowballing'!$AC$2:$AC$281,"Sin área SWEBOK") -> 0 | S25: =SUM(C25:R25) -> 0
B26: T019 Ejemplificación | C26: =COUNTIFS('Prácticas_Revisiones'!$S$2:$S$282,"T019",'Prácticas_Revisiones'!$T$2:$T$282,"REQUIREMENTS > *")+COUNTIFS('Prácticas_Snowballing'!$AB$2:$AB$281,"T019",'Prácticas_Snowballing'!$AC$2:$AC$281,"REQUIREMENTS > *") -> 0 | D26: =COUNTIFS('Prácticas_Revisiones'!$S$2:$S$282,"T019",'Prácticas_Revisiones'!$T$2:$T$282,"ARCHITECTURE > *")+COUNTIFS('Prácticas_Snowballing'!$AB$2:$AB$281,"T019",'Prácticas_Snowballing'!$AC$2:$AC$281,"ARCHITECTURE > *") -> 0 | E26: =COUNTIFS('Prácticas_Revisiones'!$S$2:$S$282,"T019",'Prácticas_Revisiones'!$T$2:$T$282,"DESIGN > *")+COUNTIFS('Prácticas_Snowballing'!$AB$2:$AB$281,"T019",'Prácticas_Snowballing'!$AC$2:$AC$281,"DESIGN > *") -> 0 | F26: =COUNTIFS('Prácticas_Revisiones'!$S$2:$S$282,"T019",'Prácticas_Revisiones'!$T$2:$T$282,"CONSTRUCTION > *")+COUNTIFS('Prácticas_Snowballing'!$AB$2:$AB$281,"T019",'Prácticas_Snowballing'!$AC$2:$AC$281,"CONSTRUCTION > *") -> 22 | G26: =COUNTIFS('Prácticas_Revisiones'!$S$2:$S$282,"T019",'Prácticas_Revisiones'!$T$2:$T$282,"SOFTWARE TESTING > *")+COUNTIFS('Prácticas_Snowballing'!$AB$2:$AB$281,"T019",'Prácticas_Snowballing'!$AC$2:$AC$281,"SOFTWARE TESTING > *") -> 0 | H26: =COUNTIFS('Prácticas_Revisiones'!$S$2:$S$282,"T019",'Prácticas_Revisiones'!$T$2:$T$282,"SOFTWARE ENG. OPERATIONS > *")+COUNTIFS('Prácticas_Snowballing'!$AB$2:$AB$281,"T019",'Prácticas_Snowballing'!$AC$2:$AC$281,"SOFTWARE ENG. OPERATIONS > *") -> 0 | I26: =COUNTIFS('Prácticas_Revisiones'!$S$2:$S$282,"T019",'Prácticas_Revisiones'!$T$2:$T$282,"MAINTENANCE > *")+COUNTIFS('Prácticas_Snowballing'!$AB$2:$AB$281,"T019",'Prácticas_Snowballing'!$AC$2:$AC$281,"MAINTENANCE > *") -> 0 | J26: =COUNTIFS('Prácticas_Revisiones'!$S$2:$S$282,"T019",'Prácticas_Revisiones'!$T$2:$T$282,"SOFTWARE CONFIG. MGMT. > *")+COUNTIFS('Prácticas_Snowballing'!$AB$2:$AB$281,"T019",'Prácticas_Snowballing'!$AC$2:$AC$281,"SOFTWARE CONFIG. MGMT. > *") -> 0 | K26: =COUNTIFS('Prácticas_Revisiones'!$S$2:$S$282,"T019",'Prácticas_Revisiones'!$T$2:$T$282,"SOFTWARE ENG. PROCESS > *")+COUNTIFS('Prácticas_Snowballing'!$AB$2:$AB$281,"T019",'Prácticas_Snowballing'!$AC$2:$AC$281,"SOFTWARE ENG. PROCESS > *") -> 0 | L26: =COUNTIFS('Prácticas_Revisiones'!$S$2:$S$282,"T019",'Prácticas_Revisiones'!$T$2:$T$282,"SOFTWARE ENG. MODELS/METH. > *")+COUNTIFS('Prácticas_Snowballing'!$AB$2:$AB$281,"T019",'Prácticas_Snowballing'!$AC$2:$AC$281,"SOFTWARE ENG. MODELS/METH. > *") -> 0 | M26: =COUNTIFS('Prácticas_Revisiones'!$S$2:$S$282,"T019",'Prácticas_Revisiones'!$T$2:$T$282,"SOFTWARE QUALITY > *")+COUNTIFS('Prácticas_Snowballing'!$AB$2:$AB$281,"T019",'Prácticas_Snowballing'!$AC$2:$AC$281,"SOFTWARE QUALITY > *") -> 1 | N26: =COUNTIFS('Prácticas_Revisiones'!$S$2:$S$282,"T019",'Prácticas_Revisiones'!$T$2:$T$282,"SOFTWARE SECURITY > *")+COUNTIFS('Prácticas_Snowballing'!$AB$2:$AB$281,"T019",'Prácticas_Snowballing'!$AC$2:$AC$281,"SOFTWARE SECURITY > *") -> 0 | O26: =COUNTIFS('Prácticas_Revisiones'!$S$2:$S$282,"T019",'Prácticas_Revisiones'!$T$2:$T$282,"PROFESSIONAL PRACTICE > *")+COUNTIFS('Prácticas_Snowballing'!$AB$2:$AB$281,"T019",'Prácticas_Snowballing'!$AC$2:$AC$281,"PROFESSIONAL PRACTICE > *") -> 0 | P26: =COUNTIFS('Prácticas_Revisiones'!$S$2:$S$282,"T019",'Prácticas_Revisiones'!$T$2:$T$282,"SOFTWARE ENG. ECONOMICS > *")+COUNTIFS('Prácticas_Snowballing'!$AB$2:$AB$281,"T019",'Prácticas_Snowballing'!$AC$2:$AC$281,"SOFTWARE ENG. ECONOMICS > *") -> 0 | Q26: =COUNTIFS('Prácticas_Revisiones'!$S$2:$S$282,"T019",'Prácticas_Revisiones'!$T$2:$T$282,"SOFTWARE ENG. MANAGEMENT > *")+COUNTIFS('Prácticas_Snowballing'!$AB$2:$AB$281,"T019",'Prácticas_Snowballing'!$AC$2:$AC$281,"SOFTWARE ENG. MANAGEMENT > *") -> 0 | R26: =COUNTIFS('Prácticas_Revisiones'!$S$2:$S$282,"T019",'Prácticas_Revisiones'!$T$2:$T$282,"Sin área SWEBOK")+COUNTIFS('Prácticas_Snowballing'!$AB$2:$AB$281,"T019",'Prácticas_Snowballing'!$AC$2:$AC$281,"Sin área SWEBOK") -> 0 | S26: =SUM(C26:R26) -> 23
B27: T020 Exposición oral | C27: =COUNTIFS('Prácticas_Revisiones'!$S$2:$S$282,"T020",'Prácticas_Revisiones'!$T$2:$T$282,"REQUIREMENTS > *")+COUNTIFS('Prácticas_Snowballing'!$AB$2:$AB$281,"T020",'Prácticas_Snowballing'!$AC$2:$AC$281,"REQUIREMENTS > *") -> 0 | D27: =COUNTIFS('Prácticas_Revisiones'!$S$2:$S$282,"T020",'Prácticas_Revisiones'!$T$2:$T$282,"ARCHITECTURE > *")+COUNTIFS('Prácticas_Snowballing'!$AB$2:$AB$281,"T020",'Prácticas_Snowballing'!$AC$2:$AC$281,"ARCHITECTURE > *") -> 0 | E27: =COUNTIFS('Prácticas_Revisiones'!$S$2:$S$282,"T020",'Prácticas_Revisiones'!$T$2:$T$282,"DESIGN > *")+COUNTIFS('Prácticas_Snowballing'!$AB$2:$AB$281,"T020",'Prácticas_Snowballing'!$AC$2:$AC$281,"DESIGN > *") -> 0 | F27: =COUNTIFS('Prácticas_Revisiones'!$S$2:$S$282,"T020",'Prácticas_Revisiones'!$T$2:$T$282,"CONSTRUCTION > *")+COUNTIFS('Prácticas_Snowballing'!$AB$2:$AB$281,"T020",'Prácticas_Snowballing'!$AC$2:$AC$281,"CONSTRUCTION > *") -> 1 | G27: =COUNTIFS('Prácticas_Revisiones'!$S$2:$S$282,"T020",'Prácticas_Revisiones'!$T$2:$T$282,"SOFTWARE TESTING > *")+COUNTIFS('Prácticas_Snowballing'!$AB$2:$AB$281,"T020",'Prácticas_Snowballing'!$AC$2:$AC$281,"SOFTWARE TESTING > *") -> 0 | H27: =COUNTIFS('Prácticas_Revisiones'!$S$2:$S$282,"T020",'Prácticas_Revisiones'!$T$2:$T$282,"SOFTWARE ENG. OPERATIONS > *")+COUNTIFS('Prácticas_Snowballing'!$AB$2:$AB$281,"T020",'Prácticas_Snowballing'!$AC$2:$AC$281,"SOFTWARE ENG. OPERATIONS > *") -> 0 | I27: =COUNTIFS('Prácticas_Revisiones'!$S$2:$S$282,"T020",'Prácticas_Revisiones'!$T$2:$T$282,"MAINTENANCE > *")+COUNTIFS('Prácticas_Snowballing'!$AB$2:$AB$281,"T020",'Prácticas_Snowballing'!$AC$2:$AC$281,"MAINTENANCE > *") -> 0 | J27: =COUNTIFS('Prácticas_Revisiones'!$S$2:$S$282,"T020",'Prácticas_Revisiones'!$T$2:$T$282,"SOFTWARE CONFIG. MGMT. > *")+COUNTIFS('Prácticas_Snowballing'!$AB$2:$AB$281,"T020",'Prácticas_Snowballing'!$AC$2:$AC$281,"SOFTWARE CONFIG. MGMT. > *") -> 0 | K27: =COUNTIFS('Prácticas_Revisiones'!$S$2:$S$282,"T020",'Prácticas_Revisiones'!$T$2:$T$282,"SOFTWARE ENG. PROCESS > *")+COUNTIFS('Prácticas_Snowballing'!$AB$2:$AB$281,"T020",'Prácticas_Snowballing'!$AC$2:$AC$281,"SOFTWARE ENG. PROCESS > *") -> 0 | L27: =COUNTIFS('Prácticas_Revisiones'!$S$2:$S$282,"T020",'Prácticas_Revisiones'!$T$2:$T$282,"SOFTWARE ENG. MODELS/METH. > *")+COUNTIFS('Prácticas_Snowballing'!$AB$2:$AB$281,"T020",'Prácticas_Snowballing'!$AC$2:$AC$281,"SOFTWARE ENG. MODELS/METH. > *") -> 0 | M27: =COUNTIFS('Prácticas_Revisiones'!$S$2:$S$282,"T020",'Prácticas_Revisiones'!$T$2:$T$282,"SOFTWARE QUALITY > *")+COUNTIFS('Prácticas_Snowballing'!$AB$2:$AB$281,"T020",'Prácticas_Snowballing'!$AC$2:$AC$281,"SOFTWARE QUALITY > *") -> 0 | N27: =COUNTIFS('Prácticas_Revisiones'!$S$2:$S$282,"T020",'Prácticas_Revisiones'!$T$2:$T$282,"SOFTWARE SECURITY > *")+COUNTIFS('Prácticas_Snowballing'!$AB$2:$AB$281,"T020",'Prácticas_Snowballing'!$AC$2:$AC$281,"SOFTWARE SECURITY > *") -> 0 | O27: =COUNTIFS('Prácticas_Revisiones'!$S$2:$S$282,"T020",'Prácticas_Revisiones'!$T$2:$T$282,"PROFESSIONAL PRACTICE > *")+COUNTIFS('Prácticas_Snowballing'!$AB$2:$AB$281,"T020",'Prácticas_Snowballing'!$AC$2:$AC$281,"PROFESSIONAL PRACTICE > *") -> 0 | P27: =COUNTIFS('Prácticas_Revisiones'!$S$2:$S$282,"T020",'Prácticas_Revisiones'!$T$2:$T$282,"SOFTWARE ENG. ECONOMICS > *")+COUNTIFS('Prácticas_Snowballing'!$AB$2:$AB$281,"T020",'Prácticas_Snowballing'!$AC$2:$AC$281,"SOFTWARE ENG. ECONOMICS > *") -> 0 | Q27: =COUNTIFS('Prácticas_Revisiones'!$S$2:$S$282,"T020",'Prácticas_Revisiones'!$T$2:$T$282,"SOFTWARE ENG. MANAGEMENT > *")+COUNTIFS('Prácticas_Snowballing'!$AB$2:$AB$281,"T020",'Prácticas_Snowballing'!$AC$2:$AC$281,"SOFTWARE ENG. MANAGEMENT > *") -> 0 | R27: =COUNTIFS('Prácticas_Revisiones'!$S$2:$S$282,"T020",'Prácticas_Revisiones'!$T$2:$T$282,"Sin área SWEBOK")+COUNTIFS('Prácticas_Snowballing'!$AB$2:$AB$281,"T020",'Prácticas_Snowballing'!$AC$2:$AC$281,"Sin área SWEBOK") -> 0 | S27: =SUM(C27:R27) -> 1
B28: T021 Feynman | C28: =COUNTIFS('Prácticas_Revisiones'!$S$2:$S$282,"T021",'Prácticas_Revisiones'!$T$2:$T$282,"REQUIREMENTS > *")+COUNTIFS('Prácticas_Snowballing'!$AB$2:$AB$281,"T021",'Prácticas_Snowballing'!$AC$2:$AC$281,"REQUIREMENTS > *") -> 0 | D28: =COUNTIFS('Prácticas_Revisiones'!$S$2:$S$282,"T021",'Prácticas_Revisiones'!$T$2:$T$282,"ARCHITECTURE > *")+COUNTIFS('Prácticas_Snowballing'!$AB$2:$AB$281,"T021",'Prácticas_Snowballing'!$AC$2:$AC$281,"ARCHITECTURE > *") -> 0 | E28: =COUNTIFS('Prácticas_Revisiones'!$S$2:$S$282,"T021",'Prácticas_Revisiones'!$T$2:$T$282,"DESIGN > *")+COUNTIFS('Prácticas_Snowballing'!$AB$2:$AB$281,"T021",'Prácticas_Snowballing'!$AC$2:$AC$281,"DESIGN > *") -> 1 | F28: =COUNTIFS('Prácticas_Revisiones'!$S$2:$S$282,"T021",'Prácticas_Revisiones'!$T$2:$T$282,"CONSTRUCTION > *")+COUNTIFS('Prácticas_Snowballing'!$AB$2:$AB$281,"T021",'Prácticas_Snowballing'!$AC$2:$AC$281,"CONSTRUCTION > *") -> 5 | G28: =COUNTIFS('Prácticas_Revisiones'!$S$2:$S$282,"T021",'Prácticas_Revisiones'!$T$2:$T$282,"SOFTWARE TESTING > *")+COUNTIFS('Prácticas_Snowballing'!$AB$2:$AB$281,"T021",'Prácticas_Snowballing'!$AC$2:$AC$281,"SOFTWARE TESTING > *") -> 0 | H28: =COUNTIFS('Prácticas_Revisiones'!$S$2:$S$282,"T021",'Prácticas_Revisiones'!$T$2:$T$282,"SOFTWARE ENG. OPERATIONS > *")+COUNTIFS('Prácticas_Snowballing'!$AB$2:$AB$281,"T021",'Prácticas_Snowballing'!$AC$2:$AC$281,"SOFTWARE ENG. OPERATIONS > *") -> 0 | I28: =COUNTIFS('Prácticas_Revisiones'!$S$2:$S$282,"T021",'Prácticas_Revisiones'!$T$2:$T$282,"MAINTENANCE > *")+COUNTIFS('Prácticas_Snowballing'!$AB$2:$AB$281,"T021",'Prácticas_Snowballing'!$AC$2:$AC$281,"MAINTENANCE > *") -> 0 | J28: =COUNTIFS('Prácticas_Revisiones'!$S$2:$S$282,"T021",'Prácticas_Revisiones'!$T$2:$T$282,"SOFTWARE CONFIG. MGMT. > *")+COUNTIFS('Prácticas_Snowballing'!$AB$2:$AB$281,"T021",'Prácticas_Snowballing'!$AC$2:$AC$281,"SOFTWARE CONFIG. MGMT. > *") -> 0 | K28: =COUNTIFS('Prácticas_Revisiones'!$S$2:$S$282,"T021",'Prácticas_Revisiones'!$T$2:$T$282,"SOFTWARE ENG. PROCESS > *")+COUNTIFS('Prácticas_Snowballing'!$AB$2:$AB$281,"T021",'Prácticas_Snowballing'!$AC$2:$AC$281,"SOFTWARE ENG. PROCESS > *") -> 0 | L28: =COUNTIFS('Prácticas_Revisiones'!$S$2:$S$282,"T021",'Prácticas_Revisiones'!$T$2:$T$282,"SOFTWARE ENG. MODELS/METH. > *")+COUNTIFS('Prácticas_Snowballing'!$AB$2:$AB$281,"T021",'Prácticas_Snowballing'!$AC$2:$AC$281,"SOFTWARE ENG. MODELS/METH. > *") -> 0 | M28: =COUNTIFS('Prácticas_Revisiones'!$S$2:$S$282,"T021",'Prácticas_Revisiones'!$T$2:$T$282,"SOFTWARE QUALITY > *")+COUNTIFS('Prácticas_Snowballing'!$AB$2:$AB$281,"T021",'Prácticas_Snowballing'!$AC$2:$AC$281,"SOFTWARE QUALITY > *") -> 0 | N28: =COUNTIFS('Prácticas_Revisiones'!$S$2:$S$282,"T021",'Prácticas_Revisiones'!$T$2:$T$282,"SOFTWARE SECURITY > *")+COUNTIFS('Prácticas_Snowballing'!$AB$2:$AB$281,"T021",'Prácticas_Snowballing'!$AC$2:$AC$281,"SOFTWARE SECURITY > *") -> 0 | O28: =COUNTIFS('Prácticas_Revisiones'!$S$2:$S$282,"T021",'Prácticas_Revisiones'!$T$2:$T$282,"PROFESSIONAL PRACTICE > *")+COUNTIFS('Prácticas_Snowballing'!$AB$2:$AB$281,"T021",'Prácticas_Snowballing'!$AC$2:$AC$281,"PROFESSIONAL PRACTICE > *") -> 0 | P28: =COUNTIFS('Prácticas_Revisiones'!$S$2:$S$282,"T021",'Prácticas_Revisiones'!$T$2:$T$282,"SOFTWARE ENG. ECONOMICS > *")+COUNTIFS('Prácticas_Snowballing'!$AB$2:$AB$281,"T021",'Prácticas_Snowballing'!$AC$2:$AC$281,"SOFTWARE ENG. ECONOMICS > *") -> 0 | Q28: =COUNTIFS('Prácticas_Revisiones'!$S$2:$S$282,"T021",'Prácticas_Revisiones'!$T$2:$T$282,"SOFTWARE ENG. MANAGEMENT > *")+COUNTIFS('Prácticas_Snowballing'!$AB$2:$AB$281,"T021",'Prácticas_Snowballing'!$AC$2:$AC$281,"SOFTWARE ENG. MANAGEMENT > *") -> 0 | R28: =COUNTIFS('Prácticas_Revisiones'!$S$2:$S$282,"T021",'Prácticas_Revisiones'!$T$2:$T$282,"Sin área SWEBOK")+COUNTIFS('Prácticas_Snowballing'!$AB$2:$AB$281,"T021",'Prácticas_Snowballing'!$AC$2:$AC$281,"Sin área SWEBOK") -> 0 | S28: =SUM(C28:R28) -> 6
B29: T022 Glosario colaborativo | C29: =COUNTIFS('Prácticas_Revisiones'!$S$2:$S$282,"T022",'Prácticas_Revisiones'!$T$2:$T$282,"REQUIREMENTS > *")+COUNTIFS('Prácticas_Snowballing'!$AB$2:$AB$281,"T022",'Prácticas_Snowballing'!$AC$2:$AC$281,"REQUIREMENTS > *") -> 0 | D29: =COUNTIFS('Prácticas_Revisiones'!$S$2:$S$282,"T022",'Prácticas_Revisiones'!$T$2:$T$282,"ARCHITECTURE > *")+COUNTIFS('Prácticas_Snowballing'!$AB$2:$AB$281,"T022",'Prácticas_Snowballing'!$AC$2:$AC$281,"ARCHITECTURE > *") -> 0 | E29: =COUNTIFS('Prácticas_Revisiones'!$S$2:$S$282,"T022",'Prácticas_Revisiones'!$T$2:$T$282,"DESIGN > *")+COUNTIFS('Prácticas_Snowballing'!$AB$2:$AB$281,"T022",'Prácticas_Snowballing'!$AC$2:$AC$281,"DESIGN > *") -> 0 | F29: =COUNTIFS('Prácticas_Revisiones'!$S$2:$S$282,"T022",'Prácticas_Revisiones'!$T$2:$T$282,"CONSTRUCTION > *")+COUNTIFS('Prácticas_Snowballing'!$AB$2:$AB$281,"T022",'Prácticas_Snowballing'!$AC$2:$AC$281,"CONSTRUCTION > *") -> 0 | G29: =COUNTIFS('Prácticas_Revisiones'!$S$2:$S$282,"T022",'Prácticas_Revisiones'!$T$2:$T$282,"SOFTWARE TESTING > *")+COUNTIFS('Prácticas_Snowballing'!$AB$2:$AB$281,"T022",'Prácticas_Snowballing'!$AC$2:$AC$281,"SOFTWARE TESTING > *") -> 0 | H29: =COUNTIFS('Prácticas_Revisiones'!$S$2:$S$282,"T022",'Prácticas_Revisiones'!$T$2:$T$282,"SOFTWARE ENG. OPERATIONS > *")+COUNTIFS('Prácticas_Snowballing'!$AB$2:$AB$281,"T022",'Prácticas_Snowballing'!$AC$2:$AC$281,"SOFTWARE ENG. OPERATIONS > *") -> 0 | I29: =COUNTIFS('Prácticas_Revisiones'!$S$2:$S$282,"T022",'Prácticas_Revisiones'!$T$2:$T$282,"MAINTENANCE > *")+COUNTIFS('Prácticas_Snowballing'!$AB$2:$AB$281,"T022",'Prácticas_Snowballing'!$AC$2:$AC$281,"MAINTENANCE > *") -> 0 | J29: =COUNTIFS('Prácticas_Revisiones'!$S$2:$S$282,"T022",'Prácticas_Revisiones'!$T$2:$T$282,"SOFTWARE CONFIG. MGMT. > *")+COUNTIFS('Prácticas_Snowballing'!$AB$2:$AB$281,"T022",'Prácticas_Snowballing'!$AC$2:$AC$281,"SOFTWARE CONFIG. MGMT. > *") -> 0 | K29: =COUNTIFS('Prácticas_Revisiones'!$S$2:$S$282,"T022",'Prácticas_Revisiones'!$T$2:$T$282,"SOFTWARE ENG. PROCESS > *")+COUNTIFS('Prácticas_Snowballing'!$AB$2:$AB$281,"T022",'Prácticas_Snowballing'!$AC$2:$AC$281,"SOFTWARE ENG. PROCESS > *") -> 0 | L29: =COUNTIFS('Prácticas_Revisiones'!$S$2:$S$282,"T022",'Prácticas_Revisiones'!$T$2:$T$282,"SOFTWARE ENG. MODELS/METH. > *")+COUNTIFS('Prácticas_Snowballing'!$AB$2:$AB$281,"T022",'Prácticas_Snowballing'!$AC$2:$AC$281,"SOFTWARE ENG. MODELS/METH. > *") -> 0 | M29: =COUNTIFS('Prácticas_Revisiones'!$S$2:$S$282,"T022",'Prácticas_Revisiones'!$T$2:$T$282,"SOFTWARE QUALITY > *")+COUNTIFS('Prácticas_Snowballing'!$AB$2:$AB$281,"T022",'Prácticas_Snowballing'!$AC$2:$AC$281,"SOFTWARE QUALITY > *") -> 0 | N29: =COUNTIFS('Prácticas_Revisiones'!$S$2:$S$282,"T022",'Prácticas_Revisiones'!$T$2:$T$282,"SOFTWARE SECURITY > *")+COUNTIFS('Prácticas_Snowballing'!$AB$2:$AB$281,"T022",'Prácticas_Snowballing'!$AC$2:$AC$281,"SOFTWARE SECURITY > *") -> 0 | O29: =COUNTIFS('Prácticas_Revisiones'!$S$2:$S$282,"T022",'Prácticas_Revisiones'!$T$2:$T$282,"PROFESSIONAL PRACTICE > *")+COUNTIFS('Prácticas_Snowballing'!$AB$2:$AB$281,"T022",'Prácticas_Snowballing'!$AC$2:$AC$281,"PROFESSIONAL PRACTICE > *") -> 0 | P29: =COUNTIFS('Prácticas_Revisiones'!$S$2:$S$282,"T022",'Prácticas_Revisiones'!$T$2:$T$282,"SOFTWARE ENG. ECONOMICS > *")+COUNTIFS('Prácticas_Snowballing'!$AB$2:$AB$281,"T022",'Prácticas_Snowballing'!$AC$2:$AC$281,"SOFTWARE ENG. ECONOMICS > *") -> 0 | Q29: =COUNTIFS('Prácticas_Revisiones'!$S$2:$S$282,"T022",'Prácticas_Revisiones'!$T$2:$T$282,"SOFTWARE ENG. MANAGEMENT > *")+COUNTIFS('Prácticas_Snowballing'!$AB$2:$AB$281,"T022",'Prácticas_Snowballing'!$AC$2:$AC$281,"SOFTWARE ENG. MANAGEMENT > *") -> 0 | R29: =COUNTIFS('Prácticas_Revisiones'!$S$2:$S$282,"T022",'Prácticas_Revisiones'!$T$2:$T$282,"Sin área SWEBOK")+COUNTIFS('Prácticas_Snowballing'!$AB$2:$AB$281,"T022",'Prácticas_Snowballing'!$AC$2:$AC$281,"Sin área SWEBOK") -> 0 | S29: =SUM(C29:R29) -> 0
B30: T023 Grupos focales | C30: =COUNTIFS('Prácticas_Revisiones'!$S$2:$S$282,"T023",'Prácticas_Revisiones'!$T$2:$T$282,"REQUIREMENTS > *")+COUNTIFS('Prácticas_Snowballing'!$AB$2:$AB$281,"T023",'Prácticas_Snowballing'!$AC$2:$AC$281,"REQUIREMENTS > *") -> 0 | D30: =COUNTIFS('Prácticas_Revisiones'!$S$2:$S$282,"T023",'Prácticas_Revisiones'!$T$2:$T$282,"ARCHITECTURE > *")+COUNTIFS('Prácticas_Snowballing'!$AB$2:$AB$281,"T023",'Prácticas_Snowballing'!$AC$2:$AC$281,"ARCHITECTURE > *") -> 0 | E30: =COUNTIFS('Prácticas_Revisiones'!$S$2:$S$282,"T023",'Prácticas_Revisiones'!$T$2:$T$282,"DESIGN > *")+COUNTIFS('Prácticas_Snowballing'!$AB$2:$AB$281,"T023",'Prácticas_Snowballing'!$AC$2:$AC$281,"DESIGN > *") -> 0 | F30: =COUNTIFS('Prácticas_Revisiones'!$S$2:$S$282,"T023",'Prácticas_Revisiones'!$T$2:$T$282,"CONSTRUCTION > *")+COUNTIFS('Prácticas_Snowballing'!$AB$2:$AB$281,"T023",'Prácticas_Snowballing'!$AC$2:$AC$281,"CONSTRUCTION > *") -> 0 | G30: =COUNTIFS('Prácticas_Revisiones'!$S$2:$S$282,"T023",'Prácticas_Revisiones'!$T$2:$T$282,"SOFTWARE TESTING > *")+COUNTIFS('Prácticas_Snowballing'!$AB$2:$AB$281,"T023",'Prácticas_Snowballing'!$AC$2:$AC$281,"SOFTWARE TESTING > *") -> 0 | H30: =COUNTIFS('Prácticas_Revisiones'!$S$2:$S$282,"T023",'Prácticas_Revisiones'!$T$2:$T$282,"SOFTWARE ENG. OPERATIONS > *")+COUNTIFS('Prácticas_Snowballing'!$AB$2:$AB$281,"T023",'Prácticas_Snowballing'!$AC$2:$AC$281,"SOFTWARE ENG. OPERATIONS > *") -> 0 | I30: =COUNTIFS('Prácticas_Revisiones'!$S$2:$S$282,"T023",'Prácticas_Revisiones'!$T$2:$T$282,"MAINTENANCE > *")+COUNTIFS('Prácticas_Snowballing'!$AB$2:$AB$281,"T023",'Prácticas_Snowballing'!$AC$2:$AC$281,"MAINTENANCE > *") -> 0 | J30: =COUNTIFS('Prácticas_Revisiones'!$S$2:$S$282,"T023",'Prácticas_Revisiones'!$T$2:$T$282,"SOFTWARE CONFIG. MGMT. > *")+COUNTIFS('Prácticas_Snowballing'!$AB$2:$AB$281,"T023",'Prácticas_Snowballing'!$AC$2:$AC$281,"SOFTWARE CONFIG. MGMT. > *") -> 0 | K30: =COUNTIFS('Prácticas_Revisiones'!$S$2:$S$282,"T023",'Prácticas_Revisiones'!$T$2:$T$282,"SOFTWARE ENG. PROCESS > *")+COUNTIFS('Prácticas_Snowballing'!$AB$2:$AB$281,"T023",'Prácticas_Snowballing'!$AC$2:$AC$281,"SOFTWARE ENG. PROCESS > *") -> 0 | L30: =COUNTIFS('Prácticas_Revisiones'!$S$2:$S$282,"T023",'Prácticas_Revisiones'!$T$2:$T$282,"SOFTWARE ENG. MODELS/METH. > *")+COUNTIFS('Prácticas_Snowballing'!$AB$2:$AB$281,"T023",'Prácticas_Snowballing'!$AC$2:$AC$281,"SOFTWARE ENG. MODELS/METH. > *") -> 0 | M30: =COUNTIFS('Prácticas_Revisiones'!$S$2:$S$282,"T023",'Prácticas_Revisiones'!$T$2:$T$282,"SOFTWARE QUALITY > *")+COUNTIFS('Prácticas_Snowballing'!$AB$2:$AB$281,"T023",'Prácticas_Snowballing'!$AC$2:$AC$281,"SOFTWARE QUALITY > *") -> 0 | N30: =COUNTIFS('Prácticas_Revisiones'!$S$2:$S$282,"T023",'Prácticas_Revisiones'!$T$2:$T$282,"SOFTWARE SECURITY > *")+COUNTIFS('Prácticas_Snowballing'!$AB$2:$AB$281,"T023",'Prácticas_Snowballing'!$AC$2:$AC$281,"SOFTWARE SECURITY > *") -> 0 | O30: =COUNTIFS('Prácticas_Revisiones'!$S$2:$S$282,"T023",'Prácticas_Revisiones'!$T$2:$T$282,"PROFESSIONAL PRACTICE > *")+COUNTIFS('Prácticas_Snowballing'!$AB$2:$AB$281,"T023",'Prácticas_Snowballing'!$AC$2:$AC$281,"PROFESSIONAL PRACTICE > *") -> 0 | P30: =COUNTIFS('Prácticas_Revisiones'!$S$2:$S$282,"T023",'Prácticas_Revisiones'!$T$2:$T$282,"SOFTWARE ENG. ECONOMICS > *")+COUNTIFS('Prácticas_Snowballing'!$AB$2:$AB$281,"T023",'Prácticas_Snowballing'!$AC$2:$AC$281,"SOFTWARE ENG. ECONOMICS > *") -> 0 | Q30: =COUNTIFS('Prácticas_Revisiones'!$S$2:$S$282,"T023",'Prácticas_Revisiones'!$T$2:$T$282,"SOFTWARE ENG. MANAGEMENT > *")+COUNTIFS('Prácticas_Snowballing'!$AB$2:$AB$281,"T023",'Prácticas_Snowballing'!$AC$2:$AC$281,"SOFTWARE ENG. MANAGEMENT > *") -> 0 | R30: =COUNTIFS('Prácticas_Revisiones'!$S$2:$S$282,"T023",'Prácticas_Revisiones'!$T$2:$T$282,"Sin área SWEBOK")+COUNTIFS('Prácticas_Snowballing'!$AB$2:$AB$281,"T023",'Prácticas_Snowballing'!$AC$2:$AC$281,"Sin área SWEBOK") -> 0 | S30: =SUM(C30:R30) -> 0
B31: T024 Historieta | C31: =COUNTIFS('Prácticas_Revisiones'!$S$2:$S$282,"T024",'Prácticas_Revisiones'!$T$2:$T$282,"REQUIREMENTS > *")+COUNTIFS('Prácticas_Snowballing'!$AB$2:$AB$281,"T024",'Prácticas_Snowballing'!$AC$2:$AC$281,"REQUIREMENTS > *") -> 0 | D31: =COUNTIFS('Prácticas_Revisiones'!$S$2:$S$282,"T024",'Prácticas_Revisiones'!$T$2:$T$282,"ARCHITECTURE > *")+COUNTIFS('Prácticas_Snowballing'!$AB$2:$AB$281,"T024",'Prácticas_Snowballing'!$AC$2:$AC$281,"ARCHITECTURE > *") -> 0 | E31: =COUNTIFS('Prácticas_Revisiones'!$S$2:$S$282,"T024",'Prácticas_Revisiones'!$T$2:$T$282,"DESIGN > *")+COUNTIFS('Prácticas_Snowballing'!$AB$2:$AB$281,"T024",'Prácticas_Snowballing'!$AC$2:$AC$281,"DESIGN > *") -> 0 | F31: =COUNTIFS('Prácticas_Revisiones'!$S$2:$S$282,"T024",'Prácticas_Revisiones'!$T$2:$T$282,"CONSTRUCTION > *")+COUNTIFS('Prácticas_Snowballing'!$AB$2:$AB$281,"T024",'Prácticas_Snowballing'!$AC$2:$AC$281,"CONSTRUCTION > *") -> 1 | G31: =COUNTIFS('Prácticas_Revisiones'!$S$2:$S$282,"T024",'Prácticas_Revisiones'!$T$2:$T$282,"SOFTWARE TESTING > *")+COUNTIFS('Prácticas_Snowballing'!$AB$2:$AB$281,"T024",'Prácticas_Snowballing'!$AC$2:$AC$281,"SOFTWARE TESTING > *") -> 0 | H31: =COUNTIFS('Prácticas_Revisiones'!$S$2:$S$282,"T024",'Prácticas_Revisiones'!$T$2:$T$282,"SOFTWARE ENG. OPERATIONS > *")+COUNTIFS('Prácticas_Snowballing'!$AB$2:$AB$281,"T024",'Prácticas_Snowballing'!$AC$2:$AC$281,"SOFTWARE ENG. OPERATIONS > *") -> 0 | I31: =COUNTIFS('Prácticas_Revisiones'!$S$2:$S$282,"T024",'Prácticas_Revisiones'!$T$2:$T$282,"MAINTENANCE > *")+COUNTIFS('Prácticas_Snowballing'!$AB$2:$AB$281,"T024",'Prácticas_Snowballing'!$AC$2:$AC$281,"MAINTENANCE > *") -> 0 | J31: =COUNTIFS('Prácticas_Revisiones'!$S$2:$S$282,"T024",'Prácticas_Revisiones'!$T$2:$T$282,"SOFTWARE CONFIG. MGMT. > *")+COUNTIFS('Prácticas_Snowballing'!$AB$2:$AB$281,"T024",'Prácticas_Snowballing'!$AC$2:$AC$281,"SOFTWARE CONFIG. MGMT. > *") -> 0 | K31: =COUNTIFS('Prácticas_Revisiones'!$S$2:$S$282,"T024",'Prácticas_Revisiones'!$T$2:$T$282,"SOFTWARE ENG. PROCESS > *")+COUNTIFS('Prácticas_Snowballing'!$AB$2:$AB$281,"T024",'Prácticas_Snowballing'!$AC$2:$AC$281,"SOFTWARE ENG. PROCESS > *") -> 0 | L31: =COUNTIFS('Prácticas_Revisiones'!$S$2:$S$282,"T024",'Prácticas_Revisiones'!$T$2:$T$282,"SOFTWARE ENG. MODELS/METH. > *")+COUNTIFS('Prácticas_Snowballing'!$AB$2:$AB$281,"T024",'Prácticas_Snowballing'!$AC$2:$AC$281,"SOFTWARE ENG. MODELS/METH. > *") -> 0 | M31: =COUNTIFS('Prácticas_Revisiones'!$S$2:$S$282,"T024",'Prácticas_Revisiones'!$T$2:$T$282,"SOFTWARE QUALITY > *")+COUNTIFS('Prácticas_Snowballing'!$AB$2:$AB$281,"T024",'Prácticas_Snowballing'!$AC$2:$AC$281,"SOFTWARE QUALITY > *") -> 0 | N31: =COUNTIFS('Prácticas_Revisiones'!$S$2:$S$282,"T024",'Prácticas_Revisiones'!$T$2:$T$282,"SOFTWARE SECURITY > *")+COUNTIFS('Prácticas_Snowballing'!$AB$2:$AB$281,"T024",'Prácticas_Snowballing'!$AC$2:$AC$281,"SOFTWARE SECURITY > *") -> 0 | O31: =COUNTIFS('Prácticas_Revisiones'!$S$2:$S$282,"T024",'Prácticas_Revisiones'!$T$2:$T$282,"PROFESSIONAL PRACTICE > *")+COUNTIFS('Prácticas_Snowballing'!$AB$2:$AB$281,"T024",'Prácticas_Snowballing'!$AC$2:$AC$281,"PROFESSIONAL PRACTICE > *") -> 0 | P31: =COUNTIFS('Prácticas_Revisiones'!$S$2:$S$282,"T024",'Prácticas_Revisiones'!$T$2:$T$282,"SOFTWARE ENG. ECONOMICS > *")+COUNTIFS('Prácticas_Snowballing'!$AB$2:$AB$281,"T024",'Prácticas_Snowballing'!$AC$2:$AC$281,"SOFTWARE ENG. ECONOMICS > *") -> 0 | Q31: =COUNTIFS('Prácticas_Revisiones'!$S$2:$S$282,"T024",'Prácticas_Revisiones'!$T$2:$T$282,"SOFTWARE ENG. MANAGEMENT > *")+COUNTIFS('Prácticas_Snowballing'!$AB$2:$AB$281,"T024",'Prácticas_Snowballing'!$AC$2:$AC$281,"SOFTWARE ENG. MANAGEMENT > *") -> 0 | R31: =COUNTIFS('Prácticas_Revisiones'!$S$2:$S$282,"T024",'Prácticas_Revisiones'!$T$2:$T$282,"Sin área SWEBOK")+COUNTIFS('Prácticas_Snowballing'!$AB$2:$AB$281,"T024",'Prácticas_Snowballing'!$AC$2:$AC$281,"Sin área SWEBOK") -> 0 | S31: =SUM(C31:R31) -> 1
B32: T025 Informe | C32: =COUNTIFS('Prácticas_Revisiones'!$S$2:$S$282,"T025",'Prácticas_Revisiones'!$T$2:$T$282,"REQUIREMENTS > *")+COUNTIFS('Prácticas_Snowballing'!$AB$2:$AB$281,"T025",'Prácticas_Snowballing'!$AC$2:$AC$281,"REQUIREMENTS > *") -> 0 | D32: =COUNTIFS('Prácticas_Revisiones'!$S$2:$S$282,"T025",'Prácticas_Revisiones'!$T$2:$T$282,"ARCHITECTURE > *")+COUNTIFS('Prácticas_Snowballing'!$AB$2:$AB$281,"T025",'Prácticas_Snowballing'!$AC$2:$AC$281,"ARCHITECTURE > *") -> 0 | E32: =COUNTIFS('Prácticas_Revisiones'!$S$2:$S$282,"T025",'Prácticas_Revisiones'!$T$2:$T$282,"DESIGN > *")+COUNTIFS('Prácticas_Snowballing'!$AB$2:$AB$281,"T025",'Prácticas_Snowballing'!$AC$2:$AC$281,"DESIGN > *") -> 1 | F32: =COUNTIFS('Prácticas_Revisiones'!$S$2:$S$282,"T025",'Prácticas_Revisiones'!$T$2:$T$282,"CONSTRUCTION > *")+COUNTIFS('Prácticas_Snowballing'!$AB$2:$AB$281,"T025",'Prácticas_Snowballing'!$AC$2:$AC$281,"CONSTRUCTION > *") -> 1 | G32: =COUNTIFS('Prácticas_Revisiones'!$S$2:$S$282,"T025",'Prácticas_Revisiones'!$T$2:$T$282,"SOFTWARE TESTING > *")+COUNTIFS('Prácticas_Snowballing'!$AB$2:$AB$281,"T025",'Prácticas_Snowballing'!$AC$2:$AC$281,"SOFTWARE TESTING > *") -> 0 | H32: =COUNTIFS('Prácticas_Revisiones'!$S$2:$S$282,"T025",'Prácticas_Revisiones'!$T$2:$T$282,"SOFTWARE ENG. OPERATIONS > *")+COUNTIFS('Prácticas_Snowballing'!$AB$2:$AB$281,"T025",'Prácticas_Snowballing'!$AC$2:$AC$281,"SOFTWARE ENG. OPERATIONS > *") -> 0 | I32: =COUNTIFS('Prácticas_Revisiones'!$S$2:$S$282,"T025",'Prácticas_Revisiones'!$T$2:$T$282,"MAINTENANCE > *")+COUNTIFS('Prácticas_Snowballing'!$AB$2:$AB$281,"T025",'Prácticas_Snowballing'!$AC$2:$AC$281,"MAINTENANCE > *") -> 0 | J32: =COUNTIFS('Prácticas_Revisiones'!$S$2:$S$282,"T025",'Prácticas_Revisiones'!$T$2:$T$282,"SOFTWARE CONFIG. MGMT. > *")+COUNTIFS('Prácticas_Snowballing'!$AB$2:$AB$281,"T025",'Prácticas_Snowballing'!$AC$2:$AC$281,"SOFTWARE CONFIG. MGMT. > *") -> 0 | K32: =COUNTIFS('Prácticas_Revisiones'!$S$2:$S$282,"T025",'Prácticas_Revisiones'!$T$2:$T$282,"SOFTWARE ENG. PROCESS > *")+COUNTIFS('Prácticas_Snowballing'!$AB$2:$AB$281,"T025",'Prácticas_Snowballing'!$AC$2:$AC$281,"SOFTWARE ENG. PROCESS > *") -> 0 | L32: =COUNTIFS('Prácticas_Revisiones'!$S$2:$S$282,"T025",'Prácticas_Revisiones'!$T$2:$T$282,"SOFTWARE ENG. MODELS/METH. > *")+COUNTIFS('Prácticas_Snowballing'!$AB$2:$AB$281,"T025",'Prácticas_Snowballing'!$AC$2:$AC$281,"SOFTWARE ENG. MODELS/METH. > *") -> 0 | M32: =COUNTIFS('Prácticas_Revisiones'!$S$2:$S$282,"T025",'Prácticas_Revisiones'!$T$2:$T$282,"SOFTWARE QUALITY > *")+COUNTIFS('Prácticas_Snowballing'!$AB$2:$AB$281,"T025",'Prácticas_Snowballing'!$AC$2:$AC$281,"SOFTWARE QUALITY > *") -> 0 | N32: =COUNTIFS('Prácticas_Revisiones'!$S$2:$S$282,"T025",'Prácticas_Revisiones'!$T$2:$T$282,"SOFTWARE SECURITY > *")+COUNTIFS('Prácticas_Snowballing'!$AB$2:$AB$281,"T025",'Prácticas_Snowballing'!$AC$2:$AC$281,"SOFTWARE SECURITY > *") -> 0 | O32: =COUNTIFS('Prácticas_Revisiones'!$S$2:$S$282,"T025",'Prácticas_Revisiones'!$T$2:$T$282,"PROFESSIONAL PRACTICE > *")+COUNTIFS('Prácticas_Snowballing'!$AB$2:$AB$281,"T025",'Prácticas_Snowballing'!$AC$2:$AC$281,"PROFESSIONAL PRACTICE > *") -> 0 | P32: =COUNTIFS('Prácticas_Revisiones'!$S$2:$S$282,"T025",'Prácticas_Revisiones'!$T$2:$T$282,"SOFTWARE ENG. ECONOMICS > *")+COUNTIFS('Prácticas_Snowballing'!$AB$2:$AB$281,"T025",'Prácticas_Snowballing'!$AC$2:$AC$281,"SOFTWARE ENG. ECONOMICS > *") -> 0 | Q32: =COUNTIFS('Prácticas_Revisiones'!$S$2:$S$282,"T025",'Prácticas_Revisiones'!$T$2:$T$282,"SOFTWARE ENG. MANAGEMENT > *")+COUNTIFS('Prácticas_Snowballing'!$AB$2:$AB$281,"T025",'Prácticas_Snowballing'!$AC$2:$AC$281,"SOFTWARE ENG. MANAGEMENT > *") -> 0 | R32: =COUNTIFS('Prácticas_Revisiones'!$S$2:$S$282,"T025",'Prácticas_Revisiones'!$T$2:$T$282,"Sin área SWEBOK")+COUNTIFS('Prácticas_Snowballing'!$AB$2:$AB$281,"T025",'Prácticas_Snowballing'!$AC$2:$AC$281,"Sin área SWEBOK") -> 2 | S32: =SUM(C32:R32) -> 4
B33: T026 Lluvia de ideas dirigida | C33: =COUNTIFS('Prácticas_Revisiones'!$S$2:$S$282,"T026",'Prácticas_Revisiones'!$T$2:$T$282,"REQUIREMENTS > *")+COUNTIFS('Prácticas_Snowballing'!$AB$2:$AB$281,"T026",'Prácticas_Snowballing'!$AC$2:$AC$281,"REQUIREMENTS > *") -> 0 | D33: =COUNTIFS('Prácticas_Revisiones'!$S$2:$S$282,"T026",'Prácticas_Revisiones'!$T$2:$T$282,"ARCHITECTURE > *")+COUNTIFS('Prácticas_Snowballing'!$AB$2:$AB$281,"T026",'Prácticas_Snowballing'!$AC$2:$AC$281,"ARCHITECTURE > *") -> 0 | E33: =COUNTIFS('Prácticas_Revisiones'!$S$2:$S$282,"T026",'Prácticas_Revisiones'!$T$2:$T$282,"DESIGN > *")+COUNTIFS('Prácticas_Snowballing'!$AB$2:$AB$281,"T026",'Prácticas_Snowballing'!$AC$2:$AC$281,"DESIGN > *") -> 2 | F33: =COUNTIFS('Prácticas_Revisiones'!$S$2:$S$282,"T026",'Prácticas_Revisiones'!$T$2:$T$282,"CONSTRUCTION > *")+COUNTIFS('Prácticas_Snowballing'!$AB$2:$AB$281,"T026",'Prácticas_Snowballing'!$AC$2:$AC$281,"CONSTRUCTION > *") -> 0 | G33: =COUNTIFS('Prácticas_Revisiones'!$S$2:$S$282,"T026",'Prácticas_Revisiones'!$T$2:$T$282,"SOFTWARE TESTING > *")+COUNTIFS('Prácticas_Snowballing'!$AB$2:$AB$281,"T026",'Prácticas_Snowballing'!$AC$2:$AC$281,"SOFTWARE TESTING > *") -> 0 | H33: =COUNTIFS('Prácticas_Revisiones'!$S$2:$S$282,"T026",'Prácticas_Revisiones'!$T$2:$T$282,"SOFTWARE ENG. OPERATIONS > *")+COUNTIFS('Prácticas_Snowballing'!$AB$2:$AB$281,"T026",'Prácticas_Snowballing'!$AC$2:$AC$281,"SOFTWARE ENG. OPERATIONS > *") -> 0 | I33: =COUNTIFS('Prácticas_Revisiones'!$S$2:$S$282,"T026",'Prácticas_Revisiones'!$T$2:$T$282,"MAINTENANCE > *")+COUNTIFS('Prácticas_Snowballing'!$AB$2:$AB$281,"T026",'Prácticas_Snowballing'!$AC$2:$AC$281,"MAINTENANCE > *") -> 0 | J33: =COUNTIFS('Prácticas_Revisiones'!$S$2:$S$282,"T026",'Prácticas_Revisiones'!$T$2:$T$282,"SOFTWARE CONFIG. MGMT. > *")+COUNTIFS('Prácticas_Snowballing'!$AB$2:$AB$281,"T026",'Prácticas_Snowballing'!$AC$2:$AC$281,"SOFTWARE CONFIG. MGMT. > *") -> 0 | K33: =COUNTIFS('Prácticas_Revisiones'!$S$2:$S$282,"T026",'Prácticas_Revisiones'!$T$2:$T$282,"SOFTWARE ENG. PROCESS > *")+COUNTIFS('Prácticas_Snowballing'!$AB$2:$AB$281,"T026",'Prácticas_Snowballing'!$AC$2:$AC$281,"SOFTWARE ENG. PROCESS > *") -> 0 | L33: =COUNTIFS('Prácticas_Revisiones'!$S$2:$S$282,"T026",'Prácticas_Revisiones'!$T$2:$T$282,"SOFTWARE ENG. MODELS/METH. > *")+COUNTIFS('Prácticas_Snowballing'!$AB$2:$AB$281,"T026",'Prácticas_Snowballing'!$AC$2:$AC$281,"SOFTWARE ENG. MODELS/METH. > *") -> 0 | M33: =COUNTIFS('Prácticas_Revisiones'!$S$2:$S$282,"T026",'Prácticas_Revisiones'!$T$2:$T$282,"SOFTWARE QUALITY > *")+COUNTIFS('Prácticas_Snowballing'!$AB$2:$AB$281,"T026",'Prácticas_Snowballing'!$AC$2:$AC$281,"SOFTWARE QUALITY > *") -> 0 | N33: =COUNTIFS('Prácticas_Revisiones'!$S$2:$S$282,"T026",'Prácticas_Revisiones'!$T$2:$T$282,"SOFTWARE SECURITY > *")+COUNTIFS('Prácticas_Snowballing'!$AB$2:$AB$281,"T026",'Prácticas_Snowballing'!$AC$2:$AC$281,"SOFTWARE SECURITY > *") -> 0 | O33: =COUNTIFS('Prácticas_Revisiones'!$S$2:$S$282,"T026",'Prácticas_Revisiones'!$T$2:$T$282,"PROFESSIONAL PRACTICE > *")+COUNTIFS('Prácticas_Snowballing'!$AB$2:$AB$281,"T026",'Prácticas_Snowballing'!$AC$2:$AC$281,"PROFESSIONAL PRACTICE > *") -> 0 | P33: =COUNTIFS('Prácticas_Revisiones'!$S$2:$S$282,"T026",'Prácticas_Revisiones'!$T$2:$T$282,"SOFTWARE ENG. ECONOMICS > *")+COUNTIFS('Prácticas_Snowballing'!$AB$2:$AB$281,"T026",'Prácticas_Snowballing'!$AC$2:$AC$281,"SOFTWARE ENG. ECONOMICS > *") -> 0 | Q33: =COUNTIFS('Prácticas_Revisiones'!$S$2:$S$282,"T026",'Prácticas_Revisiones'!$T$2:$T$282,"SOFTWARE ENG. MANAGEMENT > *")+COUNTIFS('Prácticas_Snowballing'!$AB$2:$AB$281,"T026",'Prácticas_Snowballing'!$AC$2:$AC$281,"SOFTWARE ENG. MANAGEMENT > *") -> 0 | R33: =COUNTIFS('Prácticas_Revisiones'!$S$2:$S$282,"T026",'Prácticas_Revisiones'!$T$2:$T$282,"Sin área SWEBOK")+COUNTIFS('Prácticas_Snowballing'!$AB$2:$AB$281,"T026",'Prácticas_Snowballing'!$AC$2:$AC$281,"Sin área SWEBOK") -> 0 | S33: =SUM(C33:R33) -> 2
B34: T027 Monografía | C34: =COUNTIFS('Prácticas_Revisiones'!$S$2:$S$282,"T027",'Prácticas_Revisiones'!$T$2:$T$282,"REQUIREMENTS > *")+COUNTIFS('Prácticas_Snowballing'!$AB$2:$AB$281,"T027",'Prácticas_Snowballing'!$AC$2:$AC$281,"REQUIREMENTS > *") -> 0 | D34: =COUNTIFS('Prácticas_Revisiones'!$S$2:$S$282,"T027",'Prácticas_Revisiones'!$T$2:$T$282,"ARCHITECTURE > *")+COUNTIFS('Prácticas_Snowballing'!$AB$2:$AB$281,"T027",'Prácticas_Snowballing'!$AC$2:$AC$281,"ARCHITECTURE > *") -> 0 | E34: =COUNTIFS('Prácticas_Revisiones'!$S$2:$S$282,"T027",'Prácticas_Revisiones'!$T$2:$T$282,"DESIGN > *")+COUNTIFS('Prácticas_Snowballing'!$AB$2:$AB$281,"T027",'Prácticas_Snowballing'!$AC$2:$AC$281,"DESIGN > *") -> 0 | F34: =COUNTIFS('Prácticas_Revisiones'!$S$2:$S$282,"T027",'Prácticas_Revisiones'!$T$2:$T$282,"CONSTRUCTION > *")+COUNTIFS('Prácticas_Snowballing'!$AB$2:$AB$281,"T027",'Prácticas_Snowballing'!$AC$2:$AC$281,"CONSTRUCTION > *") -> 0 | G34: =COUNTIFS('Prácticas_Revisiones'!$S$2:$S$282,"T027",'Prácticas_Revisiones'!$T$2:$T$282,"SOFTWARE TESTING > *")+COUNTIFS('Prácticas_Snowballing'!$AB$2:$AB$281,"T027",'Prácticas_Snowballing'!$AC$2:$AC$281,"SOFTWARE TESTING > *") -> 0 | H34: =COUNTIFS('Prácticas_Revisiones'!$S$2:$S$282,"T027",'Prácticas_Revisiones'!$T$2:$T$282,"SOFTWARE ENG. OPERATIONS > *")+COUNTIFS('Prácticas_Snowballing'!$AB$2:$AB$281,"T027",'Prácticas_Snowballing'!$AC$2:$AC$281,"SOFTWARE ENG. OPERATIONS > *") -> 0 | I34: =COUNTIFS('Prácticas_Revisiones'!$S$2:$S$282,"T027",'Prácticas_Revisiones'!$T$2:$T$282,"MAINTENANCE > *")+COUNTIFS('Prácticas_Snowballing'!$AB$2:$AB$281,"T027",'Prácticas_Snowballing'!$AC$2:$AC$281,"MAINTENANCE > *") -> 0 | J34: =COUNTIFS('Prácticas_Revisiones'!$S$2:$S$282,"T027",'Prácticas_Revisiones'!$T$2:$T$282,"SOFTWARE CONFIG. MGMT. > *")+COUNTIFS('Prácticas_Snowballing'!$AB$2:$AB$281,"T027",'Prácticas_Snowballing'!$AC$2:$AC$281,"SOFTWARE CONFIG. MGMT. > *") -> 0 | K34: =COUNTIFS('Prácticas_Revisiones'!$S$2:$S$282,"T027",'Prácticas_Revisiones'!$T$2:$T$282,"SOFTWARE ENG. PROCESS > *")+COUNTIFS('Prácticas_Snowballing'!$AB$2:$AB$281,"T027",'Prácticas_Snowballing'!$AC$2:$AC$281,"SOFTWARE ENG. PROCESS > *") -> 0 | L34: =COUNTIFS('Prácticas_Revisiones'!$S$2:$S$282,"T027",'Prácticas_Revisiones'!$T$2:$T$282,"SOFTWARE ENG. MODELS/METH. > *")+COUNTIFS('Prácticas_Snowballing'!$AB$2:$AB$281,"T027",'Prácticas_Snowballing'!$AC$2:$AC$281,"SOFTWARE ENG. MODELS/METH. > *") -> 0 | M34: =COUNTIFS('Prácticas_Revisiones'!$S$2:$S$282,"T027",'Prácticas_Revisiones'!$T$2:$T$282,"SOFTWARE QUALITY > *")+COUNTIFS('Prácticas_Snowballing'!$AB$2:$AB$281,"T027",'Prácticas_Snowballing'!$AC$2:$AC$281,"SOFTWARE QUALITY > *") -> 0 | N34: =COUNTIFS('Prácticas_Revisiones'!$S$2:$S$282,"T027",'Prácticas_Revisiones'!$T$2:$T$282,"SOFTWARE SECURITY > *")+COUNTIFS('Prácticas_Snowballing'!$AB$2:$AB$281,"T027",'Prácticas_Snowballing'!$AC$2:$AC$281,"SOFTWARE SECURITY > *") -> 0 | O34: =COUNTIFS('Prácticas_Revisiones'!$S$2:$S$282,"T027",'Prácticas_Revisiones'!$T$2:$T$282,"PROFESSIONAL PRACTICE > *")+COUNTIFS('Prácticas_Snowballing'!$AB$2:$AB$281,"T027",'Prácticas_Snowballing'!$AC$2:$AC$281,"PROFESSIONAL PRACTICE > *") -> 0 | P34: =COUNTIFS('Prácticas_Revisiones'!$S$2:$S$282,"T027",'Prácticas_Revisiones'!$T$2:$T$282,"SOFTWARE ENG. ECONOMICS > *")+COUNTIFS('Prácticas_Snowballing'!$AB$2:$AB$281,"T027",'Prácticas_Snowballing'!$AC$2:$AC$281,"SOFTWARE ENG. ECONOMICS > *") -> 0 | Q34: =COUNTIFS('Prácticas_Revisiones'!$S$2:$S$282,"T027",'Prácticas_Revisiones'!$T$2:$T$282,"SOFTWARE ENG. MANAGEMENT > *")+COUNTIFS('Prácticas_Snowballing'!$AB$2:$AB$281,"T027",'Prácticas_Snowballing'!$AC$2:$AC$281,"SOFTWARE ENG. MANAGEMENT > *") -> 0 | R34: =COUNTIFS('Prácticas_Revisiones'!$S$2:$S$282,"T027",'Prácticas_Revisiones'!$T$2:$T$282,"Sin área SWEBOK")+COUNTIFS('Prácticas_Snowballing'!$AB$2:$AB$281,"T027",'Prácticas_Snowballing'!$AC$2:$AC$281,"Sin área SWEBOK") -> 0 | S34: =SUM(C34:R34) -> 0
B35: T028 Reporte de investigación | C35: =COUNTIFS('Prácticas_Revisiones'!$S$2:$S$282,"T028",'Prácticas_Revisiones'!$T$2:$T$282,"REQUIREMENTS > *")+COUNTIFS('Prácticas_Snowballing'!$AB$2:$AB$281,"T028",'Prácticas_Snowballing'!$AC$2:$AC$281,"REQUIREMENTS > *") -> 0 | D35: =COUNTIFS('Prácticas_Revisiones'!$S$2:$S$282,"T028",'Prácticas_Revisiones'!$T$2:$T$282,"ARCHITECTURE > *")+COUNTIFS('Prácticas_Snowballing'!$AB$2:$AB$281,"T028",'Prácticas_Snowballing'!$AC$2:$AC$281,"ARCHITECTURE > *") -> 0 | E35: =COUNTIFS('Prácticas_Revisiones'!$S$2:$S$282,"T028",'Prácticas_Revisiones'!$T$2:$T$282,"DESIGN > *")+COUNTIFS('Prácticas_Snowballing'!$AB$2:$AB$281,"T028",'Prácticas_Snowballing'!$AC$2:$AC$281,"DESIGN > *") -> 0 | F35: =COUNTIFS('Prácticas_Revisiones'!$S$2:$S$282,"T028",'Prácticas_Revisiones'!$T$2:$T$282,"CONSTRUCTION > *")+COUNTIFS('Prácticas_Snowballing'!$AB$2:$AB$281,"T028",'Prácticas_Snowballing'!$AC$2:$AC$281,"CONSTRUCTION > *") -> 0 | G35: =COUNTIFS('Prácticas_Revisiones'!$S$2:$S$282,"T028",'Prácticas_Revisiones'!$T$2:$T$282,"SOFTWARE TESTING > *")+COUNTIFS('Prácticas_Snowballing'!$AB$2:$AB$281,"T028",'Prácticas_Snowballing'!$AC$2:$AC$281,"SOFTWARE TESTING > *") -> 0 | H35: =COUNTIFS('Prácticas_Revisiones'!$S$2:$S$282,"T028",'Prácticas_Revisiones'!$T$2:$T$282,"SOFTWARE ENG. OPERATIONS > *")+COUNTIFS('Prácticas_Snowballing'!$AB$2:$AB$281,"T028",'Prácticas_Snowballing'!$AC$2:$AC$281,"SOFTWARE ENG. OPERATIONS > *") -> 0 | I35: =COUNTIFS('Prácticas_Revisiones'!$S$2:$S$282,"T028",'Prácticas_Revisiones'!$T$2:$T$282,"MAINTENANCE > *")+COUNTIFS('Prácticas_Snowballing'!$AB$2:$AB$281,"T028",'Prácticas_Snowballing'!$AC$2:$AC$281,"MAINTENANCE > *") -> 0 | J35: =COUNTIFS('Prácticas_Revisiones'!$S$2:$S$282,"T028",'Prácticas_Revisiones'!$T$2:$T$282,"SOFTWARE CONFIG. MGMT. > *")+COUNTIFS('Prácticas_Snowballing'!$AB$2:$AB$281,"T028",'Prácticas_Snowballing'!$AC$2:$AC$281,"SOFTWARE CONFIG. MGMT. > *") -> 0 | K35: =COUNTIFS('Prácticas_Revisiones'!$S$2:$S$282,"T028",'Prácticas_Revisiones'!$T$2:$T$282,"SOFTWARE ENG. PROCESS > *")+COUNTIFS('Prácticas_Snowballing'!$AB$2:$AB$281,"T028",'Prácticas_Snowballing'!$AC$2:$AC$281,"SOFTWARE ENG. PROCESS > *") -> 0 | L35: =COUNTIFS('Prácticas_Revisiones'!$S$2:$S$282,"T028",'Prácticas_Revisiones'!$T$2:$T$282,"SOFTWARE ENG. MODELS/METH. > *")+COUNTIFS('Prácticas_Snowballing'!$AB$2:$AB$281,"T028",'Prácticas_Snowballing'!$AC$2:$AC$281,"SOFTWARE ENG. MODELS/METH. > *") -> 0 | M35: =COUNTIFS('Prácticas_Revisiones'!$S$2:$S$282,"T028",'Prácticas_Revisiones'!$T$2:$T$282,"SOFTWARE QUALITY > *")+COUNTIFS('Prácticas_Snowballing'!$AB$2:$AB$281,"T028",'Prácticas_Snowballing'!$AC$2:$AC$281,"SOFTWARE QUALITY > *") -> 0 | N35: =COUNTIFS('Prácticas_Revisiones'!$S$2:$S$282,"T028",'Prácticas_Revisiones'!$T$2:$T$282,"SOFTWARE SECURITY > *")+COUNTIFS('Prácticas_Snowballing'!$AB$2:$AB$281,"T028",'Prácticas_Snowballing'!$AC$2:$AC$281,"SOFTWARE SECURITY > *") -> 0 | O35: =COUNTIFS('Prácticas_Revisiones'!$S$2:$S$282,"T028",'Prácticas_Revisiones'!$T$2:$T$282,"PROFESSIONAL PRACTICE > *")+COUNTIFS('Prácticas_Snowballing'!$AB$2:$AB$281,"T028",'Prácticas_Snowballing'!$AC$2:$AC$281,"PROFESSIONAL PRACTICE > *") -> 0 | P35: =COUNTIFS('Prácticas_Revisiones'!$S$2:$S$282,"T028",'Prácticas_Revisiones'!$T$2:$T$282,"SOFTWARE ENG. ECONOMICS > *")+COUNTIFS('Prácticas_Snowballing'!$AB$2:$AB$281,"T028",'Prácticas_Snowballing'!$AC$2:$AC$281,"SOFTWARE ENG. ECONOMICS > *") -> 0 | Q35: =COUNTIFS('Prácticas_Revisiones'!$S$2:$S$282,"T028",'Prácticas_Revisiones'!$T$2:$T$282,"SOFTWARE ENG. MANAGEMENT > *")+COUNTIFS('Prácticas_Snowballing'!$AB$2:$AB$281,"T028",'Prácticas_Snowballing'!$AC$2:$AC$281,"SOFTWARE ENG. MANAGEMENT > *") -> 0 | R35: =COUNTIFS('Prácticas_Revisiones'!$S$2:$S$282,"T028",'Prácticas_Revisiones'!$T$2:$T$282,"Sin área SWEBOK")+COUNTIFS('Prácticas_Snowballing'!$AB$2:$AB$281,"T028",'Prácticas_Snowballing'!$AC$2:$AC$281,"Sin área SWEBOK") -> 0 | S35: =SUM(C35:R35) -> 0
B36: T029 Reporte de lectura general | C36: =COUNTIFS('Prácticas_Revisiones'!$S$2:$S$282,"T029",'Prácticas_Revisiones'!$T$2:$T$282,"REQUIREMENTS > *")+COUNTIFS('Prácticas_Snowballing'!$AB$2:$AB$281,"T029",'Prácticas_Snowballing'!$AC$2:$AC$281,"REQUIREMENTS > *") -> 0 | D36: =COUNTIFS('Prácticas_Revisiones'!$S$2:$S$282,"T029",'Prácticas_Revisiones'!$T$2:$T$282,"ARCHITECTURE > *")+COUNTIFS('Prácticas_Snowballing'!$AB$2:$AB$281,"T029",'Prácticas_Snowballing'!$AC$2:$AC$281,"ARCHITECTURE > *") -> 0 | E36: =COUNTIFS('Prácticas_Revisiones'!$S$2:$S$282,"T029",'Prácticas_Revisiones'!$T$2:$T$282,"DESIGN > *")+COUNTIFS('Prácticas_Snowballing'!$AB$2:$AB$281,"T029",'Prácticas_Snowballing'!$AC$2:$AC$281,"DESIGN > *") -> 0 | F36: =COUNTIFS('Prácticas_Revisiones'!$S$2:$S$282,"T029",'Prácticas_Revisiones'!$T$2:$T$282,"CONSTRUCTION > *")+COUNTIFS('Prácticas_Snowballing'!$AB$2:$AB$281,"T029",'Prácticas_Snowballing'!$AC$2:$AC$281,"CONSTRUCTION > *") -> 0 | G36: =COUNTIFS('Prácticas_Revisiones'!$S$2:$S$282,"T029",'Prácticas_Revisiones'!$T$2:$T$282,"SOFTWARE TESTING > *")+COUNTIFS('Prácticas_Snowballing'!$AB$2:$AB$281,"T029",'Prácticas_Snowballing'!$AC$2:$AC$281,"SOFTWARE TESTING > *") -> 0 | H36: =COUNTIFS('Prácticas_Revisiones'!$S$2:$S$282,"T029",'Prácticas_Revisiones'!$T$2:$T$282,"SOFTWARE ENG. OPERATIONS > *")+COUNTIFS('Prácticas_Snowballing'!$AB$2:$AB$281,"T029",'Prácticas_Snowballing'!$AC$2:$AC$281,"SOFTWARE ENG. OPERATIONS > *") -> 0 | I36: =COUNTIFS('Prácticas_Revisiones'!$S$2:$S$282,"T029",'Prácticas_Revisiones'!$T$2:$T$282,"MAINTENANCE > *")+COUNTIFS('Prácticas_Snowballing'!$AB$2:$AB$281,"T029",'Prácticas_Snowballing'!$AC$2:$AC$281,"MAINTENANCE > *") -> 0 | J36: =COUNTIFS('Prácticas_Revisiones'!$S$2:$S$282,"T029",'Prácticas_Revisiones'!$T$2:$T$282,"SOFTWARE CONFIG. MGMT. > *")+COUNTIFS('Prácticas_Snowballing'!$AB$2:$AB$281,"T029",'Prácticas_Snowballing'!$AC$2:$AC$281,"SOFTWARE CONFIG. MGMT. > *") -> 0 | K36: =COUNTIFS('Prácticas_Revisiones'!$S$2:$S$282,"T029",'Prácticas_Revisiones'!$T$2:$T$282,"SOFTWARE ENG. PROCESS > *")+COUNTIFS('Prácticas_Snowballing'!$AB$2:$AB$281,"T029",'Prácticas_Snowballing'!$AC$2:$AC$281,"SOFTWARE ENG. PROCESS > *") -> 0 | L36: =COUNTIFS('Prácticas_Revisiones'!$S$2:$S$282,"T029",'Prácticas_Revisiones'!$T$2:$T$282,"SOFTWARE ENG. MODELS/METH. > *")+COUNTIFS('Prácticas_Snowballing'!$AB$2:$AB$281,"T029",'Prácticas_Snowballing'!$AC$2:$AC$281,"SOFTWARE ENG. MODELS/METH. > *") -> 0 | M36: =COUNTIFS('Prácticas_Revisiones'!$S$2:$S$282,"T029",'Prácticas_Revisiones'!$T$2:$T$282,"SOFTWARE QUALITY > *")+COUNTIFS('Prácticas_Snowballing'!$AB$2:$AB$281,"T029",'Prácticas_Snowballing'!$AC$2:$AC$281,"SOFTWARE QUALITY > *") -> 0 | N36: =COUNTIFS('Prácticas_Revisiones'!$S$2:$S$282,"T029",'Prácticas_Revisiones'!$T$2:$T$282,"SOFTWARE SECURITY > *")+COUNTIFS('Prácticas_Snowballing'!$AB$2:$AB$281,"T029",'Prácticas_Snowballing'!$AC$2:$AC$281,"SOFTWARE SECURITY > *") -> 0 | O36: =COUNTIFS('Prácticas_Revisiones'!$S$2:$S$282,"T029",'Prácticas_Revisiones'!$T$2:$T$282,"PROFESSIONAL PRACTICE > *")+COUNTIFS('Prácticas_Snowballing'!$AB$2:$AB$281,"T029",'Prácticas_Snowballing'!$AC$2:$AC$281,"PROFESSIONAL PRACTICE > *") -> 0 | P36: =COUNTIFS('Prácticas_Revisiones'!$S$2:$S$282,"T029",'Prácticas_Revisiones'!$T$2:$T$282,"SOFTWARE ENG. ECONOMICS > *")+COUNTIFS('Prácticas_Snowballing'!$AB$2:$AB$281,"T029",'Prácticas_Snowballing'!$AC$2:$AC$281,"SOFTWARE ENG. ECONOMICS > *") -> 0 | Q36: =COUNTIFS('Prácticas_Revisiones'!$S$2:$S$282,"T029",'Prácticas_Revisiones'!$T$2:$T$282,"SOFTWARE ENG. MANAGEMENT > *")+COUNTIFS('Prácticas_Snowballing'!$AB$2:$AB$281,"T029",'Prácticas_Snowballing'!$AC$2:$AC$281,"SOFTWARE ENG. MANAGEMENT > *") -> 0 | R36: =COUNTIFS('Prácticas_Revisiones'!$S$2:$S$282,"T029",'Prácticas_Revisiones'!$T$2:$T$282,"Sin área SWEBOK")+COUNTIFS('Prácticas_Snowballing'!$AB$2:$AB$281,"T029",'Prácticas_Snowballing'!$AC$2:$AC$281,"Sin área SWEBOK") -> 1 | S36: =SUM(C36:R36) -> 1
B37: T030 Reseña | C37: =COUNTIFS('Prácticas_Revisiones'!$S$2:$S$282,"T030",'Prácticas_Revisiones'!$T$2:$T$282,"REQUIREMENTS > *")+COUNTIFS('Prácticas_Snowballing'!$AB$2:$AB$281,"T030",'Prácticas_Snowballing'!$AC$2:$AC$281,"REQUIREMENTS > *") -> 0 | D37: =COUNTIFS('Prácticas_Revisiones'!$S$2:$S$282,"T030",'Prácticas_Revisiones'!$T$2:$T$282,"ARCHITECTURE > *")+COUNTIFS('Prácticas_Snowballing'!$AB$2:$AB$281,"T030",'Prácticas_Snowballing'!$AC$2:$AC$281,"ARCHITECTURE > *") -> 0 | E37: =COUNTIFS('Prácticas_Revisiones'!$S$2:$S$282,"T030",'Prácticas_Revisiones'!$T$2:$T$282,"DESIGN > *")+COUNTIFS('Prácticas_Snowballing'!$AB$2:$AB$281,"T030",'Prácticas_Snowballing'!$AC$2:$AC$281,"DESIGN > *") -> 0 | F37: =COUNTIFS('Prácticas_Revisiones'!$S$2:$S$282,"T030",'Prácticas_Revisiones'!$T$2:$T$282,"CONSTRUCTION > *")+COUNTIFS('Prácticas_Snowballing'!$AB$2:$AB$281,"T030",'Prácticas_Snowballing'!$AC$2:$AC$281,"CONSTRUCTION > *") -> 0 | G37: =COUNTIFS('Prácticas_Revisiones'!$S$2:$S$282,"T030",'Prácticas_Revisiones'!$T$2:$T$282,"SOFTWARE TESTING > *")+COUNTIFS('Prácticas_Snowballing'!$AB$2:$AB$281,"T030",'Prácticas_Snowballing'!$AC$2:$AC$281,"SOFTWARE TESTING > *") -> 0 | H37: =COUNTIFS('Prácticas_Revisiones'!$S$2:$S$282,"T030",'Prácticas_Revisiones'!$T$2:$T$282,"SOFTWARE ENG. OPERATIONS > *")+COUNTIFS('Prácticas_Snowballing'!$AB$2:$AB$281,"T030",'Prácticas_Snowballing'!$AC$2:$AC$281,"SOFTWARE ENG. OPERATIONS > *") -> 0 | I37: =COUNTIFS('Prácticas_Revisiones'!$S$2:$S$282,"T030",'Prácticas_Revisiones'!$T$2:$T$282,"MAINTENANCE > *")+COUNTIFS('Prácticas_Snowballing'!$AB$2:$AB$281,"T030",'Prácticas_Snowballing'!$AC$2:$AC$281,"MAINTENANCE > *") -> 0 | J37: =COUNTIFS('Prácticas_Revisiones'!$S$2:$S$282,"T030",'Prácticas_Revisiones'!$T$2:$T$282,"SOFTWARE CONFIG. MGMT. > *")+COUNTIFS('Prácticas_Snowballing'!$AB$2:$AB$281,"T030",'Prácticas_Snowballing'!$AC$2:$AC$281,"SOFTWARE CONFIG. MGMT. > *") -> 0 | K37: =COUNTIFS('Prácticas_Revisiones'!$S$2:$S$282,"T030",'Prácticas_Revisiones'!$T$2:$T$282,"SOFTWARE ENG. PROCESS > *")+COUNTIFS('Prácticas_Snowballing'!$AB$2:$AB$281,"T030",'Prácticas_Snowballing'!$AC$2:$AC$281,"SOFTWARE ENG. PROCESS > *") -> 0 | L37: =COUNTIFS('Prácticas_Revisiones'!$S$2:$S$282,"T030",'Prácticas_Revisiones'!$T$2:$T$282,"SOFTWARE ENG. MODELS/METH. > *")+COUNTIFS('Prácticas_Snowballing'!$AB$2:$AB$281,"T030",'Prácticas_Snowballing'!$AC$2:$AC$281,"SOFTWARE ENG. MODELS/METH. > *") -> 0 | M37: =COUNTIFS('Prácticas_Revisiones'!$S$2:$S$282,"T030",'Prácticas_Revisiones'!$T$2:$T$282,"SOFTWARE QUALITY > *")+COUNTIFS('Prácticas_Snowballing'!$AB$2:$AB$281,"T030",'Prácticas_Snowballing'!$AC$2:$AC$281,"SOFTWARE QUALITY > *") -> 0 | N37: =COUNTIFS('Prácticas_Revisiones'!$S$2:$S$282,"T030",'Prácticas_Revisiones'!$T$2:$T$282,"SOFTWARE SECURITY > *")+COUNTIFS('Prácticas_Snowballing'!$AB$2:$AB$281,"T030",'Prácticas_Snowballing'!$AC$2:$AC$281,"SOFTWARE SECURITY > *") -> 0 | O37: =COUNTIFS('Prácticas_Revisiones'!$S$2:$S$282,"T030",'Prácticas_Revisiones'!$T$2:$T$282,"PROFESSIONAL PRACTICE > *")+COUNTIFS('Prácticas_Snowballing'!$AB$2:$AB$281,"T030",'Prácticas_Snowballing'!$AC$2:$AC$281,"PROFESSIONAL PRACTICE > *") -> 0 | P37: =COUNTIFS('Prácticas_Revisiones'!$S$2:$S$282,"T030",'Prácticas_Revisiones'!$T$2:$T$282,"SOFTWARE ENG. ECONOMICS > *")+COUNTIFS('Prácticas_Snowballing'!$AB$2:$AB$281,"T030",'Prácticas_Snowballing'!$AC$2:$AC$281,"SOFTWARE ENG. ECONOMICS > *") -> 0 | Q37: =COUNTIFS('Prácticas_Revisiones'!$S$2:$S$282,"T030",'Prácticas_Revisiones'!$T$2:$T$282,"SOFTWARE ENG. MANAGEMENT > *")+COUNTIFS('Prácticas_Snowballing'!$AB$2:$AB$281,"T030",'Prácticas_Snowballing'!$AC$2:$AC$281,"SOFTWARE ENG. MANAGEMENT > *") -> 0 | R37: =COUNTIFS('Prácticas_Revisiones'!$S$2:$S$282,"T030",'Prácticas_Revisiones'!$T$2:$T$282,"Sin área SWEBOK")+COUNTIFS('Prácticas_Snowballing'!$AB$2:$AB$281,"T030",'Prácticas_Snowballing'!$AC$2:$AC$281,"Sin área SWEBOK") -> 0 | S37: =SUM(C37:R37) -> 0
B38: Sin equivalente en catálogo | C38: =COUNTIFS('Prácticas_Revisiones'!$S$2:$S$282,"Sin equivalente en catálogo (EXPLICAR)",'Prácticas_Revisiones'!$T$2:$T$282,"REQUIREMENTS > *")+COUNTIFS('Prácticas_Snowballing'!$AB$2:$AB$281,"Sin equivalente en catálogo (EXPLICAR)",'Prácticas_Snowballing'!$AC$2:$AC$281,"REQUIREMENTS > *") -> 0 | D38: =COUNTIFS('Prácticas_Revisiones'!$S$2:$S$282,"Sin equivalente en catálogo (EXPLICAR)",'Prácticas_Revisiones'!$T$2:$T$282,"ARCHITECTURE > *")+COUNTIFS('Prácticas_Snowballing'!$AB$2:$AB$281,"Sin equivalente en catálogo (EXPLICAR)",'Prácticas_Snowballing'!$AC$2:$AC$281,"ARCHITECTURE > *") -> 0 | E38: =COUNTIFS('Prácticas_Revisiones'!$S$2:$S$282,"Sin equivalente en catálogo (EXPLICAR)",'Prácticas_Revisiones'!$T$2:$T$282,"DESIGN > *")+COUNTIFS('Prácticas_Snowballing'!$AB$2:$AB$281,"Sin equivalente en catálogo (EXPLICAR)",'Prácticas_Snowballing'!$AC$2:$AC$281,"DESIGN > *") -> 0 | F38: =COUNTIFS('Prácticas_Revisiones'!$S$2:$S$282,"Sin equivalente en catálogo (EXPLICAR)",'Prácticas_Revisiones'!$T$2:$T$282,"CONSTRUCTION > *")+COUNTIFS('Prácticas_Snowballing'!$AB$2:$AB$281,"Sin equivalente en catálogo (EXPLICAR)",'Prácticas_Snowballing'!$AC$2:$AC$281,"CONSTRUCTION > *") -> 0 | G38: =COUNTIFS('Prácticas_Revisiones'!$S$2:$S$282,"Sin equivalente en catálogo (EXPLICAR)",'Prácticas_Revisiones'!$T$2:$T$282,"SOFTWARE TESTING > *")+COUNTIFS('Prácticas_Snowballing'!$AB$2:$AB$281,"Sin equivalente en catálogo (EXPLICAR)",'Prácticas_Snowballing'!$AC$2:$AC$281,"SOFTWARE TESTING > *") -> 0 | H38: =COUNTIFS('Prácticas_Revisiones'!$S$2:$S$282,"Sin equivalente en catálogo (EXPLICAR)",'Prácticas_Revisiones'!$T$2:$T$282,"SOFTWARE ENG. OPERATIONS > *")+COUNTIFS('Prácticas_Snowballing'!$AB$2:$AB$281,"Sin equivalente en catálogo (EXPLICAR)",'Prácticas_Snowballing'!$AC$2:$AC$281,"SOFTWARE ENG. OPERATIONS > *") -> 0 | I38: =COUNTIFS('Prácticas_Revisiones'!$S$2:$S$282,"Sin equivalente en catálogo (EXPLICAR)",'Prácticas_Revisiones'!$T$2:$T$282,"MAINTENANCE > *")+COUNTIFS('Prácticas_Snowballing'!$AB$2:$AB$281,"Sin equivalente en catálogo (EXPLICAR)",'Prácticas_Snowballing'!$AC$2:$AC$281,"MAINTENANCE > *") -> 0 | J38: =COUNTIFS('Prácticas_Revisiones'!$S$2:$S$282,"Sin equivalente en catálogo (EXPLICAR)",'Prácticas_Revisiones'!$T$2:$T$282,"SOFTWARE CONFIG. MGMT. > *")+COUNTIFS('Prácticas_Snowballing'!$AB$2:$AB$281,"Sin equivalente en catálogo (EXPLICAR)",'Prácticas_Snowballing'!$AC$2:$AC$281,"SOFTWARE CONFIG. MGMT. > *") -> 0 | K38: =COUNTIFS('Prácticas_Revisiones'!$S$2:$S$282,"Sin equivalente en catálogo (EXPLICAR)",'Prácticas_Revisiones'!$T$2:$T$282,"SOFTWARE ENG. PROCESS > *")+COUNTIFS('Prácticas_Snowballing'!$AB$2:$AB$281,"Sin equivalente en catálogo (EXPLICAR)",'Prácticas_Snowballing'!$AC$2:$AC$281,"SOFTWARE ENG. PROCESS > *") -> 0 | L38: =COUNTIFS('Prácticas_Revisiones'!$S$2:$S$282,"Sin equivalente en catálogo (EXPLICAR)",'Prácticas_Revisiones'!$T$2:$T$282,"SOFTWARE ENG. MODELS/METH. > *")+COUNTIFS('Prácticas_Snowballing'!$AB$2:$AB$281,"Sin equivalente en catálogo (EXPLICAR)",'Prácticas_Snowballing'!$AC$2:$AC$281,"SOFTWARE ENG. MODELS/METH. > *") -> 0 | M38: =COUNTIFS('Prácticas_Revisiones'!$S$2:$S$282,"Sin equivalente en catálogo (EXPLICAR)",'Prácticas_Revisiones'!$T$2:$T$282,"SOFTWARE QUALITY > *")+COUNTIFS('Prácticas_Snowballing'!$AB$2:$AB$281,"Sin equivalente en catálogo (EXPLICAR)",'Prácticas_Snowballing'!$AC$2:$AC$281,"SOFTWARE QUALITY > *") -> 0 | N38: =COUNTIFS('Prácticas_Revisiones'!$S$2:$S$282,"Sin equivalente en catálogo (EXPLICAR)",'Prácticas_Revisiones'!$T$2:$T$282,"SOFTWARE SECURITY > *")+COUNTIFS('Prácticas_Snowballing'!$AB$2:$AB$281,"Sin equivalente en catálogo (EXPLICAR)",'Prácticas_Snowballing'!$AC$2:$AC$281,"SOFTWARE SECURITY > *") -> 0 | O38: =COUNTIFS('Prácticas_Revisiones'!$S$2:$S$282,"Sin equivalente en catálogo (EXPLICAR)",'Prácticas_Revisiones'!$T$2:$T$282,"PROFESSIONAL PRACTICE > *")+COUNTIFS('Prácticas_Snowballing'!$AB$2:$AB$281,"Sin equivalente en catálogo (EXPLICAR)",'Prácticas_Snowballing'!$AC$2:$AC$281,"PROFESSIONAL PRACTICE > *") -> 0 | P38: =COUNTIFS('Prácticas_Revisiones'!$S$2:$S$282,"Sin equivalente en catálogo (EXPLICAR)",'Prácticas_Revisiones'!$T$2:$T$282,"SOFTWARE ENG. ECONOMICS > *")+COUNTIFS('Prácticas_Snowballing'!$AB$2:$AB$281,"Sin equivalente en catálogo (EXPLICAR)",'Prácticas_Snowballing'!$AC$2:$AC$281,"SOFTWARE ENG. ECONOMICS > *") -> 0 | Q38: =COUNTIFS('Prácticas_Revisiones'!$S$2:$S$282,"Sin equivalente en catálogo (EXPLICAR)",'Prácticas_Revisiones'!$T$2:$T$282,"SOFTWARE ENG. MANAGEMENT > *")+COUNTIFS('Prácticas_Snowballing'!$AB$2:$AB$281,"Sin equivalente en catálogo (EXPLICAR)",'Prácticas_Snowballing'!$AC$2:$AC$281,"SOFTWARE ENG. MANAGEMENT > *") -> 0 | R38: =COUNTIFS('Prácticas_Revisiones'!$S$2:$S$282,"Sin equivalente en catálogo (EXPLICAR)",'Prácticas_Revisiones'!$T$2:$T$282,"Sin área SWEBOK")+COUNTIFS('Prácticas_Snowballing'!$AB$2:$AB$281,"Sin equivalente en catálogo (EXPLICAR)",'Prácticas_Snowballing'!$AC$2:$AC$281,"Sin área SWEBOK") -> 0 | S38: =SUM(C38:R38) -> 0
A39: Subtotal EXPLICAR | C39: =SUM(C19:C38) -> 0 | D39: =SUM(D19:D38) -> 0 | E39: =SUM(E19:E38) -> 4 | F39: =SUM(F19:F38) -> 39 | G39: =SUM(G19:G38) -> 0 | H39: =SUM(H19:H38) -> 0 | I39: =SUM(I19:I38) -> 1 | J39: =SUM(J19:J38) -> 0 | ... S39: =SUM(S19:S38) -> 48
A40: APLICAR | B40: T031 Consulta pública | C40: =COUNTIFS('Prácticas_Revisiones'!$S$2:$S$282,"T031",'Prácticas_Revisiones'!$T$2:$T$282,"REQUIREMENTS > *")+COUNTIFS('Prácticas_Snowballing'!$AB$2:$AB$281,"T031",'Prácticas_Snowballing'!$AC$2:$AC$281,"REQUIREMENTS > *") -> 0 | D40: =COUNTIFS('Prácticas_Revisiones'!$S$2:$S$282,"T031",'Prácticas_Revisiones'!$T$2:$T$282,"ARCHITECTURE > *")+COUNTIFS('Prácticas_Snowballing'!$AB$2:$AB$281,"T031",'Prácticas_Snowballing'!$AC$2:$AC$281,"ARCHITECTURE > *") -> 0 | E40: =COUNTIFS('Prácticas_Revisiones'!$S$2:$S$282,"T031",'Prácticas_Revisiones'!$T$2:$T$282,"DESIGN > *")+COUNTIFS('Prácticas_Snowballing'!$AB$2:$AB$281,"T031",'Prácticas_Snowballing'!$AC$2:$AC$281,"DESIGN > *") -> 0 | F40: =COUNTIFS('Prácticas_Revisiones'!$S$2:$S$282,"T031",'Prácticas_Revisiones'!$T$2:$T$282,"CONSTRUCTION > *")+COUNTIFS('Prácticas_Snowballing'!$AB$2:$AB$281,"T031",'Prácticas_Snowballing'!$AC$2:$AC$281,"CONSTRUCTION > *") -> 0 | G40: =COUNTIFS('Prácticas_Revisiones'!$S$2:$S$282,"T031",'Prácticas_Revisiones'!$T$2:$T$282,"SOFTWARE TESTING > *")+COUNTIFS('Prácticas_Snowballing'!$AB$2:$AB$281,"T031",'Prácticas_Snowballing'!$AC$2:$AC$281,"SOFTWARE TESTING > *") -> 0 | H40: =COUNTIFS('Prácticas_Revisiones'!$S$2:$S$282,"T031",'Prácticas_Revisiones'!$T$2:$T$282,"SOFTWARE ENG. OPERATIONS > *")+COUNTIFS('Prácticas_Snowballing'!$AB$2:$AB$281,"T031",'Prácticas_Snowballing'!$AC$2:$AC$281,"SOFTWARE ENG. OPERATIONS > *") -> 0 | I40: =COUNTIFS('Prácticas_Revisiones'!$S$2:$S$282,"T031",'Prácticas_Revisiones'!$T$2:$T$282,"MAINTENANCE > *")+COUNTIFS('Prácticas_Snowballing'!$AB$2:$AB$281,"T031",'Prácticas_Snowballing'!$AC$2:$AC$281,"MAINTENANCE > *") -> 0 | J40: =COUNTIFS('Prácticas_Revisiones'!$S$2:$S$282,"T031",'Prácticas_Revisiones'!$T$2:$T$282,"SOFTWARE CONFIG. MGMT. > *")+COUNTIFS('Prácticas_Snowballing'!$AB$2:$AB$281,"T031",'Prácticas_Snowballing'!$AC$2:$AC$281,"SOFTWARE CONFIG. MGMT. > *") -> 0 | K40: =COUNTIFS('Prácticas_Revisiones'!$S$2:$S$282,"T031",'Prácticas_Revisiones'!$T$2:$T$282,"SOFTWARE ENG. PROCESS > *")+COUNTIFS('Prácticas_Snowballing'!$AB$2:$AB$281,"T031",'Prácticas_Snowballing'!$AC$2:$AC$281,"SOFTWARE ENG. PROCESS > *") -> 0 | L40: =COUNTIFS('Prácticas_Revisiones'!$S$2:$S$282,"T031",'Prácticas_Revisiones'!$T$2:$T$282,"SOFTWARE ENG. MODELS/METH. > *")+COUNTIFS('Prácticas_Snowballing'!$AB$2:$AB$281,"T031",'Prácticas_Snowballing'!$AC$2:$AC$281,"SOFTWARE ENG. MODELS/METH. > *") -> 0 | M40: =COUNTIFS('Prácticas_Revisiones'!$S$2:$S$282,"T031",'Prácticas_Revisiones'!$T$2:$T$282,"SOFTWARE QUALITY > *")+COUNTIFS('Prácticas_Snowballing'!$AB$2:$AB$281,"T031",'Prácticas_Snowballing'!$AC$2:$AC$281,"SOFTWARE QUALITY > *") -> 0 | N40: =COUNTIFS('Prácticas_Revisiones'!$S$2:$S$282,"T031",'Prácticas_Revisiones'!$T$2:$T$282,"SOFTWARE SECURITY > *")+COUNTIFS('Prácticas_Snowballing'!$AB$2:$AB$281,"T031",'Prácticas_Snowballing'!$AC$2:$AC$281,"SOFTWARE SECURITY > *") -> 0 | O40: =COUNTIFS('Prácticas_Revisiones'!$S$2:$S$282,"T031",'Prácticas_Revisiones'!$T$2:$T$282,"PROFESSIONAL PRACTICE > *")+COUNTIFS('Prácticas_Snowballing'!$AB$2:$AB$281,"T031",'Prácticas_Snowballing'!$AC$2:$AC$281,"PROFESSIONAL PRACTICE > *") -> 0 | P40: =COUNTIFS('Prácticas_Revisiones'!$S$2:$S$282,"T031",'Prácticas_Revisiones'!$T$2:$T$282,"SOFTWARE ENG. ECONOMICS > *")+COUNTIFS('Prácticas_Snowballing'!$AB$2:$AB$281,"T031",'Prácticas_Snowballing'!$AC$2:$AC$281,"SOFTWARE ENG. ECONOMICS > *") -> 0 | Q40: =COUNTIFS('Prácticas_Revisiones'!$S$2:$S$282,"T031",'Prácticas_Revisiones'!$T$2:$T$282,"SOFTWARE ENG. MANAGEMENT > *")+COUNTIFS('Prácticas_Snowballing'!$AB$2:$AB$281,"T031",'Prácticas_Snowballing'!$AC$2:$AC$281,"SOFTWARE ENG. MANAGEMENT > *") -> 0 | R40: =COUNTIFS('Prácticas_Revisiones'!$S$2:$S$282,"T031",'Prácticas_Revisiones'!$T$2:$T$282,"Sin área SWEBOK")+COUNTIFS('Prácticas_Snowballing'!$AB$2:$AB$281,"T031",'Prácticas_Snowballing'!$AC$2:$AC$281,"Sin área SWEBOK") -> 0 | S40: =SUM(C40:R40) -> 0
B41: T032 Cuestionario | C41: =COUNTIFS('Prácticas_Revisiones'!$S$2:$S$282,"T032",'Prácticas_Revisiones'!$T$2:$T$282,"REQUIREMENTS > *")+COUNTIFS('Prácticas_Snowballing'!$AB$2:$AB$281,"T032",'Prácticas_Snowballing'!$AC$2:$AC$281,"REQUIREMENTS > *") -> 0 | D41: =COUNTIFS('Prácticas_Revisiones'!$S$2:$S$282,"T032",'Prácticas_Revisiones'!$T$2:$T$282,"ARCHITECTURE > *")+COUNTIFS('Prácticas_Snowballing'!$AB$2:$AB$281,"T032",'Prácticas_Snowballing'!$AC$2:$AC$281,"ARCHITECTURE > *") -> 0 | E41: =COUNTIFS('Prácticas_Revisiones'!$S$2:$S$282,"T032",'Prácticas_Revisiones'!$T$2:$T$282,"DESIGN > *")+COUNTIFS('Prácticas_Snowballing'!$AB$2:$AB$281,"T032",'Prácticas_Snowballing'!$AC$2:$AC$281,"DESIGN > *") -> 0 | F41: =COUNTIFS('Prácticas_Revisiones'!$S$2:$S$282,"T032",'Prácticas_Revisiones'!$T$2:$T$282,"CONSTRUCTION > *")+COUNTIFS('Prácticas_Snowballing'!$AB$2:$AB$281,"T032",'Prácticas_Snowballing'!$AC$2:$AC$281,"CONSTRUCTION > *") -> 10 | G41: =COUNTIFS('Prácticas_Revisiones'!$S$2:$S$282,"T032",'Prácticas_Revisiones'!$T$2:$T$282,"SOFTWARE TESTING > *")+COUNTIFS('Prácticas_Snowballing'!$AB$2:$AB$281,"T032",'Prácticas_Snowballing'!$AC$2:$AC$281,"SOFTWARE TESTING > *") -> 0 | H41: =COUNTIFS('Prácticas_Revisiones'!$S$2:$S$282,"T032",'Prácticas_Revisiones'!$T$2:$T$282,"SOFTWARE ENG. OPERATIONS > *")+COUNTIFS('Prácticas_Snowballing'!$AB$2:$AB$281,"T032",'Prácticas_Snowballing'!$AC$2:$AC$281,"SOFTWARE ENG. OPERATIONS > *") -> 0 | I41: =COUNTIFS('Prácticas_Revisiones'!$S$2:$S$282,"T032",'Prácticas_Revisiones'!$T$2:$T$282,"MAINTENANCE > *")+COUNTIFS('Prácticas_Snowballing'!$AB$2:$AB$281,"T032",'Prácticas_Snowballing'!$AC$2:$AC$281,"MAINTENANCE > *") -> 0 | J41: =COUNTIFS('Prácticas_Revisiones'!$S$2:$S$282,"T032",'Prácticas_Revisiones'!$T$2:$T$282,"SOFTWARE CONFIG. MGMT. > *")+COUNTIFS('Prácticas_Snowballing'!$AB$2:$AB$281,"T032",'Prácticas_Snowballing'!$AC$2:$AC$281,"SOFTWARE CONFIG. MGMT. > *") -> 0 | K41: =COUNTIFS('Prácticas_Revisiones'!$S$2:$S$282,"T032",'Prácticas_Revisiones'!$T$2:$T$282,"SOFTWARE ENG. PROCESS > *")+COUNTIFS('Prácticas_Snowballing'!$AB$2:$AB$281,"T032",'Prácticas_Snowballing'!$AC$2:$AC$281,"SOFTWARE ENG. PROCESS > *") -> 0 | L41: =COUNTIFS('Prácticas_Revisiones'!$S$2:$S$282,"T032",'Prácticas_Revisiones'!$T$2:$T$282,"SOFTWARE ENG. MODELS/METH. > *")+COUNTIFS('Prácticas_Snowballing'!$AB$2:$AB$281,"T032",'Prácticas_Snowballing'!$AC$2:$AC$281,"SOFTWARE ENG. MODELS/METH. > *") -> 0 | M41: =COUNTIFS('Prácticas_Revisiones'!$S$2:$S$282,"T032",'Prácticas_Revisiones'!$T$2:$T$282,"SOFTWARE QUALITY > *")+COUNTIFS('Prácticas_Snowballing'!$AB$2:$AB$281,"T032",'Prácticas_Snowballing'!$AC$2:$AC$281,"SOFTWARE QUALITY > *") -> 0 | N41: =COUNTIFS('Prácticas_Revisiones'!$S$2:$S$282,"T032",'Prácticas_Revisiones'!$T$2:$T$282,"SOFTWARE SECURITY > *")+COUNTIFS('Prácticas_Snowballing'!$AB$2:$AB$281,"T032",'Prácticas_Snowballing'!$AC$2:$AC$281,"SOFTWARE SECURITY > *") -> 0 | O41: =COUNTIFS('Prácticas_Revisiones'!$S$2:$S$282,"T032",'Prácticas_Revisiones'!$T$2:$T$282,"PROFESSIONAL PRACTICE > *")+COUNTIFS('Prácticas_Snowballing'!$AB$2:$AB$281,"T032",'Prácticas_Snowballing'!$AC$2:$AC$281,"PROFESSIONAL PRACTICE > *") -> 0 | P41: =COUNTIFS('Prácticas_Revisiones'!$S$2:$S$282,"T032",'Prácticas_Revisiones'!$T$2:$T$282,"SOFTWARE ENG. ECONOMICS > *")+COUNTIFS('Prácticas_Snowballing'!$AB$2:$AB$281,"T032",'Prácticas_Snowballing'!$AC$2:$AC$281,"SOFTWARE ENG. ECONOMICS > *") -> 0 | Q41: =COUNTIFS('Prácticas_Revisiones'!$S$2:$S$282,"T032",'Prácticas_Revisiones'!$T$2:$T$282,"SOFTWARE ENG. MANAGEMENT > *")+COUNTIFS('Prácticas_Snowballing'!$AB$2:$AB$281,"T032",'Prácticas_Snowballing'!$AC$2:$AC$281,"SOFTWARE ENG. MANAGEMENT > *") -> 0 | R41: =COUNTIFS('Prácticas_Revisiones'!$S$2:$S$282,"T032",'Prácticas_Revisiones'!$T$2:$T$282,"Sin área SWEBOK")+COUNTIFS('Prácticas_Snowballing'!$AB$2:$AB$281,"T032",'Prácticas_Snowballing'!$AC$2:$AC$281,"Sin área SWEBOK") -> 1 | S41: =SUM(C41:R41) -> 11
B42: T033 Debate | C42: =COUNTIFS('Prácticas_Revisiones'!$S$2:$S$282,"T033",'Prácticas_Revisiones'!$T$2:$T$282,"REQUIREMENTS > *")+COUNTIFS('Prácticas_Snowballing'!$AB$2:$AB$281,"T033",'Prácticas_Snowballing'!$AC$2:$AC$281,"REQUIREMENTS > *") -> 0 | D42: =COUNTIFS('Prácticas_Revisiones'!$S$2:$S$282,"T033",'Prácticas_Revisiones'!$T$2:$T$282,"ARCHITECTURE > *")+COUNTIFS('Prácticas_Snowballing'!$AB$2:$AB$281,"T033",'Prácticas_Snowballing'!$AC$2:$AC$281,"ARCHITECTURE > *") -> 0 | E42: =COUNTIFS('Prácticas_Revisiones'!$S$2:$S$282,"T033",'Prácticas_Revisiones'!$T$2:$T$282,"DESIGN > *")+COUNTIFS('Prácticas_Snowballing'!$AB$2:$AB$281,"T033",'Prácticas_Snowballing'!$AC$2:$AC$281,"DESIGN > *") -> 0 | F42: =COUNTIFS('Prácticas_Revisiones'!$S$2:$S$282,"T033",'Prácticas_Revisiones'!$T$2:$T$282,"CONSTRUCTION > *")+COUNTIFS('Prácticas_Snowballing'!$AB$2:$AB$281,"T033",'Prácticas_Snowballing'!$AC$2:$AC$281,"CONSTRUCTION > *") -> 1 | G42: =COUNTIFS('Prácticas_Revisiones'!$S$2:$S$282,"T033",'Prácticas_Revisiones'!$T$2:$T$282,"SOFTWARE TESTING > *")+COUNTIFS('Prácticas_Snowballing'!$AB$2:$AB$281,"T033",'Prácticas_Snowballing'!$AC$2:$AC$281,"SOFTWARE TESTING > *") -> 0 | H42: =COUNTIFS('Prácticas_Revisiones'!$S$2:$S$282,"T033",'Prácticas_Revisiones'!$T$2:$T$282,"SOFTWARE ENG. OPERATIONS > *")+COUNTIFS('Prácticas_Snowballing'!$AB$2:$AB$281,"T033",'Prácticas_Snowballing'!$AC$2:$AC$281,"SOFTWARE ENG. OPERATIONS > *") -> 0 | I42: =COUNTIFS('Prácticas_Revisiones'!$S$2:$S$282,"T033",'Prácticas_Revisiones'!$T$2:$T$282,"MAINTENANCE > *")+COUNTIFS('Prácticas_Snowballing'!$AB$2:$AB$281,"T033",'Prácticas_Snowballing'!$AC$2:$AC$281,"MAINTENANCE > *") -> 0 | J42: =COUNTIFS('Prácticas_Revisiones'!$S$2:$S$282,"T033",'Prácticas_Revisiones'!$T$2:$T$282,"SOFTWARE CONFIG. MGMT. > *")+COUNTIFS('Prácticas_Snowballing'!$AB$2:$AB$281,"T033",'Prácticas_Snowballing'!$AC$2:$AC$281,"SOFTWARE CONFIG. MGMT. > *") -> 0 | K42: =COUNTIFS('Prácticas_Revisiones'!$S$2:$S$282,"T033",'Prácticas_Revisiones'!$T$2:$T$282,"SOFTWARE ENG. PROCESS > *")+COUNTIFS('Prácticas_Snowballing'!$AB$2:$AB$281,"T033",'Prácticas_Snowballing'!$AC$2:$AC$281,"SOFTWARE ENG. PROCESS > *") -> 0 | L42: =COUNTIFS('Prácticas_Revisiones'!$S$2:$S$282,"T033",'Prácticas_Revisiones'!$T$2:$T$282,"SOFTWARE ENG. MODELS/METH. > *")+COUNTIFS('Prácticas_Snowballing'!$AB$2:$AB$281,"T033",'Prácticas_Snowballing'!$AC$2:$AC$281,"SOFTWARE ENG. MODELS/METH. > *") -> 0 | M42: =COUNTIFS('Prácticas_Revisiones'!$S$2:$S$282,"T033",'Prácticas_Revisiones'!$T$2:$T$282,"SOFTWARE QUALITY > *")+COUNTIFS('Prácticas_Snowballing'!$AB$2:$AB$281,"T033",'Prácticas_Snowballing'!$AC$2:$AC$281,"SOFTWARE QUALITY > *") -> 0 | N42: =COUNTIFS('Prácticas_Revisiones'!$S$2:$S$282,"T033",'Prácticas_Revisiones'!$T$2:$T$282,"SOFTWARE SECURITY > *")+COUNTIFS('Prácticas_Snowballing'!$AB$2:$AB$281,"T033",'Prácticas_Snowballing'!$AC$2:$AC$281,"SOFTWARE SECURITY > *") -> 0 | O42: =COUNTIFS('Prácticas_Revisiones'!$S$2:$S$282,"T033",'Prácticas_Revisiones'!$T$2:$T$282,"PROFESSIONAL PRACTICE > *")+COUNTIFS('Prácticas_Snowballing'!$AB$2:$AB$281,"T033",'Prácticas_Snowballing'!$AC$2:$AC$281,"PROFESSIONAL PRACTICE > *") -> 0 | P42: =COUNTIFS('Prácticas_Revisiones'!$S$2:$S$282,"T033",'Prácticas_Revisiones'!$T$2:$T$282,"SOFTWARE ENG. ECONOMICS > *")+COUNTIFS('Prácticas_Snowballing'!$AB$2:$AB$281,"T033",'Prácticas_Snowballing'!$AC$2:$AC$281,"SOFTWARE ENG. ECONOMICS > *") -> 0 | Q42: =COUNTIFS('Prácticas_Revisiones'!$S$2:$S$282,"T033",'Prácticas_Revisiones'!$T$2:$T$282,"SOFTWARE ENG. MANAGEMENT > *")+COUNTIFS('Prácticas_Snowballing'!$AB$2:$AB$281,"T033",'Prácticas_Snowballing'!$AC$2:$AC$281,"SOFTWARE ENG. MANAGEMENT > *") -> 0 | R42: =COUNTIFS('Prácticas_Revisiones'!$S$2:$S$282,"T033",'Prácticas_Revisiones'!$T$2:$T$282,"Sin área SWEBOK")+COUNTIFS('Prácticas_Snowballing'!$AB$2:$AB$281,"T033",'Prácticas_Snowballing'!$AC$2:$AC$281,"Sin área SWEBOK") -> 0 | S42: =SUM(C42:R42) -> 1
B43: T034 Debate público | C43: =COUNTIFS('Prácticas_Revisiones'!$S$2:$S$282,"T034",'Prácticas_Revisiones'!$T$2:$T$282,"REQUIREMENTS > *")+COUNTIFS('Prácticas_Snowballing'!$AB$2:$AB$281,"T034",'Prácticas_Snowballing'!$AC$2:$AC$281,"REQUIREMENTS > *") -> 0 | D43: =COUNTIFS('Prácticas_Revisiones'!$S$2:$S$282,"T034",'Prácticas_Revisiones'!$T$2:$T$282,"ARCHITECTURE > *")+COUNTIFS('Prácticas_Snowballing'!$AB$2:$AB$281,"T034",'Prácticas_Snowballing'!$AC$2:$AC$281,"ARCHITECTURE > *") -> 0 | E43: =COUNTIFS('Prácticas_Revisiones'!$S$2:$S$282,"T034",'Prácticas_Revisiones'!$T$2:$T$282,"DESIGN > *")+COUNTIFS('Prácticas_Snowballing'!$AB$2:$AB$281,"T034",'Prácticas_Snowballing'!$AC$2:$AC$281,"DESIGN > *") -> 0 | F43: =COUNTIFS('Prácticas_Revisiones'!$S$2:$S$282,"T034",'Prácticas_Revisiones'!$T$2:$T$282,"CONSTRUCTION > *")+COUNTIFS('Prácticas_Snowballing'!$AB$2:$AB$281,"T034",'Prácticas_Snowballing'!$AC$2:$AC$281,"CONSTRUCTION > *") -> 0 | G43: =COUNTIFS('Prácticas_Revisiones'!$S$2:$S$282,"T034",'Prácticas_Revisiones'!$T$2:$T$282,"SOFTWARE TESTING > *")+COUNTIFS('Prácticas_Snowballing'!$AB$2:$AB$281,"T034",'Prácticas_Snowballing'!$AC$2:$AC$281,"SOFTWARE TESTING > *") -> 0 | H43: =COUNTIFS('Prácticas_Revisiones'!$S$2:$S$282,"T034",'Prácticas_Revisiones'!$T$2:$T$282,"SOFTWARE ENG. OPERATIONS > *")+COUNTIFS('Prácticas_Snowballing'!$AB$2:$AB$281,"T034",'Prácticas_Snowballing'!$AC$2:$AC$281,"SOFTWARE ENG. OPERATIONS > *") -> 0 | I43: =COUNTIFS('Prácticas_Revisiones'!$S$2:$S$282,"T034",'Prácticas_Revisiones'!$T$2:$T$282,"MAINTENANCE > *")+COUNTIFS('Prácticas_Snowballing'!$AB$2:$AB$281,"T034",'Prácticas_Snowballing'!$AC$2:$AC$281,"MAINTENANCE > *") -> 0 | J43: =COUNTIFS('Prácticas_Revisiones'!$S$2:$S$282,"T034",'Prácticas_Revisiones'!$T$2:$T$282,"SOFTWARE CONFIG. MGMT. > *")+COUNTIFS('Prácticas_Snowballing'!$AB$2:$AB$281,"T034",'Prácticas_Snowballing'!$AC$2:$AC$281,"SOFTWARE CONFIG. MGMT. > *") -> 0 | K43: =COUNTIFS('Prácticas_Revisiones'!$S$2:$S$282,"T034",'Prácticas_Revisiones'!$T$2:$T$282,"SOFTWARE ENG. PROCESS > *")+COUNTIFS('Prácticas_Snowballing'!$AB$2:$AB$281,"T034",'Prácticas_Snowballing'!$AC$2:$AC$281,"SOFTWARE ENG. PROCESS > *") -> 0 | L43: =COUNTIFS('Prácticas_Revisiones'!$S$2:$S$282,"T034",'Prácticas_Revisiones'!$T$2:$T$282,"SOFTWARE ENG. MODELS/METH. > *")+COUNTIFS('Prácticas_Snowballing'!$AB$2:$AB$281,"T034",'Prácticas_Snowballing'!$AC$2:$AC$281,"SOFTWARE ENG. MODELS/METH. > *") -> 0 | M43: =COUNTIFS('Prácticas_Revisiones'!$S$2:$S$282,"T034",'Prácticas_Revisiones'!$T$2:$T$282,"SOFTWARE QUALITY > *")+COUNTIFS('Prácticas_Snowballing'!$AB$2:$AB$281,"T034",'Prácticas_Snowballing'!$AC$2:$AC$281,"SOFTWARE QUALITY > *") -> 0 | N43: =COUNTIFS('Prácticas_Revisiones'!$S$2:$S$282,"T034",'Prácticas_Revisiones'!$T$2:$T$282,"SOFTWARE SECURITY > *")+COUNTIFS('Prácticas_Snowballing'!$AB$2:$AB$281,"T034",'Prácticas_Snowballing'!$AC$2:$AC$281,"SOFTWARE SECURITY > *") -> 0 | O43: =COUNTIFS('Prácticas_Revisiones'!$S$2:$S$282,"T034",'Prácticas_Revisiones'!$T$2:$T$282,"PROFESSIONAL PRACTICE > *")+COUNTIFS('Prácticas_Snowballing'!$AB$2:$AB$281,"T034",'Prácticas_Snowballing'!$AC$2:$AC$281,"PROFESSIONAL PRACTICE > *") -> 0 | P43: =COUNTIFS('Prácticas_Revisiones'!$S$2:$S$282,"T034",'Prácticas_Revisiones'!$T$2:$T$282,"SOFTWARE ENG. ECONOMICS > *")+COUNTIFS('Prácticas_Snowballing'!$AB$2:$AB$281,"T034",'Prácticas_Snowballing'!$AC$2:$AC$281,"SOFTWARE ENG. ECONOMICS > *") -> 0 | Q43: =COUNTIFS('Prácticas_Revisiones'!$S$2:$S$282,"T034",'Prácticas_Revisiones'!$T$2:$T$282,"SOFTWARE ENG. MANAGEMENT > *")+COUNTIFS('Prácticas_Snowballing'!$AB$2:$AB$281,"T034",'Prácticas_Snowballing'!$AC$2:$AC$281,"SOFTWARE ENG. MANAGEMENT > *") -> 0 | R43: =COUNTIFS('Prácticas_Revisiones'!$S$2:$S$282,"T034",'Prácticas_Revisiones'!$T$2:$T$282,"Sin área SWEBOK")+COUNTIFS('Prácticas_Snowballing'!$AB$2:$AB$281,"T034",'Prácticas_Snowballing'!$AC$2:$AC$281,"Sin área SWEBOK") -> 0 | S43: =SUM(C43:R43) -> 0
B44: T035 Demostración silenciosa | C44: =COUNTIFS('Prácticas_Revisiones'!$S$2:$S$282,"T035",'Prácticas_Revisiones'!$T$2:$T$282,"REQUIREMENTS > *")+COUNTIFS('Prácticas_Snowballing'!$AB$2:$AB$281,"T035",'Prácticas_Snowballing'!$AC$2:$AC$281,"REQUIREMENTS > *") -> 0 | D44: =COUNTIFS('Prácticas_Revisiones'!$S$2:$S$282,"T035",'Prácticas_Revisiones'!$T$2:$T$282,"ARCHITECTURE > *")+COUNTIFS('Prácticas_Snowballing'!$AB$2:$AB$281,"T035",'Prácticas_Snowballing'!$AC$2:$AC$281,"ARCHITECTURE > *") -> 0 | E44: =COUNTIFS('Prácticas_Revisiones'!$S$2:$S$282,"T035",'Prácticas_Revisiones'!$T$2:$T$282,"DESIGN > *")+COUNTIFS('Prácticas_Snowballing'!$AB$2:$AB$281,"T035",'Prácticas_Snowballing'!$AC$2:$AC$281,"DESIGN > *") -> 0 | F44: =COUNTIFS('Prácticas_Revisiones'!$S$2:$S$282,"T035",'Prácticas_Revisiones'!$T$2:$T$282,"CONSTRUCTION > *")+COUNTIFS('Prácticas_Snowballing'!$AB$2:$AB$281,"T035",'Prácticas_Snowballing'!$AC$2:$AC$281,"CONSTRUCTION > *") -> 1 | G44: =COUNTIFS('Prácticas_Revisiones'!$S$2:$S$282,"T035",'Prácticas_Revisiones'!$T$2:$T$282,"SOFTWARE TESTING > *")+COUNTIFS('Prácticas_Snowballing'!$AB$2:$AB$281,"T035",'Prácticas_Snowballing'!$AC$2:$AC$281,"SOFTWARE TESTING > *") -> 0 | H44: =COUNTIFS('Prácticas_Revisiones'!$S$2:$S$282,"T035",'Prácticas_Revisiones'!$T$2:$T$282,"SOFTWARE ENG. OPERATIONS > *")+COUNTIFS('Prácticas_Snowballing'!$AB$2:$AB$281,"T035",'Prácticas_Snowballing'!$AC$2:$AC$281,"SOFTWARE ENG. OPERATIONS > *") -> 0 | I44: =COUNTIFS('Prácticas_Revisiones'!$S$2:$S$282,"T035",'Prácticas_Revisiones'!$T$2:$T$282,"MAINTENANCE > *")+COUNTIFS('Prácticas_Snowballing'!$AB$2:$AB$281,"T035",'Prácticas_Snowballing'!$AC$2:$AC$281,"MAINTENANCE > *") -> 1 | J44: =COUNTIFS('Prácticas_Revisiones'!$S$2:$S$282,"T035",'Prácticas_Revisiones'!$T$2:$T$282,"SOFTWARE CONFIG. MGMT. > *")+COUNTIFS('Prácticas_Snowballing'!$AB$2:$AB$281,"T035",'Prácticas_Snowballing'!$AC$2:$AC$281,"SOFTWARE CONFIG. MGMT. > *") -> 0 | K44: =COUNTIFS('Prácticas_Revisiones'!$S$2:$S$282,"T035",'Prácticas_Revisiones'!$T$2:$T$282,"SOFTWARE ENG. PROCESS > *")+COUNTIFS('Prácticas_Snowballing'!$AB$2:$AB$281,"T035",'Prácticas_Snowballing'!$AC$2:$AC$281,"SOFTWARE ENG. PROCESS > *") -> 0 | L44: =COUNTIFS('Prácticas_Revisiones'!$S$2:$S$282,"T035",'Prácticas_Revisiones'!$T$2:$T$282,"SOFTWARE ENG. MODELS/METH. > *")+COUNTIFS('Prácticas_Snowballing'!$AB$2:$AB$281,"T035",'Prácticas_Snowballing'!$AC$2:$AC$281,"SOFTWARE ENG. MODELS/METH. > *") -> 0 | M44: =COUNTIFS('Prácticas_Revisiones'!$S$2:$S$282,"T035",'Prácticas_Revisiones'!$T$2:$T$282,"SOFTWARE QUALITY > *")+COUNTIFS('Prácticas_Snowballing'!$AB$2:$AB$281,"T035",'Prácticas_Snowballing'!$AC$2:$AC$281,"SOFTWARE QUALITY > *") -> 0 | N44: =COUNTIFS('Prácticas_Revisiones'!$S$2:$S$282,"T035",'Prácticas_Revisiones'!$T$2:$T$282,"SOFTWARE SECURITY > *")+COUNTIFS('Prácticas_Snowballing'!$AB$2:$AB$281,"T035",'Prácticas_Snowballing'!$AC$2:$AC$281,"SOFTWARE SECURITY > *") -> 0 | O44: =COUNTIFS('Prácticas_Revisiones'!$S$2:$S$282,"T035",'Prácticas_Revisiones'!$T$2:$T$282,"PROFESSIONAL PRACTICE > *")+COUNTIFS('Prácticas_Snowballing'!$AB$2:$AB$281,"T035",'Prácticas_Snowballing'!$AC$2:$AC$281,"PROFESSIONAL PRACTICE > *") -> 0 | P44: =COUNTIFS('Prácticas_Revisiones'!$S$2:$S$282,"T035",'Prácticas_Revisiones'!$T$2:$T$282,"SOFTWARE ENG. ECONOMICS > *")+COUNTIFS('Prácticas_Snowballing'!$AB$2:$AB$281,"T035",'Prácticas_Snowballing'!$AC$2:$AC$281,"SOFTWARE ENG. ECONOMICS > *") -> 0 | Q44: =COUNTIFS('Prácticas_Revisiones'!$S$2:$S$282,"T035",'Prácticas_Revisiones'!$T$2:$T$282,"SOFTWARE ENG. MANAGEMENT > *")+COUNTIFS('Prácticas_Snowballing'!$AB$2:$AB$281,"T035",'Prácticas_Snowballing'!$AC$2:$AC$281,"SOFTWARE ENG. MANAGEMENT > *") -> 0 | R44: =COUNTIFS('Prácticas_Revisiones'!$S$2:$S$282,"T035",'Prácticas_Revisiones'!$T$2:$T$282,"Sin área SWEBOK")+COUNTIFS('Prácticas_Snowballing'!$AB$2:$AB$281,"T035",'Prácticas_Snowballing'!$AC$2:$AC$281,"Sin área SWEBOK") -> 0 | S44: =SUM(C44:R44) -> 2
B45: T036 Descripción de un personaje | C45: =COUNTIFS('Prácticas_Revisiones'!$S$2:$S$282,"T036",'Prácticas_Revisiones'!$T$2:$T$282,"REQUIREMENTS > *")+COUNTIFS('Prácticas_Snowballing'!$AB$2:$AB$281,"T036",'Prácticas_Snowballing'!$AC$2:$AC$281,"REQUIREMENTS > *") -> 0 | D45: =COUNTIFS('Prácticas_Revisiones'!$S$2:$S$282,"T036",'Prácticas_Revisiones'!$T$2:$T$282,"ARCHITECTURE > *")+COUNTIFS('Prácticas_Snowballing'!$AB$2:$AB$281,"T036",'Prácticas_Snowballing'!$AC$2:$AC$281,"ARCHITECTURE > *") -> 0 | E45: =COUNTIFS('Prácticas_Revisiones'!$S$2:$S$282,"T036",'Prácticas_Revisiones'!$T$2:$T$282,"DESIGN > *")+COUNTIFS('Prácticas_Snowballing'!$AB$2:$AB$281,"T036",'Prácticas_Snowballing'!$AC$2:$AC$281,"DESIGN > *") -> 0 | F45: =COUNTIFS('Prácticas_Revisiones'!$S$2:$S$282,"T036",'Prácticas_Revisiones'!$T$2:$T$282,"CONSTRUCTION > *")+COUNTIFS('Prácticas_Snowballing'!$AB$2:$AB$281,"T036",'Prácticas_Snowballing'!$AC$2:$AC$281,"CONSTRUCTION > *") -> 0 | G45: =COUNTIFS('Prácticas_Revisiones'!$S$2:$S$282,"T036",'Prácticas_Revisiones'!$T$2:$T$282,"SOFTWARE TESTING > *")+COUNTIFS('Prácticas_Snowballing'!$AB$2:$AB$281,"T036",'Prácticas_Snowballing'!$AC$2:$AC$281,"SOFTWARE TESTING > *") -> 0 | H45: =COUNTIFS('Prácticas_Revisiones'!$S$2:$S$282,"T036",'Prácticas_Revisiones'!$T$2:$T$282,"SOFTWARE ENG. OPERATIONS > *")+COUNTIFS('Prácticas_Snowballing'!$AB$2:$AB$281,"T036",'Prácticas_Snowballing'!$AC$2:$AC$281,"SOFTWARE ENG. OPERATIONS > *") -> 0 | I45: =COUNTIFS('Prácticas_Revisiones'!$S$2:$S$282,"T036",'Prácticas_Revisiones'!$T$2:$T$282,"MAINTENANCE > *")+COUNTIFS('Prácticas_Snowballing'!$AB$2:$AB$281,"T036",'Prácticas_Snowballing'!$AC$2:$AC$281,"MAINTENANCE > *") -> 0 | J45: =COUNTIFS('Prácticas_Revisiones'!$S$2:$S$282,"T036",'Prácticas_Revisiones'!$T$2:$T$282,"SOFTWARE CONFIG. MGMT. > *")+COUNTIFS('Prácticas_Snowballing'!$AB$2:$AB$281,"T036",'Prácticas_Snowballing'!$AC$2:$AC$281,"SOFTWARE CONFIG. MGMT. > *") -> 0 | K45: =COUNTIFS('Prácticas_Revisiones'!$S$2:$S$282,"T036",'Prácticas_Revisiones'!$T$2:$T$282,"SOFTWARE ENG. PROCESS > *")+COUNTIFS('Prácticas_Snowballing'!$AB$2:$AB$281,"T036",'Prácticas_Snowballing'!$AC$2:$AC$281,"SOFTWARE ENG. PROCESS > *") -> 0 | L45: =COUNTIFS('Prácticas_Revisiones'!$S$2:$S$282,"T036",'Prácticas_Revisiones'!$T$2:$T$282,"SOFTWARE ENG. MODELS/METH. > *")+COUNTIFS('Prácticas_Snowballing'!$AB$2:$AB$281,"T036",'Prácticas_Snowballing'!$AC$2:$AC$281,"SOFTWARE ENG. MODELS/METH. > *") -> 0 | M45: =COUNTIFS('Prácticas_Revisiones'!$S$2:$S$282,"T036",'Prácticas_Revisiones'!$T$2:$T$282,"SOFTWARE QUALITY > *")+COUNTIFS('Prácticas_Snowballing'!$AB$2:$AB$281,"T036",'Prácticas_Snowballing'!$AC$2:$AC$281,"SOFTWARE QUALITY > *") -> 0 | N45: =COUNTIFS('Prácticas_Revisiones'!$S$2:$S$282,"T036",'Prácticas_Revisiones'!$T$2:$T$282,"SOFTWARE SECURITY > *")+COUNTIFS('Prácticas_Snowballing'!$AB$2:$AB$281,"T036",'Prácticas_Snowballing'!$AC$2:$AC$281,"SOFTWARE SECURITY > *") -> 0 | O45: =COUNTIFS('Prácticas_Revisiones'!$S$2:$S$282,"T036",'Prácticas_Revisiones'!$T$2:$T$282,"PROFESSIONAL PRACTICE > *")+COUNTIFS('Prácticas_Snowballing'!$AB$2:$AB$281,"T036",'Prácticas_Snowballing'!$AC$2:$AC$281,"PROFESSIONAL PRACTICE > *") -> 0 | P45: =COUNTIFS('Prácticas_Revisiones'!$S$2:$S$282,"T036",'Prácticas_Revisiones'!$T$2:$T$282,"SOFTWARE ENG. ECONOMICS > *")+COUNTIFS('Prácticas_Snowballing'!$AB$2:$AB$281,"T036",'Prácticas_Snowballing'!$AC$2:$AC$281,"SOFTWARE ENG. ECONOMICS > *") -> 0 | Q45: =COUNTIFS('Prácticas_Revisiones'!$S$2:$S$282,"T036",'Prácticas_Revisiones'!$T$2:$T$282,"SOFTWARE ENG. MANAGEMENT > *")+COUNTIFS('Prácticas_Snowballing'!$AB$2:$AB$281,"T036",'Prácticas_Snowballing'!$AC$2:$AC$281,"SOFTWARE ENG. MANAGEMENT > *") -> 0 | R45: =COUNTIFS('Prácticas_Revisiones'!$S$2:$S$282,"T036",'Prácticas_Revisiones'!$T$2:$T$282,"Sin área SWEBOK")+COUNTIFS('Prácticas_Snowballing'!$AB$2:$AB$281,"T036",'Prácticas_Snowballing'!$AC$2:$AC$281,"Sin área SWEBOK") -> 0 | S45: =SUM(C45:R45) -> 0
B46: T037 Diálogos simultáneos | C46: =COUNTIFS('Prácticas_Revisiones'!$S$2:$S$282,"T037",'Prácticas_Revisiones'!$T$2:$T$282,"REQUIREMENTS > *")+COUNTIFS('Prácticas_Snowballing'!$AB$2:$AB$281,"T037",'Prácticas_Snowballing'!$AC$2:$AC$281,"REQUIREMENTS > *") -> 0 | D46: =COUNTIFS('Prácticas_Revisiones'!$S$2:$S$282,"T037",'Prácticas_Revisiones'!$T$2:$T$282,"ARCHITECTURE > *")+COUNTIFS('Prácticas_Snowballing'!$AB$2:$AB$281,"T037",'Prácticas_Snowballing'!$AC$2:$AC$281,"ARCHITECTURE > *") -> 0 | E46: =COUNTIFS('Prácticas_Revisiones'!$S$2:$S$282,"T037",'Prácticas_Revisiones'!$T$2:$T$282,"DESIGN > *")+COUNTIFS('Prácticas_Snowballing'!$AB$2:$AB$281,"T037",'Prácticas_Snowballing'!$AC$2:$AC$281,"DESIGN > *") -> 0 | F46: =COUNTIFS('Prácticas_Revisiones'!$S$2:$S$282,"T037",'Prácticas_Revisiones'!$T$2:$T$282,"CONSTRUCTION > *")+COUNTIFS('Prácticas_Snowballing'!$AB$2:$AB$281,"T037",'Prácticas_Snowballing'!$AC$2:$AC$281,"CONSTRUCTION > *") -> 1 | G46: =COUNTIFS('Prácticas_Revisiones'!$S$2:$S$282,"T037",'Prácticas_Revisiones'!$T$2:$T$282,"SOFTWARE TESTING > *")+COUNTIFS('Prácticas_Snowballing'!$AB$2:$AB$281,"T037",'Prácticas_Snowballing'!$AC$2:$AC$281,"SOFTWARE TESTING > *") -> 0 | H46: =COUNTIFS('Prácticas_Revisiones'!$S$2:$S$282,"T037",'Prácticas_Revisiones'!$T$2:$T$282,"SOFTWARE ENG. OPERATIONS > *")+COUNTIFS('Prácticas_Snowballing'!$AB$2:$AB$281,"T037",'Prácticas_Snowballing'!$AC$2:$AC$281,"SOFTWARE ENG. OPERATIONS > *") -> 0 | I46: =COUNTIFS('Prácticas_Revisiones'!$S$2:$S$282,"T037",'Prácticas_Revisiones'!$T$2:$T$282,"MAINTENANCE > *")+COUNTIFS('Prácticas_Snowballing'!$AB$2:$AB$281,"T037",'Prácticas_Snowballing'!$AC$2:$AC$281,"MAINTENANCE > *") -> 0 | J46: =COUNTIFS('Prácticas_Revisiones'!$S$2:$S$282,"T037",'Prácticas_Revisiones'!$T$2:$T$282,"SOFTWARE CONFIG. MGMT. > *")+COUNTIFS('Prácticas_Snowballing'!$AB$2:$AB$281,"T037",'Prácticas_Snowballing'!$AC$2:$AC$281,"SOFTWARE CONFIG. MGMT. > *") -> 0 | K46: =COUNTIFS('Prácticas_Revisiones'!$S$2:$S$282,"T037",'Prácticas_Revisiones'!$T$2:$T$282,"SOFTWARE ENG. PROCESS > *")+COUNTIFS('Prácticas_Snowballing'!$AB$2:$AB$281,"T037",'Prácticas_Snowballing'!$AC$2:$AC$281,"SOFTWARE ENG. PROCESS > *") -> 0 | L46: =COUNTIFS('Prácticas_Revisiones'!$S$2:$S$282,"T037",'Prácticas_Revisiones'!$T$2:$T$282,"SOFTWARE ENG. MODELS/METH. > *")+COUNTIFS('Prácticas_Snowballing'!$AB$2:$AB$281,"T037",'Prácticas_Snowballing'!$AC$2:$AC$281,"SOFTWARE ENG. MODELS/METH. > *") -> 0 | M46: =COUNTIFS('Prácticas_Revisiones'!$S$2:$S$282,"T037",'Prácticas_Revisiones'!$T$2:$T$282,"SOFTWARE QUALITY > *")+COUNTIFS('Prácticas_Snowballing'!$AB$2:$AB$281,"T037",'Prácticas_Snowballing'!$AC$2:$AC$281,"SOFTWARE QUALITY > *") -> 0 | N46: =COUNTIFS('Prácticas_Revisiones'!$S$2:$S$282,"T037",'Prácticas_Revisiones'!$T$2:$T$282,"SOFTWARE SECURITY > *")+COUNTIFS('Prácticas_Snowballing'!$AB$2:$AB$281,"T037",'Prácticas_Snowballing'!$AC$2:$AC$281,"SOFTWARE SECURITY > *") -> 0 | O46: =COUNTIFS('Prácticas_Revisiones'!$S$2:$S$282,"T037",'Prácticas_Revisiones'!$T$2:$T$282,"PROFESSIONAL PRACTICE > *")+COUNTIFS('Prácticas_Snowballing'!$AB$2:$AB$281,"T037",'Prácticas_Snowballing'!$AC$2:$AC$281,"PROFESSIONAL PRACTICE > *") -> 0 | P46: =COUNTIFS('Prácticas_Revisiones'!$S$2:$S$282,"T037",'Prácticas_Revisiones'!$T$2:$T$282,"SOFTWARE ENG. ECONOMICS > *")+COUNTIFS('Prácticas_Snowballing'!$AB$2:$AB$281,"T037",'Prácticas_Snowballing'!$AC$2:$AC$281,"SOFTWARE ENG. ECONOMICS > *") -> 0 | Q46: =COUNTIFS('Prácticas_Revisiones'!$S$2:$S$282,"T037",'Prácticas_Revisiones'!$T$2:$T$282,"SOFTWARE ENG. MANAGEMENT > *")+COUNTIFS('Prácticas_Snowballing'!$AB$2:$AB$281,"T037",'Prácticas_Snowballing'!$AC$2:$AC$281,"SOFTWARE ENG. MANAGEMENT > *") -> 0 | R46: =COUNTIFS('Prácticas_Revisiones'!$S$2:$S$282,"T037",'Prácticas_Revisiones'!$T$2:$T$282,"Sin área SWEBOK")+COUNTIFS('Prácticas_Snowballing'!$AB$2:$AB$281,"T037",'Prácticas_Snowballing'!$AC$2:$AC$281,"Sin área SWEBOK") -> 0 | S46: =SUM(C46:R46) -> 1
B47: T038 Encuesta interactiva | C47: =COUNTIFS('Prácticas_Revisiones'!$S$2:$S$282,"T038",'Prácticas_Revisiones'!$T$2:$T$282,"REQUIREMENTS > *")+COUNTIFS('Prácticas_Snowballing'!$AB$2:$AB$281,"T038",'Prácticas_Snowballing'!$AC$2:$AC$281,"REQUIREMENTS > *") -> 0 | D47: =COUNTIFS('Prácticas_Revisiones'!$S$2:$S$282,"T038",'Prácticas_Revisiones'!$T$2:$T$282,"ARCHITECTURE > *")+COUNTIFS('Prácticas_Snowballing'!$AB$2:$AB$281,"T038",'Prácticas_Snowballing'!$AC$2:$AC$281,"ARCHITECTURE > *") -> 0 | E47: =COUNTIFS('Prácticas_Revisiones'!$S$2:$S$282,"T038",'Prácticas_Revisiones'!$T$2:$T$282,"DESIGN > *")+COUNTIFS('Prácticas_Snowballing'!$AB$2:$AB$281,"T038",'Prácticas_Snowballing'!$AC$2:$AC$281,"DESIGN > *") -> 0 | F47: =COUNTIFS('Prácticas_Revisiones'!$S$2:$S$282,"T038",'Prácticas_Revisiones'!$T$2:$T$282,"CONSTRUCTION > *")+COUNTIFS('Prácticas_Snowballing'!$AB$2:$AB$281,"T038",'Prácticas_Snowballing'!$AC$2:$AC$281,"CONSTRUCTION > *") -> 0 | G47: =COUNTIFS('Prácticas_Revisiones'!$S$2:$S$282,"T038",'Prácticas_Revisiones'!$T$2:$T$282,"SOFTWARE TESTING > *")+COUNTIFS('Prácticas_Snowballing'!$AB$2:$AB$281,"T038",'Prácticas_Snowballing'!$AC$2:$AC$281,"SOFTWARE TESTING > *") -> 0 | H47: =COUNTIFS('Prácticas_Revisiones'!$S$2:$S$282,"T038",'Prácticas_Revisiones'!$T$2:$T$282,"SOFTWARE ENG. OPERATIONS > *")+COUNTIFS('Prácticas_Snowballing'!$AB$2:$AB$281,"T038",'Prácticas_Snowballing'!$AC$2:$AC$281,"SOFTWARE ENG. OPERATIONS > *") -> 0 | I47: =COUNTIFS('Prácticas_Revisiones'!$S$2:$S$282,"T038",'Prácticas_Revisiones'!$T$2:$T$282,"MAINTENANCE > *")+COUNTIFS('Prácticas_Snowballing'!$AB$2:$AB$281,"T038",'Prácticas_Snowballing'!$AC$2:$AC$281,"MAINTENANCE > *") -> 0 | J47: =COUNTIFS('Prácticas_Revisiones'!$S$2:$S$282,"T038",'Prácticas_Revisiones'!$T$2:$T$282,"SOFTWARE CONFIG. MGMT. > *")+COUNTIFS('Prácticas_Snowballing'!$AB$2:$AB$281,"T038",'Prácticas_Snowballing'!$AC$2:$AC$281,"SOFTWARE CONFIG. MGMT. > *") -> 0 | K47: =COUNTIFS('Prácticas_Revisiones'!$S$2:$S$282,"T038",'Prácticas_Revisiones'!$T$2:$T$282,"SOFTWARE ENG. PROCESS > *")+COUNTIFS('Prácticas_Snowballing'!$AB$2:$AB$281,"T038",'Prácticas_Snowballing'!$AC$2:$AC$281,"SOFTWARE ENG. PROCESS > *") -> 0 | L47: =COUNTIFS('Prácticas_Revisiones'!$S$2:$S$282,"T038",'Prácticas_Revisiones'!$T$2:$T$282,"SOFTWARE ENG. MODELS/METH. > *")+COUNTIFS('Prácticas_Snowballing'!$AB$2:$AB$281,"T038",'Prácticas_Snowballing'!$AC$2:$AC$281,"SOFTWARE ENG. MODELS/METH. > *") -> 0 | M47: =COUNTIFS('Prácticas_Revisiones'!$S$2:$S$282,"T038",'Prácticas_Revisiones'!$T$2:$T$282,"SOFTWARE QUALITY > *")+COUNTIFS('Prácticas_Snowballing'!$AB$2:$AB$281,"T038",'Prácticas_Snowballing'!$AC$2:$AC$281,"SOFTWARE QUALITY > *") -> 0 | N47: =COUNTIFS('Prácticas_Revisiones'!$S$2:$S$282,"T038",'Prácticas_Revisiones'!$T$2:$T$282,"SOFTWARE SECURITY > *")+COUNTIFS('Prácticas_Snowballing'!$AB$2:$AB$281,"T038",'Prácticas_Snowballing'!$AC$2:$AC$281,"SOFTWARE SECURITY > *") -> 0 | O47: =COUNTIFS('Prácticas_Revisiones'!$S$2:$S$282,"T038",'Prácticas_Revisiones'!$T$2:$T$282,"PROFESSIONAL PRACTICE > *")+COUNTIFS('Prácticas_Snowballing'!$AB$2:$AB$281,"T038",'Prácticas_Snowballing'!$AC$2:$AC$281,"PROFESSIONAL PRACTICE > *") -> 0 | P47: =COUNTIFS('Prácticas_Revisiones'!$S$2:$S$282,"T038",'Prácticas_Revisiones'!$T$2:$T$282,"SOFTWARE ENG. ECONOMICS > *")+COUNTIFS('Prácticas_Snowballing'!$AB$2:$AB$281,"T038",'Prácticas_Snowballing'!$AC$2:$AC$281,"SOFTWARE ENG. ECONOMICS > *") -> 0 | Q47: =COUNTIFS('Prácticas_Revisiones'!$S$2:$S$282,"T038",'Prácticas_Revisiones'!$T$2:$T$282,"SOFTWARE ENG. MANAGEMENT > *")+COUNTIFS('Prácticas_Snowballing'!$AB$2:$AB$281,"T038",'Prácticas_Snowballing'!$AC$2:$AC$281,"SOFTWARE ENG. MANAGEMENT > *") -> 0 | R47: =COUNTIFS('Prácticas_Revisiones'!$S$2:$S$282,"T038",'Prácticas_Revisiones'!$T$2:$T$282,"Sin área SWEBOK")+COUNTIFS('Prácticas_Snowballing'!$AB$2:$AB$281,"T038",'Prácticas_Snowballing'!$AC$2:$AC$281,"Sin área SWEBOK") -> 0 | S47: =SUM(C47:R47) -> 0
B48: T039 Entrevista | C48: =COUNTIFS('Prácticas_Revisiones'!$S$2:$S$282,"T039",'Prácticas_Revisiones'!$T$2:$T$282,"REQUIREMENTS > *")+COUNTIFS('Prácticas_Snowballing'!$AB$2:$AB$281,"T039",'Prácticas_Snowballing'!$AC$2:$AC$281,"REQUIREMENTS > *") -> 4 | D48: =COUNTIFS('Prácticas_Revisiones'!$S$2:$S$282,"T039",'Prácticas_Revisiones'!$T$2:$T$282,"ARCHITECTURE > *")+COUNTIFS('Prácticas_Snowballing'!$AB$2:$AB$281,"T039",'Prácticas_Snowballing'!$AC$2:$AC$281,"ARCHITECTURE > *") -> 0 | E48: =COUNTIFS('Prácticas_Revisiones'!$S$2:$S$282,"T039",'Prácticas_Revisiones'!$T$2:$T$282,"DESIGN > *")+COUNTIFS('Prácticas_Snowballing'!$AB$2:$AB$281,"T039",'Prácticas_Snowballing'!$AC$2:$AC$281,"DESIGN > *") -> 0 | F48: =COUNTIFS('Prácticas_Revisiones'!$S$2:$S$282,"T039",'Prácticas_Revisiones'!$T$2:$T$282,"CONSTRUCTION > *")+COUNTIFS('Prácticas_Snowballing'!$AB$2:$AB$281,"T039",'Prácticas_Snowballing'!$AC$2:$AC$281,"CONSTRUCTION > *") -> 0 | G48: =COUNTIFS('Prácticas_Revisiones'!$S$2:$S$282,"T039",'Prácticas_Revisiones'!$T$2:$T$282,"SOFTWARE TESTING > *")+COUNTIFS('Prácticas_Snowballing'!$AB$2:$AB$281,"T039",'Prácticas_Snowballing'!$AC$2:$AC$281,"SOFTWARE TESTING > *") -> 0 | H48: =COUNTIFS('Prácticas_Revisiones'!$S$2:$S$282,"T039",'Prácticas_Revisiones'!$T$2:$T$282,"SOFTWARE ENG. OPERATIONS > *")+COUNTIFS('Prácticas_Snowballing'!$AB$2:$AB$281,"T039",'Prácticas_Snowballing'!$AC$2:$AC$281,"SOFTWARE ENG. OPERATIONS > *") -> 0 | I48: =COUNTIFS('Prácticas_Revisiones'!$S$2:$S$282,"T039",'Prácticas_Revisiones'!$T$2:$T$282,"MAINTENANCE > *")+COUNTIFS('Prácticas_Snowballing'!$AB$2:$AB$281,"T039",'Prácticas_Snowballing'!$AC$2:$AC$281,"MAINTENANCE > *") -> 0 | J48: =COUNTIFS('Prácticas_Revisiones'!$S$2:$S$282,"T039",'Prácticas_Revisiones'!$T$2:$T$282,"SOFTWARE CONFIG. MGMT. > *")+COUNTIFS('Prácticas_Snowballing'!$AB$2:$AB$281,"T039",'Prácticas_Snowballing'!$AC$2:$AC$281,"SOFTWARE CONFIG. MGMT. > *") -> 0 | K48: =COUNTIFS('Prácticas_Revisiones'!$S$2:$S$282,"T039",'Prácticas_Revisiones'!$T$2:$T$282,"SOFTWARE ENG. PROCESS > *")+COUNTIFS('Prácticas_Snowballing'!$AB$2:$AB$281,"T039",'Prácticas_Snowballing'!$AC$2:$AC$281,"SOFTWARE ENG. PROCESS > *") -> 0 | L48: =COUNTIFS('Prácticas_Revisiones'!$S$2:$S$282,"T039",'Prácticas_Revisiones'!$T$2:$T$282,"SOFTWARE ENG. MODELS/METH. > *")+COUNTIFS('Prácticas_Snowballing'!$AB$2:$AB$281,"T039",'Prácticas_Snowballing'!$AC$2:$AC$281,"SOFTWARE ENG. MODELS/METH. > *") -> 0 | M48: =COUNTIFS('Prácticas_Revisiones'!$S$2:$S$282,"T039",'Prácticas_Revisiones'!$T$2:$T$282,"SOFTWARE QUALITY > *")+COUNTIFS('Prácticas_Snowballing'!$AB$2:$AB$281,"T039",'Prácticas_Snowballing'!$AC$2:$AC$281,"SOFTWARE QUALITY > *") -> 0 | N48: =COUNTIFS('Prácticas_Revisiones'!$S$2:$S$282,"T039",'Prácticas_Revisiones'!$T$2:$T$282,"SOFTWARE SECURITY > *")+COUNTIFS('Prácticas_Snowballing'!$AB$2:$AB$281,"T039",'Prácticas_Snowballing'!$AC$2:$AC$281,"SOFTWARE SECURITY > *") -> 0 | O48: =COUNTIFS('Prácticas_Revisiones'!$S$2:$S$282,"T039",'Prácticas_Revisiones'!$T$2:$T$282,"PROFESSIONAL PRACTICE > *")+COUNTIFS('Prácticas_Snowballing'!$AB$2:$AB$281,"T039",'Prácticas_Snowballing'!$AC$2:$AC$281,"PROFESSIONAL PRACTICE > *") -> 0 | P48: =COUNTIFS('Prácticas_Revisiones'!$S$2:$S$282,"T039",'Prácticas_Revisiones'!$T$2:$T$282,"SOFTWARE ENG. ECONOMICS > *")+COUNTIFS('Prácticas_Snowballing'!$AB$2:$AB$281,"T039",'Prácticas_Snowballing'!$AC$2:$AC$281,"SOFTWARE ENG. ECONOMICS > *") -> 0 | Q48: =COUNTIFS('Prácticas_Revisiones'!$S$2:$S$282,"T039",'Prácticas_Revisiones'!$T$2:$T$282,"SOFTWARE ENG. MANAGEMENT > *")+COUNTIFS('Prácticas_Snowballing'!$AB$2:$AB$281,"T039",'Prácticas_Snowballing'!$AC$2:$AC$281,"SOFTWARE ENG. MANAGEMENT > *") -> 0 | R48: =COUNTIFS('Prácticas_Revisiones'!$S$2:$S$282,"T039",'Prácticas_Revisiones'!$T$2:$T$282,"Sin área SWEBOK")+COUNTIFS('Prácticas_Snowballing'!$AB$2:$AB$281,"T039",'Prácticas_Snowballing'!$AC$2:$AC$281,"Sin área SWEBOK") -> 0 | S48: =SUM(C48:R48) -> 4
B49: T040 Estudio intercalado | C49: =COUNTIFS('Prácticas_Revisiones'!$S$2:$S$282,"T040",'Prácticas_Revisiones'!$T$2:$T$282,"REQUIREMENTS > *")+COUNTIFS('Prácticas_Snowballing'!$AB$2:$AB$281,"T040",'Prácticas_Snowballing'!$AC$2:$AC$281,"REQUIREMENTS > *") -> 0 | D49: =COUNTIFS('Prácticas_Revisiones'!$S$2:$S$282,"T040",'Prácticas_Revisiones'!$T$2:$T$282,"ARCHITECTURE > *")+COUNTIFS('Prácticas_Snowballing'!$AB$2:$AB$281,"T040",'Prácticas_Snowballing'!$AC$2:$AC$281,"ARCHITECTURE > *") -> 0 | E49: =COUNTIFS('Prácticas_Revisiones'!$S$2:$S$282,"T040",'Prácticas_Revisiones'!$T$2:$T$282,"DESIGN > *")+COUNTIFS('Prácticas_Snowballing'!$AB$2:$AB$281,"T040",'Prácticas_Snowballing'!$AC$2:$AC$281,"DESIGN > *") -> 0 | F49: =COUNTIFS('Prácticas_Revisiones'!$S$2:$S$282,"T040",'Prácticas_Revisiones'!$T$2:$T$282,"CONSTRUCTION > *")+COUNTIFS('Prácticas_Snowballing'!$AB$2:$AB$281,"T040",'Prácticas_Snowballing'!$AC$2:$AC$281,"CONSTRUCTION > *") -> 0 | G49: =COUNTIFS('Prácticas_Revisiones'!$S$2:$S$282,"T040",'Prácticas_Revisiones'!$T$2:$T$282,"SOFTWARE TESTING > *")+COUNTIFS('Prácticas_Snowballing'!$AB$2:$AB$281,"T040",'Prácticas_Snowballing'!$AC$2:$AC$281,"SOFTWARE TESTING > *") -> 0 | H49: =COUNTIFS('Prácticas_Revisiones'!$S$2:$S$282,"T040",'Prácticas_Revisiones'!$T$2:$T$282,"SOFTWARE ENG. OPERATIONS > *")+COUNTIFS('Prácticas_Snowballing'!$AB$2:$AB$281,"T040",'Prácticas_Snowballing'!$AC$2:$AC$281,"SOFTWARE ENG. OPERATIONS > *") -> 0 | I49: =COUNTIFS('Prácticas_Revisiones'!$S$2:$S$282,"T040",'Prácticas_Revisiones'!$T$2:$T$282,"MAINTENANCE > *")+COUNTIFS('Prácticas_Snowballing'!$AB$2:$AB$281,"T040",'Prácticas_Snowballing'!$AC$2:$AC$281,"MAINTENANCE > *") -> 0 | J49: =COUNTIFS('Prácticas_Revisiones'!$S$2:$S$282,"T040",'Prácticas_Revisiones'!$T$2:$T$282,"SOFTWARE CONFIG. MGMT. > *")+COUNTIFS('Prácticas_Snowballing'!$AB$2:$AB$281,"T040",'Prácticas_Snowballing'!$AC$2:$AC$281,"SOFTWARE CONFIG. MGMT. > *") -> 0 | K49: =COUNTIFS('Prácticas_Revisiones'!$S$2:$S$282,"T040",'Prácticas_Revisiones'!$T$2:$T$282,"SOFTWARE ENG. PROCESS > *")+COUNTIFS('Prácticas_Snowballing'!$AB$2:$AB$281,"T040",'Prácticas_Snowballing'!$AC$2:$AC$281,"SOFTWARE ENG. PROCESS > *") -> 0 | L49: =COUNTIFS('Prácticas_Revisiones'!$S$2:$S$282,"T040",'Prácticas_Revisiones'!$T$2:$T$282,"SOFTWARE ENG. MODELS/METH. > *")+COUNTIFS('Prácticas_Snowballing'!$AB$2:$AB$281,"T040",'Prácticas_Snowballing'!$AC$2:$AC$281,"SOFTWARE ENG. MODELS/METH. > *") -> 0 | M49: =COUNTIFS('Prácticas_Revisiones'!$S$2:$S$282,"T040",'Prácticas_Revisiones'!$T$2:$T$282,"SOFTWARE QUALITY > *")+COUNTIFS('Prácticas_Snowballing'!$AB$2:$AB$281,"T040",'Prácticas_Snowballing'!$AC$2:$AC$281,"SOFTWARE QUALITY > *") -> 0 | N49: =COUNTIFS('Prácticas_Revisiones'!$S$2:$S$282,"T040",'Prácticas_Revisiones'!$T$2:$T$282,"SOFTWARE SECURITY > *")+COUNTIFS('Prácticas_Snowballing'!$AB$2:$AB$281,"T040",'Prácticas_Snowballing'!$AC$2:$AC$281,"SOFTWARE SECURITY > *") -> 0 | O49: =COUNTIFS('Prácticas_Revisiones'!$S$2:$S$282,"T040",'Prácticas_Revisiones'!$T$2:$T$282,"PROFESSIONAL PRACTICE > *")+COUNTIFS('Prácticas_Snowballing'!$AB$2:$AB$281,"T040",'Prácticas_Snowballing'!$AC$2:$AC$281,"PROFESSIONAL PRACTICE > *") -> 0 | P49: =COUNTIFS('Prácticas_Revisiones'!$S$2:$S$282,"T040",'Prácticas_Revisiones'!$T$2:$T$282,"SOFTWARE ENG. ECONOMICS > *")+COUNTIFS('Prácticas_Snowballing'!$AB$2:$AB$281,"T040",'Prácticas_Snowballing'!$AC$2:$AC$281,"SOFTWARE ENG. ECONOMICS > *") -> 0 | Q49: =COUNTIFS('Prácticas_Revisiones'!$S$2:$S$282,"T040",'Prácticas_Revisiones'!$T$2:$T$282,"SOFTWARE ENG. MANAGEMENT > *")+COUNTIFS('Prácticas_Snowballing'!$AB$2:$AB$281,"T040",'Prácticas_Snowballing'!$AC$2:$AC$281,"SOFTWARE ENG. MANAGEMENT > *") -> 0 | R49: =COUNTIFS('Prácticas_Revisiones'!$S$2:$S$282,"T040",'Prácticas_Revisiones'!$T$2:$T$282,"Sin área SWEBOK")+COUNTIFS('Prácticas_Snowballing'!$AB$2:$AB$281,"T040",'Prácticas_Snowballing'!$AC$2:$AC$281,"Sin área SWEBOK") -> 0 | S49: =SUM(C49:R49) -> 0
B50: T041 Examen práctico | C50: =COUNTIFS('Prácticas_Revisiones'!$S$2:$S$282,"T041",'Prácticas_Revisiones'!$T$2:$T$282,"REQUIREMENTS > *")+COUNTIFS('Prácticas_Snowballing'!$AB$2:$AB$281,"T041",'Prácticas_Snowballing'!$AC$2:$AC$281,"REQUIREMENTS > *") -> 0 | D50: =COUNTIFS('Prácticas_Revisiones'!$S$2:$S$282,"T041",'Prácticas_Revisiones'!$T$2:$T$282,"ARCHITECTURE > *")+COUNTIFS('Prácticas_Snowballing'!$AB$2:$AB$281,"T041",'Prácticas_Snowballing'!$AC$2:$AC$281,"ARCHITECTURE > *") -> 0 | E50: =COUNTIFS('Prácticas_Revisiones'!$S$2:$S$282,"T041",'Prácticas_Revisiones'!$T$2:$T$282,"DESIGN > *")+COUNTIFS('Prácticas_Snowballing'!$AB$2:$AB$281,"T041",'Prácticas_Snowballing'!$AC$2:$AC$281,"DESIGN > *") -> 0 | F50: =COUNTIFS('Prácticas_Revisiones'!$S$2:$S$282,"T041",'Prácticas_Revisiones'!$T$2:$T$282,"CONSTRUCTION > *")+COUNTIFS('Prácticas_Snowballing'!$AB$2:$AB$281,"T041",'Prácticas_Snowballing'!$AC$2:$AC$281,"CONSTRUCTION > *") -> 22 | G50: =COUNTIFS('Prácticas_Revisiones'!$S$2:$S$282,"T041",'Prácticas_Revisiones'!$T$2:$T$282,"SOFTWARE TESTING > *")+COUNTIFS('Prácticas_Snowballing'!$AB$2:$AB$281,"T041",'Prácticas_Snowballing'!$AC$2:$AC$281,"SOFTWARE TESTING > *") -> 5 | H50: =COUNTIFS('Prácticas_Revisiones'!$S$2:$S$282,"T041",'Prácticas_Revisiones'!$T$2:$T$282,"SOFTWARE ENG. OPERATIONS > *")+COUNTIFS('Prácticas_Snowballing'!$AB$2:$AB$281,"T041",'Prácticas_Snowballing'!$AC$2:$AC$281,"SOFTWARE ENG. OPERATIONS > *") -> 0 | I50: =COUNTIFS('Prácticas_Revisiones'!$S$2:$S$282,"T041",'Prácticas_Revisiones'!$T$2:$T$282,"MAINTENANCE > *")+COUNTIFS('Prácticas_Snowballing'!$AB$2:$AB$281,"T041",'Prácticas_Snowballing'!$AC$2:$AC$281,"MAINTENANCE > *") -> 0 | J50: =COUNTIFS('Prácticas_Revisiones'!$S$2:$S$282,"T041",'Prácticas_Revisiones'!$T$2:$T$282,"SOFTWARE CONFIG. MGMT. > *")+COUNTIFS('Prácticas_Snowballing'!$AB$2:$AB$281,"T041",'Prácticas_Snowballing'!$AC$2:$AC$281,"SOFTWARE CONFIG. MGMT. > *") -> 1 | K50: =COUNTIFS('Prácticas_Revisiones'!$S$2:$S$282,"T041",'Prácticas_Revisiones'!$T$2:$T$282,"SOFTWARE ENG. PROCESS > *")+COUNTIFS('Prácticas_Snowballing'!$AB$2:$AB$281,"T041",'Prácticas_Snowballing'!$AC$2:$AC$281,"SOFTWARE ENG. PROCESS > *") -> 0 | L50: =COUNTIFS('Prácticas_Revisiones'!$S$2:$S$282,"T041",'Prácticas_Revisiones'!$T$2:$T$282,"SOFTWARE ENG. MODELS/METH. > *")+COUNTIFS('Prácticas_Snowballing'!$AB$2:$AB$281,"T041",'Prácticas_Snowballing'!$AC$2:$AC$281,"SOFTWARE ENG. MODELS/METH. > *") -> 1 | M50: =COUNTIFS('Prácticas_Revisiones'!$S$2:$S$282,"T041",'Prácticas_Revisiones'!$T$2:$T$282,"SOFTWARE QUALITY > *")+COUNTIFS('Prácticas_Snowballing'!$AB$2:$AB$281,"T041",'Prácticas_Snowballing'!$AC$2:$AC$281,"SOFTWARE QUALITY > *") -> 2 | N50: =COUNTIFS('Prácticas_Revisiones'!$S$2:$S$282,"T041",'Prácticas_Revisiones'!$T$2:$T$282,"SOFTWARE SECURITY > *")+COUNTIFS('Prácticas_Snowballing'!$AB$2:$AB$281,"T041",'Prácticas_Snowballing'!$AC$2:$AC$281,"SOFTWARE SECURITY > *") -> 0 | O50: =COUNTIFS('Prácticas_Revisiones'!$S$2:$S$282,"T041",'Prácticas_Revisiones'!$T$2:$T$282,"PROFESSIONAL PRACTICE > *")+COUNTIFS('Prácticas_Snowballing'!$AB$2:$AB$281,"T041",'Prácticas_Snowballing'!$AC$2:$AC$281,"PROFESSIONAL PRACTICE > *") -> 0 | P50: =COUNTIFS('Prácticas_Revisiones'!$S$2:$S$282,"T041",'Prácticas_Revisiones'!$T$2:$T$282,"SOFTWARE ENG. ECONOMICS > *")+COUNTIFS('Prácticas_Snowballing'!$AB$2:$AB$281,"T041",'Prácticas_Snowballing'!$AC$2:$AC$281,"SOFTWARE ENG. ECONOMICS > *") -> 0 | Q50: =COUNTIFS('Prácticas_Revisiones'!$S$2:$S$282,"T041",'Prácticas_Revisiones'!$T$2:$T$282,"SOFTWARE ENG. MANAGEMENT > *")+COUNTIFS('Prácticas_Snowballing'!$AB$2:$AB$281,"T041",'Prácticas_Snowballing'!$AC$2:$AC$281,"SOFTWARE ENG. MANAGEMENT > *") -> 0 | R50: =COUNTIFS('Prácticas_Revisiones'!$S$2:$S$282,"T041",'Prácticas_Revisiones'!$T$2:$T$282,"Sin área SWEBOK")+COUNTIFS('Prácticas_Snowballing'!$AB$2:$AB$281,"T041",'Prácticas_Snowballing'!$AC$2:$AC$281,"Sin área SWEBOK") -> 0 | S50: =SUM(C50:R50) -> 31
B51: T042 Foro | C51: =COUNTIFS('Prácticas_Revisiones'!$S$2:$S$282,"T042",'Prácticas_Revisiones'!$T$2:$T$282,"REQUIREMENTS > *")+COUNTIFS('Prácticas_Snowballing'!$AB$2:$AB$281,"T042",'Prácticas_Snowballing'!$AC$2:$AC$281,"REQUIREMENTS > *") -> 0 | D51: =COUNTIFS('Prácticas_Revisiones'!$S$2:$S$282,"T042",'Prácticas_Revisiones'!$T$2:$T$282,"ARCHITECTURE > *")+COUNTIFS('Prácticas_Snowballing'!$AB$2:$AB$281,"T042",'Prácticas_Snowballing'!$AC$2:$AC$281,"ARCHITECTURE > *") -> 0 | E51: =COUNTIFS('Prácticas_Revisiones'!$S$2:$S$282,"T042",'Prácticas_Revisiones'!$T$2:$T$282,"DESIGN > *")+COUNTIFS('Prácticas_Snowballing'!$AB$2:$AB$281,"T042",'Prácticas_Snowballing'!$AC$2:$AC$281,"DESIGN > *") -> 0 | F51: =COUNTIFS('Prácticas_Revisiones'!$S$2:$S$282,"T042",'Prácticas_Revisiones'!$T$2:$T$282,"CONSTRUCTION > *")+COUNTIFS('Prácticas_Snowballing'!$AB$2:$AB$281,"T042",'Prácticas_Snowballing'!$AC$2:$AC$281,"CONSTRUCTION > *") -> 2 | G51: =COUNTIFS('Prácticas_Revisiones'!$S$2:$S$282,"T042",'Prácticas_Revisiones'!$T$2:$T$282,"SOFTWARE TESTING > *")+COUNTIFS('Prácticas_Snowballing'!$AB$2:$AB$281,"T042",'Prácticas_Snowballing'!$AC$2:$AC$281,"SOFTWARE TESTING > *") -> 0 | H51: =COUNTIFS('Prácticas_Revisiones'!$S$2:$S$282,"T042",'Prácticas_Revisiones'!$T$2:$T$282,"SOFTWARE ENG. OPERATIONS > *")+COUNTIFS('Prácticas_Snowballing'!$AB$2:$AB$281,"T042",'Prácticas_Snowballing'!$AC$2:$AC$281,"SOFTWARE ENG. OPERATIONS > *") -> 0 | I51: =COUNTIFS('Prácticas_Revisiones'!$S$2:$S$282,"T042",'Prácticas_Revisiones'!$T$2:$T$282,"MAINTENANCE > *")+COUNTIFS('Prácticas_Snowballing'!$AB$2:$AB$281,"T042",'Prácticas_Snowballing'!$AC$2:$AC$281,"MAINTENANCE > *") -> 0 | J51: =COUNTIFS('Prácticas_Revisiones'!$S$2:$S$282,"T042",'Prácticas_Revisiones'!$T$2:$T$282,"SOFTWARE CONFIG. MGMT. > *")+COUNTIFS('Prácticas_Snowballing'!$AB$2:$AB$281,"T042",'Prácticas_Snowballing'!$AC$2:$AC$281,"SOFTWARE CONFIG. MGMT. > *") -> 0 | K51: =COUNTIFS('Prácticas_Revisiones'!$S$2:$S$282,"T042",'Prácticas_Revisiones'!$T$2:$T$282,"SOFTWARE ENG. PROCESS > *")+COUNTIFS('Prácticas_Snowballing'!$AB$2:$AB$281,"T042",'Prácticas_Snowballing'!$AC$2:$AC$281,"SOFTWARE ENG. PROCESS > *") -> 0 | L51: =COUNTIFS('Prácticas_Revisiones'!$S$2:$S$282,"T042",'Prácticas_Revisiones'!$T$2:$T$282,"SOFTWARE ENG. MODELS/METH. > *")+COUNTIFS('Prácticas_Snowballing'!$AB$2:$AB$281,"T042",'Prácticas_Snowballing'!$AC$2:$AC$281,"SOFTWARE ENG. MODELS/METH. > *") -> 0 | M51: =COUNTIFS('Prácticas_Revisiones'!$S$2:$S$282,"T042",'Prácticas_Revisiones'!$T$2:$T$282,"SOFTWARE QUALITY > *")+COUNTIFS('Prácticas_Snowballing'!$AB$2:$AB$281,"T042",'Prácticas_Snowballing'!$AC$2:$AC$281,"SOFTWARE QUALITY > *") -> 0 | N51: =COUNTIFS('Prácticas_Revisiones'!$S$2:$S$282,"T042",'Prácticas_Revisiones'!$T$2:$T$282,"SOFTWARE SECURITY > *")+COUNTIFS('Prácticas_Snowballing'!$AB$2:$AB$281,"T042",'Prácticas_Snowballing'!$AC$2:$AC$281,"SOFTWARE SECURITY > *") -> 0 | O51: =COUNTIFS('Prácticas_Revisiones'!$S$2:$S$282,"T042",'Prácticas_Revisiones'!$T$2:$T$282,"PROFESSIONAL PRACTICE > *")+COUNTIFS('Prácticas_Snowballing'!$AB$2:$AB$281,"T042",'Prácticas_Snowballing'!$AC$2:$AC$281,"PROFESSIONAL PRACTICE > *") -> 2 | P51: =COUNTIFS('Prácticas_Revisiones'!$S$2:$S$282,"T042",'Prácticas_Revisiones'!$T$2:$T$282,"SOFTWARE ENG. ECONOMICS > *")+COUNTIFS('Prácticas_Snowballing'!$AB$2:$AB$281,"T042",'Prácticas_Snowballing'!$AC$2:$AC$281,"SOFTWARE ENG. ECONOMICS > *") -> 0 | Q51: =COUNTIFS('Prácticas_Revisiones'!$S$2:$S$282,"T042",'Prácticas_Revisiones'!$T$2:$T$282,"SOFTWARE ENG. MANAGEMENT > *")+COUNTIFS('Prácticas_Snowballing'!$AB$2:$AB$281,"T042",'Prácticas_Snowballing'!$AC$2:$AC$281,"SOFTWARE ENG. MANAGEMENT > *") -> 0 | R51: =COUNTIFS('Prácticas_Revisiones'!$S$2:$S$282,"T042",'Prácticas_Revisiones'!$T$2:$T$282,"Sin área SWEBOK")+COUNTIFS('Prácticas_Snowballing'!$AB$2:$AB$281,"T042",'Prácticas_Snowballing'!$AC$2:$AC$281,"Sin área SWEBOK") -> 0 | S51: =SUM(C51:R51) -> 4
B52: T043 Grupos de discusión | C52: =COUNTIFS('Prácticas_Revisiones'!$S$2:$S$282,"T043",'Prácticas_Revisiones'!$T$2:$T$282,"REQUIREMENTS > *")+COUNTIFS('Prácticas_Snowballing'!$AB$2:$AB$281,"T043",'Prácticas_Snowballing'!$AC$2:$AC$281,"REQUIREMENTS > *") -> 0 | D52: =COUNTIFS('Prácticas_Revisiones'!$S$2:$S$282,"T043",'Prácticas_Revisiones'!$T$2:$T$282,"ARCHITECTURE > *")+COUNTIFS('Prácticas_Snowballing'!$AB$2:$AB$281,"T043",'Prácticas_Snowballing'!$AC$2:$AC$281,"ARCHITECTURE > *") -> 0 | E52: =COUNTIFS('Prácticas_Revisiones'!$S$2:$S$282,"T043",'Prácticas_Revisiones'!$T$2:$T$282,"DESIGN > *")+COUNTIFS('Prácticas_Snowballing'!$AB$2:$AB$281,"T043",'Prácticas_Snowballing'!$AC$2:$AC$281,"DESIGN > *") -> 0 | F52: =COUNTIFS('Prácticas_Revisiones'!$S$2:$S$282,"T043",'Prácticas_Revisiones'!$T$2:$T$282,"CONSTRUCTION > *")+COUNTIFS('Prácticas_Snowballing'!$AB$2:$AB$281,"T043",'Prácticas_Snowballing'!$AC$2:$AC$281,"CONSTRUCTION > *") -> 0 | G52: =COUNTIFS('Prácticas_Revisiones'!$S$2:$S$282,"T043",'Prácticas_Revisiones'!$T$2:$T$282,"SOFTWARE TESTING > *")+COUNTIFS('Prácticas_Snowballing'!$AB$2:$AB$281,"T043",'Prácticas_Snowballing'!$AC$2:$AC$281,"SOFTWARE TESTING > *") -> 0 | H52: =COUNTIFS('Prácticas_Revisiones'!$S$2:$S$282,"T043",'Prácticas_Revisiones'!$T$2:$T$282,"SOFTWARE ENG. OPERATIONS > *")+COUNTIFS('Prácticas_Snowballing'!$AB$2:$AB$281,"T043",'Prácticas_Snowballing'!$AC$2:$AC$281,"SOFTWARE ENG. OPERATIONS > *") -> 0 | I52: =COUNTIFS('Prácticas_Revisiones'!$S$2:$S$282,"T043",'Prácticas_Revisiones'!$T$2:$T$282,"MAINTENANCE > *")+COUNTIFS('Prácticas_Snowballing'!$AB$2:$AB$281,"T043",'Prácticas_Snowballing'!$AC$2:$AC$281,"MAINTENANCE > *") -> 0 | J52: =COUNTIFS('Prácticas_Revisiones'!$S$2:$S$282,"T043",'Prácticas_Revisiones'!$T$2:$T$282,"SOFTWARE CONFIG. MGMT. > *")+COUNTIFS('Prácticas_Snowballing'!$AB$2:$AB$281,"T043",'Prácticas_Snowballing'!$AC$2:$AC$281,"SOFTWARE CONFIG. MGMT. > *") -> 0 | K52: =COUNTIFS('Prácticas_Revisiones'!$S$2:$S$282,"T043",'Prácticas_Revisiones'!$T$2:$T$282,"SOFTWARE ENG. PROCESS > *")+COUNTIFS('Prácticas_Snowballing'!$AB$2:$AB$281,"T043",'Prácticas_Snowballing'!$AC$2:$AC$281,"SOFTWARE ENG. PROCESS > *") -> 0 | L52: =COUNTIFS('Prácticas_Revisiones'!$S$2:$S$282,"T043",'Prácticas_Revisiones'!$T$2:$T$282,"SOFTWARE ENG. MODELS/METH. > *")+COUNTIFS('Prácticas_Snowballing'!$AB$2:$AB$281,"T043",'Prácticas_Snowballing'!$AC$2:$AC$281,"SOFTWARE ENG. MODELS/METH. > *") -> 0 | M52: =COUNTIFS('Prácticas_Revisiones'!$S$2:$S$282,"T043",'Prácticas_Revisiones'!$T$2:$T$282,"SOFTWARE QUALITY > *")+COUNTIFS('Prácticas_Snowballing'!$AB$2:$AB$281,"T043",'Prácticas_Snowballing'!$AC$2:$AC$281,"SOFTWARE QUALITY > *") -> 0 | N52: =COUNTIFS('Prácticas_Revisiones'!$S$2:$S$282,"T043",'Prácticas_Revisiones'!$T$2:$T$282,"SOFTWARE SECURITY > *")+COUNTIFS('Prácticas_Snowballing'!$AB$2:$AB$281,"T043",'Prácticas_Snowballing'!$AC$2:$AC$281,"SOFTWARE SECURITY > *") -> 0 | O52: =COUNTIFS('Prácticas_Revisiones'!$S$2:$S$282,"T043",'Prácticas_Revisiones'!$T$2:$T$282,"PROFESSIONAL PRACTICE > *")+COUNTIFS('Prácticas_Snowballing'!$AB$2:$AB$281,"T043",'Prácticas_Snowballing'!$AC$2:$AC$281,"PROFESSIONAL PRACTICE > *") -> 0 | P52: =COUNTIFS('Prácticas_Revisiones'!$S$2:$S$282,"T043",'Prácticas_Revisiones'!$T$2:$T$282,"SOFTWARE ENG. ECONOMICS > *")+COUNTIFS('Prácticas_Snowballing'!$AB$2:$AB$281,"T043",'Prácticas_Snowballing'!$AC$2:$AC$281,"SOFTWARE ENG. ECONOMICS > *") -> 0 | Q52: =COUNTIFS('Prácticas_Revisiones'!$S$2:$S$282,"T043",'Prácticas_Revisiones'!$T$2:$T$282,"SOFTWARE ENG. MANAGEMENT > *")+COUNTIFS('Prácticas_Snowballing'!$AB$2:$AB$281,"T043",'Prácticas_Snowballing'!$AC$2:$AC$281,"SOFTWARE ENG. MANAGEMENT > *") -> 0 | R52: =COUNTIFS('Prácticas_Revisiones'!$S$2:$S$282,"T043",'Prácticas_Revisiones'!$T$2:$T$282,"Sin área SWEBOK")+COUNTIFS('Prácticas_Snowballing'!$AB$2:$AB$281,"T043",'Prácticas_Snowballing'!$AC$2:$AC$281,"Sin área SWEBOK") -> 0 | S52: =SUM(C52:R52) -> 0
B53: T044 Instrucción personalizada | C53: =COUNTIFS('Prácticas_Revisiones'!$S$2:$S$282,"T044",'Prácticas_Revisiones'!$T$2:$T$282,"REQUIREMENTS > *")+COUNTIFS('Prácticas_Snowballing'!$AB$2:$AB$281,"T044",'Prácticas_Snowballing'!$AC$2:$AC$281,"REQUIREMENTS > *") -> 1 | D53: =COUNTIFS('Prácticas_Revisiones'!$S$2:$S$282,"T044",'Prácticas_Revisiones'!$T$2:$T$282,"ARCHITECTURE > *")+COUNTIFS('Prácticas_Snowballing'!$AB$2:$AB$281,"T044",'Prácticas_Snowballing'!$AC$2:$AC$281,"ARCHITECTURE > *") -> 0 | E53: =COUNTIFS('Prácticas_Revisiones'!$S$2:$S$282,"T044",'Prácticas_Revisiones'!$T$2:$T$282,"DESIGN > *")+COUNTIFS('Prácticas_Snowballing'!$AB$2:$AB$281,"T044",'Prácticas_Snowballing'!$AC$2:$AC$281,"DESIGN > *") -> 2 | F53: =COUNTIFS('Prácticas_Revisiones'!$S$2:$S$282,"T044",'Prácticas_Revisiones'!$T$2:$T$282,"CONSTRUCTION > *")+COUNTIFS('Prácticas_Snowballing'!$AB$2:$AB$281,"T044",'Prácticas_Snowballing'!$AC$2:$AC$281,"CONSTRUCTION > *") -> 86 | G53: =COUNTIFS('Prácticas_Revisiones'!$S$2:$S$282,"T044",'Prácticas_Revisiones'!$T$2:$T$282,"SOFTWARE TESTING > *")+COUNTIFS('Prácticas_Snowballing'!$AB$2:$AB$281,"T044",'Prácticas_Snowballing'!$AC$2:$AC$281,"SOFTWARE TESTING > *") -> 0 | H53: =COUNTIFS('Prácticas_Revisiones'!$S$2:$S$282,"T044",'Prácticas_Revisiones'!$T$2:$T$282,"SOFTWARE ENG. OPERATIONS > *")+COUNTIFS('Prácticas_Snowballing'!$AB$2:$AB$281,"T044",'Prácticas_Snowballing'!$AC$2:$AC$281,"SOFTWARE ENG. OPERATIONS > *") -> 0 | I53: =COUNTIFS('Prácticas_Revisiones'!$S$2:$S$282,"T044",'Prácticas_Revisiones'!$T$2:$T$282,"MAINTENANCE > *")+COUNTIFS('Prácticas_Snowballing'!$AB$2:$AB$281,"T044",'Prácticas_Snowballing'!$AC$2:$AC$281,"MAINTENANCE > *") -> 1 | J53: =COUNTIFS('Prácticas_Revisiones'!$S$2:$S$282,"T044",'Prácticas_Revisiones'!$T$2:$T$282,"SOFTWARE CONFIG. MGMT. > *")+COUNTIFS('Prácticas_Snowballing'!$AB$2:$AB$281,"T044",'Prácticas_Snowballing'!$AC$2:$AC$281,"SOFTWARE CONFIG. MGMT. > *") -> 0 | K53: =COUNTIFS('Prácticas_Revisiones'!$S$2:$S$282,"T044",'Prácticas_Revisiones'!$T$2:$T$282,"SOFTWARE ENG. PROCESS > *")+COUNTIFS('Prácticas_Snowballing'!$AB$2:$AB$281,"T044",'Prácticas_Snowballing'!$AC$2:$AC$281,"SOFTWARE ENG. PROCESS > *") -> 0 | L53: =COUNTIFS('Prácticas_Revisiones'!$S$2:$S$282,"T044",'Prácticas_Revisiones'!$T$2:$T$282,"SOFTWARE ENG. MODELS/METH. > *")+COUNTIFS('Prácticas_Snowballing'!$AB$2:$AB$281,"T044",'Prácticas_Snowballing'!$AC$2:$AC$281,"SOFTWARE ENG. MODELS/METH. > *") -> 1 | M53: =COUNTIFS('Prácticas_Revisiones'!$S$2:$S$282,"T044",'Prácticas_Revisiones'!$T$2:$T$282,"SOFTWARE QUALITY > *")+COUNTIFS('Prácticas_Snowballing'!$AB$2:$AB$281,"T044",'Prácticas_Snowballing'!$AC$2:$AC$281,"SOFTWARE QUALITY > *") -> 2 | N53: =COUNTIFS('Prácticas_Revisiones'!$S$2:$S$282,"T044",'Prácticas_Revisiones'!$T$2:$T$282,"SOFTWARE SECURITY > *")+COUNTIFS('Prácticas_Snowballing'!$AB$2:$AB$281,"T044",'Prácticas_Snowballing'!$AC$2:$AC$281,"SOFTWARE SECURITY > *") -> 1 | O53: =COUNTIFS('Prácticas_Revisiones'!$S$2:$S$282,"T044",'Prácticas_Revisiones'!$T$2:$T$282,"PROFESSIONAL PRACTICE > *")+COUNTIFS('Prácticas_Snowballing'!$AB$2:$AB$281,"T044",'Prácticas_Snowballing'!$AC$2:$AC$281,"PROFESSIONAL PRACTICE > *") -> 0 | P53: =COUNTIFS('Prácticas_Revisiones'!$S$2:$S$282,"T044",'Prácticas_Revisiones'!$T$2:$T$282,"SOFTWARE ENG. ECONOMICS > *")+COUNTIFS('Prácticas_Snowballing'!$AB$2:$AB$281,"T044",'Prácticas_Snowballing'!$AC$2:$AC$281,"SOFTWARE ENG. ECONOMICS > *") -> 0 | Q53: =COUNTIFS('Prácticas_Revisiones'!$S$2:$S$282,"T044",'Prácticas_Revisiones'!$T$2:$T$282,"SOFTWARE ENG. MANAGEMENT > *")+COUNTIFS('Prácticas_Snowballing'!$AB$2:$AB$281,"T044",'Prácticas_Snowballing'!$AC$2:$AC$281,"SOFTWARE ENG. MANAGEMENT > *") -> 1 | R53: =COUNTIFS('Prácticas_Revisiones'!$S$2:$S$282,"T044",'Prácticas_Revisiones'!$T$2:$T$282,"Sin área SWEBOK")+COUNTIFS('Prácticas_Snowballing'!$AB$2:$AB$281,"T044",'Prácticas_Snowballing'!$AC$2:$AC$281,"Sin área SWEBOK") -> 0 | S53: =SUM(C53:R53) -> 95
B54: T045 Juego de roles | C54: =COUNTIFS('Prácticas_Revisiones'!$S$2:$S$282,"T045",'Prácticas_Revisiones'!$T$2:$T$282,"REQUIREMENTS > *")+COUNTIFS('Prácticas_Snowballing'!$AB$2:$AB$281,"T045",'Prácticas_Snowballing'!$AC$2:$AC$281,"REQUIREMENTS > *") -> 1 | D54: =COUNTIFS('Prácticas_Revisiones'!$S$2:$S$282,"T045",'Prácticas_Revisiones'!$T$2:$T$282,"ARCHITECTURE > *")+COUNTIFS('Prácticas_Snowballing'!$AB$2:$AB$281,"T045",'Prácticas_Snowballing'!$AC$2:$AC$281,"ARCHITECTURE > *") -> 0 | E54: =COUNTIFS('Prácticas_Revisiones'!$S$2:$S$282,"T045",'Prácticas_Revisiones'!$T$2:$T$282,"DESIGN > *")+COUNTIFS('Prácticas_Snowballing'!$AB$2:$AB$281,"T045",'Prácticas_Snowballing'!$AC$2:$AC$281,"DESIGN > *") -> 0 | F54: =COUNTIFS('Prácticas_Revisiones'!$S$2:$S$282,"T045",'Prácticas_Revisiones'!$T$2:$T$282,"CONSTRUCTION > *")+COUNTIFS('Prácticas_Snowballing'!$AB$2:$AB$281,"T045",'Prácticas_Snowballing'!$AC$2:$AC$281,"CONSTRUCTION > *") -> 5 | G54: =COUNTIFS('Prácticas_Revisiones'!$S$2:$S$282,"T045",'Prácticas_Revisiones'!$T$2:$T$282,"SOFTWARE TESTING > *")+COUNTIFS('Prácticas_Snowballing'!$AB$2:$AB$281,"T045",'Prácticas_Snowballing'!$AC$2:$AC$281,"SOFTWARE TESTING > *") -> 2 | H54: =COUNTIFS('Prácticas_Revisiones'!$S$2:$S$282,"T045",'Prácticas_Revisiones'!$T$2:$T$282,"SOFTWARE ENG. OPERATIONS > *")+COUNTIFS('Prácticas_Snowballing'!$AB$2:$AB$281,"T045",'Prácticas_Snowballing'!$AC$2:$AC$281,"SOFTWARE ENG. OPERATIONS > *") -> 0 | I54: =COUNTIFS('Prácticas_Revisiones'!$S$2:$S$282,"T045",'Prácticas_Revisiones'!$T$2:$T$282,"MAINTENANCE > *")+COUNTIFS('Prácticas_Snowballing'!$AB$2:$AB$281,"T045",'Prácticas_Snowballing'!$AC$2:$AC$281,"MAINTENANCE > *") -> 0 | J54: =COUNTIFS('Prácticas_Revisiones'!$S$2:$S$282,"T045",'Prácticas_Revisiones'!$T$2:$T$282,"SOFTWARE CONFIG. MGMT. > *")+COUNTIFS('Prácticas_Snowballing'!$AB$2:$AB$281,"T045",'Prácticas_Snowballing'!$AC$2:$AC$281,"SOFTWARE CONFIG. MGMT. > *") -> 0 | K54: =COUNTIFS('Prácticas_Revisiones'!$S$2:$S$282,"T045",'Prácticas_Revisiones'!$T$2:$T$282,"SOFTWARE ENG. PROCESS > *")+COUNTIFS('Prácticas_Snowballing'!$AB$2:$AB$281,"T045",'Prácticas_Snowballing'!$AC$2:$AC$281,"SOFTWARE ENG. PROCESS > *") -> 1 | L54: =COUNTIFS('Prácticas_Revisiones'!$S$2:$S$282,"T045",'Prácticas_Revisiones'!$T$2:$T$282,"SOFTWARE ENG. MODELS/METH. > *")+COUNTIFS('Prácticas_Snowballing'!$AB$2:$AB$281,"T045",'Prácticas_Snowballing'!$AC$2:$AC$281,"SOFTWARE ENG. MODELS/METH. > *") -> 0 | M54: =COUNTIFS('Prácticas_Revisiones'!$S$2:$S$282,"T045",'Prácticas_Revisiones'!$T$2:$T$282,"SOFTWARE QUALITY > *")+COUNTIFS('Prácticas_Snowballing'!$AB$2:$AB$281,"T045",'Prácticas_Snowballing'!$AC$2:$AC$281,"SOFTWARE QUALITY > *") -> 0 | N54: =COUNTIFS('Prácticas_Revisiones'!$S$2:$S$282,"T045",'Prácticas_Revisiones'!$T$2:$T$282,"SOFTWARE SECURITY > *")+COUNTIFS('Prácticas_Snowballing'!$AB$2:$AB$281,"T045",'Prácticas_Snowballing'!$AC$2:$AC$281,"SOFTWARE SECURITY > *") -> 0 | O54: =COUNTIFS('Prácticas_Revisiones'!$S$2:$S$282,"T045",'Prácticas_Revisiones'!$T$2:$T$282,"PROFESSIONAL PRACTICE > *")+COUNTIFS('Prácticas_Snowballing'!$AB$2:$AB$281,"T045",'Prácticas_Snowballing'!$AC$2:$AC$281,"PROFESSIONAL PRACTICE > *") -> 3 | P54: =COUNTIFS('Prácticas_Revisiones'!$S$2:$S$282,"T045",'Prácticas_Revisiones'!$T$2:$T$282,"SOFTWARE ENG. ECONOMICS > *")+COUNTIFS('Prácticas_Snowballing'!$AB$2:$AB$281,"T045",'Prácticas_Snowballing'!$AC$2:$AC$281,"SOFTWARE ENG. ECONOMICS > *") -> 0 | Q54: =COUNTIFS('Prácticas_Revisiones'!$S$2:$S$282,"T045",'Prácticas_Revisiones'!$T$2:$T$282,"SOFTWARE ENG. MANAGEMENT > *")+COUNTIFS('Prácticas_Snowballing'!$AB$2:$AB$281,"T045",'Prácticas_Snowballing'!$AC$2:$AC$281,"SOFTWARE ENG. MANAGEMENT > *") -> 0 | R54: =COUNTIFS('Prácticas_Revisiones'!$S$2:$S$282,"T045",'Prácticas_Revisiones'!$T$2:$T$282,"Sin área SWEBOK")+COUNTIFS('Prácticas_Snowballing'!$AB$2:$AB$281,"T045",'Prácticas_Snowballing'!$AC$2:$AC$281,"Sin área SWEBOK") -> 0 | S54: =SUM(C54:R54) -> 12
B55: T046 Medios sociales | C55: =COUNTIFS('Prácticas_Revisiones'!$S$2:$S$282,"T046",'Prácticas_Revisiones'!$T$2:$T$282,"REQUIREMENTS > *")+COUNTIFS('Prácticas_Snowballing'!$AB$2:$AB$281,"T046",'Prácticas_Snowballing'!$AC$2:$AC$281,"REQUIREMENTS > *") -> 0 | D55: =COUNTIFS('Prácticas_Revisiones'!$S$2:$S$282,"T046",'Prácticas_Revisiones'!$T$2:$T$282,"ARCHITECTURE > *")+COUNTIFS('Prácticas_Snowballing'!$AB$2:$AB$281,"T046",'Prácticas_Snowballing'!$AC$2:$AC$281,"ARCHITECTURE > *") -> 0 | E55: =COUNTIFS('Prácticas_Revisiones'!$S$2:$S$282,"T046",'Prácticas_Revisiones'!$T$2:$T$282,"DESIGN > *")+COUNTIFS('Prácticas_Snowballing'!$AB$2:$AB$281,"T046",'Prácticas_Snowballing'!$AC$2:$AC$281,"DESIGN > *") -> 0 | F55: =COUNTIFS('Prácticas_Revisiones'!$S$2:$S$282,"T046",'Prácticas_Revisiones'!$T$2:$T$282,"CONSTRUCTION > *")+COUNTIFS('Prácticas_Snowballing'!$AB$2:$AB$281,"T046",'Prácticas_Snowballing'!$AC$2:$AC$281,"CONSTRUCTION > *") -> 0 | G55: =COUNTIFS('Prácticas_Revisiones'!$S$2:$S$282,"T046",'Prácticas_Revisiones'!$T$2:$T$282,"SOFTWARE TESTING > *")+COUNTIFS('Prácticas_Snowballing'!$AB$2:$AB$281,"T046",'Prácticas_Snowballing'!$AC$2:$AC$281,"SOFTWARE TESTING > *") -> 0 | H55: =COUNTIFS('Prácticas_Revisiones'!$S$2:$S$282,"T046",'Prácticas_Revisiones'!$T$2:$T$282,"SOFTWARE ENG. OPERATIONS > *")+COUNTIFS('Prácticas_Snowballing'!$AB$2:$AB$281,"T046",'Prácticas_Snowballing'!$AC$2:$AC$281,"SOFTWARE ENG. OPERATIONS > *") -> 0 | I55: =COUNTIFS('Prácticas_Revisiones'!$S$2:$S$282,"T046",'Prácticas_Revisiones'!$T$2:$T$282,"MAINTENANCE > *")+COUNTIFS('Prácticas_Snowballing'!$AB$2:$AB$281,"T046",'Prácticas_Snowballing'!$AC$2:$AC$281,"MAINTENANCE > *") -> 0 | J55: =COUNTIFS('Prácticas_Revisiones'!$S$2:$S$282,"T046",'Prácticas_Revisiones'!$T$2:$T$282,"SOFTWARE CONFIG. MGMT. > *")+COUNTIFS('Prácticas_Snowballing'!$AB$2:$AB$281,"T046",'Prácticas_Snowballing'!$AC$2:$AC$281,"SOFTWARE CONFIG. MGMT. > *") -> 0 | K55: =COUNTIFS('Prácticas_Revisiones'!$S$2:$S$282,"T046",'Prácticas_Revisiones'!$T$2:$T$282,"SOFTWARE ENG. PROCESS > *")+COUNTIFS('Prácticas_Snowballing'!$AB$2:$AB$281,"T046",'Prácticas_Snowballing'!$AC$2:$AC$281,"SOFTWARE ENG. PROCESS > *") -> 0 | L55: =COUNTIFS('Prácticas_Revisiones'!$S$2:$S$282,"T046",'Prácticas_Revisiones'!$T$2:$T$282,"SOFTWARE ENG. MODELS/METH. > *")+COUNTIFS('Prácticas_Snowballing'!$AB$2:$AB$281,"T046",'Prácticas_Snowballing'!$AC$2:$AC$281,"SOFTWARE ENG. MODELS/METH. > *") -> 0 | M55: =COUNTIFS('Prácticas_Revisiones'!$S$2:$S$282,"T046",'Prácticas_Revisiones'!$T$2:$T$282,"SOFTWARE QUALITY > *")+COUNTIFS('Prácticas_Snowballing'!$AB$2:$AB$281,"T046",'Prácticas_Snowballing'!$AC$2:$AC$281,"SOFTWARE QUALITY > *") -> 0 | N55: =COUNTIFS('Prácticas_Revisiones'!$S$2:$S$282,"T046",'Prácticas_Revisiones'!$T$2:$T$282,"SOFTWARE SECURITY > *")+COUNTIFS('Prácticas_Snowballing'!$AB$2:$AB$281,"T046",'Prácticas_Snowballing'!$AC$2:$AC$281,"SOFTWARE SECURITY > *") -> 0 | O55: =COUNTIFS('Prácticas_Revisiones'!$S$2:$S$282,"T046",'Prácticas_Revisiones'!$T$2:$T$282,"PROFESSIONAL PRACTICE > *")+COUNTIFS('Prácticas_Snowballing'!$AB$2:$AB$281,"T046",'Prácticas_Snowballing'!$AC$2:$AC$281,"PROFESSIONAL PRACTICE > *") -> 0 | P55: =COUNTIFS('Prácticas_Revisiones'!$S$2:$S$282,"T046",'Prácticas_Revisiones'!$T$2:$T$282,"SOFTWARE ENG. ECONOMICS > *")+COUNTIFS('Prácticas_Snowballing'!$AB$2:$AB$281,"T046",'Prácticas_Snowballing'!$AC$2:$AC$281,"SOFTWARE ENG. ECONOMICS > *") -> 0 | Q55: =COUNTIFS('Prácticas_Revisiones'!$S$2:$S$282,"T046",'Prácticas_Revisiones'!$T$2:$T$282,"SOFTWARE ENG. MANAGEMENT > *")+COUNTIFS('Prácticas_Snowballing'!$AB$2:$AB$281,"T046",'Prácticas_Snowballing'!$AC$2:$AC$281,"SOFTWARE ENG. MANAGEMENT > *") -> 0 | R55: =COUNTIFS('Prácticas_Revisiones'!$S$2:$S$282,"T046",'Prácticas_Revisiones'!$T$2:$T$282,"Sin área SWEBOK")+COUNTIFS('Prácticas_Snowballing'!$AB$2:$AB$281,"T046",'Prácticas_Snowballing'!$AC$2:$AC$281,"Sin área SWEBOK") -> 0 | S55: =SUM(C55:R55) -> 0
B56: T047 Mesa redonda con interrogador | C56: =COUNTIFS('Prácticas_Revisiones'!$S$2:$S$282,"T047",'Prácticas_Revisiones'!$T$2:$T$282,"REQUIREMENTS > *")+COUNTIFS('Prácticas_Snowballing'!$AB$2:$AB$281,"T047",'Prácticas_Snowballing'!$AC$2:$AC$281,"REQUIREMENTS > *") -> 0 | D56: =COUNTIFS('Prácticas_Revisiones'!$S$2:$S$282,"T047",'Prácticas_Revisiones'!$T$2:$T$282,"ARCHITECTURE > *")+COUNTIFS('Prácticas_Snowballing'!$AB$2:$AB$281,"T047",'Prácticas_Snowballing'!$AC$2:$AC$281,"ARCHITECTURE > *") -> 0 | E56: =COUNTIFS('Prácticas_Revisiones'!$S$2:$S$282,"T047",'Prácticas_Revisiones'!$T$2:$T$282,"DESIGN > *")+COUNTIFS('Prácticas_Snowballing'!$AB$2:$AB$281,"T047",'Prácticas_Snowballing'!$AC$2:$AC$281,"DESIGN > *") -> 0 | F56: =COUNTIFS('Prácticas_Revisiones'!$S$2:$S$282,"T047",'Prácticas_Revisiones'!$T$2:$T$282,"CONSTRUCTION > *")+COUNTIFS('Prácticas_Snowballing'!$AB$2:$AB$281,"T047",'Prácticas_Snowballing'!$AC$2:$AC$281,"CONSTRUCTION > *") -> 0 | G56: =COUNTIFS('Prácticas_Revisiones'!$S$2:$S$282,"T047",'Prácticas_Revisiones'!$T$2:$T$282,"SOFTWARE TESTING > *")+COUNTIFS('Prácticas_Snowballing'!$AB$2:$AB$281,"T047",'Prácticas_Snowballing'!$AC$2:$AC$281,"SOFTWARE TESTING > *") -> 0 | H56: =COUNTIFS('Prácticas_Revisiones'!$S$2:$S$282,"T047",'Prácticas_Revisiones'!$T$2:$T$282,"SOFTWARE ENG. OPERATIONS > *")+COUNTIFS('Prácticas_Snowballing'!$AB$2:$AB$281,"T047",'Prácticas_Snowballing'!$AC$2:$AC$281,"SOFTWARE ENG. OPERATIONS > *") -> 0 | I56: =COUNTIFS('Prácticas_Revisiones'!$S$2:$S$282,"T047",'Prácticas_Revisiones'!$T$2:$T$282,"MAINTENANCE > *")+COUNTIFS('Prácticas_Snowballing'!$AB$2:$AB$281,"T047",'Prácticas_Snowballing'!$AC$2:$AC$281,"MAINTENANCE > *") -> 0 | J56: =COUNTIFS('Prácticas_Revisiones'!$S$2:$S$282,"T047",'Prácticas_Revisiones'!$T$2:$T$282,"SOFTWARE CONFIG. MGMT. > *")+COUNTIFS('Prácticas_Snowballing'!$AB$2:$AB$281,"T047",'Prácticas_Snowballing'!$AC$2:$AC$281,"SOFTWARE CONFIG. MGMT. > *") -> 0 | K56: =COUNTIFS('Prácticas_Revisiones'!$S$2:$S$282,"T047",'Prácticas_Revisiones'!$T$2:$T$282,"SOFTWARE ENG. PROCESS > *")+COUNTIFS('Prácticas_Snowballing'!$AB$2:$AB$281,"T047",'Prácticas_Snowballing'!$AC$2:$AC$281,"SOFTWARE ENG. PROCESS > *") -> 0 | L56: =COUNTIFS('Prácticas_Revisiones'!$S$2:$S$282,"T047",'Prácticas_Revisiones'!$T$2:$T$282,"SOFTWARE ENG. MODELS/METH. > *")+COUNTIFS('Prácticas_Snowballing'!$AB$2:$AB$281,"T047",'Prácticas_Snowballing'!$AC$2:$AC$281,"SOFTWARE ENG. MODELS/METH. > *") -> 0 | M56: =COUNTIFS('Prácticas_Revisiones'!$S$2:$S$282,"T047",'Prácticas_Revisiones'!$T$2:$T$282,"SOFTWARE QUALITY > *")+COUNTIFS('Prácticas_Snowballing'!$AB$2:$AB$281,"T047",'Prácticas_Snowballing'!$AC$2:$AC$281,"SOFTWARE QUALITY > *") -> 0 | N56: =COUNTIFS('Prácticas_Revisiones'!$S$2:$S$282,"T047",'Prácticas_Revisiones'!$T$2:$T$282,"SOFTWARE SECURITY > *")+COUNTIFS('Prácticas_Snowballing'!$AB$2:$AB$281,"T047",'Prácticas_Snowballing'!$AC$2:$AC$281,"SOFTWARE SECURITY > *") -> 0 | O56: =COUNTIFS('Prácticas_Revisiones'!$S$2:$S$282,"T047",'Prácticas_Revisiones'!$T$2:$T$282,"PROFESSIONAL PRACTICE > *")+COUNTIFS('Prácticas_Snowballing'!$AB$2:$AB$281,"T047",'Prácticas_Snowballing'!$AC$2:$AC$281,"PROFESSIONAL PRACTICE > *") -> 0 | P56: =COUNTIFS('Prácticas_Revisiones'!$S$2:$S$282,"T047",'Prácticas_Revisiones'!$T$2:$T$282,"SOFTWARE ENG. ECONOMICS > *")+COUNTIFS('Prácticas_Snowballing'!$AB$2:$AB$281,"T047",'Prácticas_Snowballing'!$AC$2:$AC$281,"SOFTWARE ENG. ECONOMICS > *") -> 0 | Q56: =COUNTIFS('Prácticas_Revisiones'!$S$2:$S$282,"T047",'Prácticas_Revisiones'!$T$2:$T$282,"SOFTWARE ENG. MANAGEMENT > *")+COUNTIFS('Prácticas_Snowballing'!$AB$2:$AB$281,"T047",'Prácticas_Snowballing'!$AC$2:$AC$281,"SOFTWARE ENG. MANAGEMENT > *") -> 0 | R56: =COUNTIFS('Prácticas_Revisiones'!$S$2:$S$282,"T047",'Prácticas_Revisiones'!$T$2:$T$282,"Sin área SWEBOK")+COUNTIFS('Prácticas_Snowballing'!$AB$2:$AB$281,"T047",'Prácticas_Snowballing'!$AC$2:$AC$281,"Sin área SWEBOK") -> 0 | S56: =SUM(C56:R56) -> 0
B57: T048 Panel de discusión | C57: =COUNTIFS('Prácticas_Revisiones'!$S$2:$S$282,"T048",'Prácticas_Revisiones'!$T$2:$T$282,"REQUIREMENTS > *")+COUNTIFS('Prácticas_Snowballing'!$AB$2:$AB$281,"T048",'Prácticas_Snowballing'!$AC$2:$AC$281,"REQUIREMENTS > *") -> 0 | D57: =COUNTIFS('Prácticas_Revisiones'!$S$2:$S$282,"T048",'Prácticas_Revisiones'!$T$2:$T$282,"ARCHITECTURE > *")+COUNTIFS('Prácticas_Snowballing'!$AB$2:$AB$281,"T048",'Prácticas_Snowballing'!$AC$2:$AC$281,"ARCHITECTURE > *") -> 0 | E57: =COUNTIFS('Prácticas_Revisiones'!$S$2:$S$282,"T048",'Prácticas_Revisiones'!$T$2:$T$282,"DESIGN > *")+COUNTIFS('Prácticas_Snowballing'!$AB$2:$AB$281,"T048",'Prácticas_Snowballing'!$AC$2:$AC$281,"DESIGN > *") -> 0 | F57: =COUNTIFS('Prácticas_Revisiones'!$S$2:$S$282,"T048",'Prácticas_Revisiones'!$T$2:$T$282,"CONSTRUCTION > *")+COUNTIFS('Prácticas_Snowballing'!$AB$2:$AB$281,"T048",'Prácticas_Snowballing'!$AC$2:$AC$281,"CONSTRUCTION > *") -> 0 | G57: =COUNTIFS('Prácticas_Revisiones'!$S$2:$S$282,"T048",'Prácticas_Revisiones'!$T$2:$T$282,"SOFTWARE TESTING > *")+COUNTIFS('Prácticas_Snowballing'!$AB$2:$AB$281,"T048",'Prácticas_Snowballing'!$AC$2:$AC$281,"SOFTWARE TESTING > *") -> 0 | H57: =COUNTIFS('Prácticas_Revisiones'!$S$2:$S$282,"T048",'Prácticas_Revisiones'!$T$2:$T$282,"SOFTWARE ENG. OPERATIONS > *")+COUNTIFS('Prácticas_Snowballing'!$AB$2:$AB$281,"T048",'Prácticas_Snowballing'!$AC$2:$AC$281,"SOFTWARE ENG. OPERATIONS > *") -> 0 | I57: =COUNTIFS('Prácticas_Revisiones'!$S$2:$S$282,"T048",'Prácticas_Revisiones'!$T$2:$T$282,"MAINTENANCE > *")+COUNTIFS('Prácticas_Snowballing'!$AB$2:$AB$281,"T048",'Prácticas_Snowballing'!$AC$2:$AC$281,"MAINTENANCE > *") -> 0 | J57: =COUNTIFS('Prácticas_Revisiones'!$S$2:$S$282,"T048",'Prácticas_Revisiones'!$T$2:$T$282,"SOFTWARE CONFIG. MGMT. > *")+COUNTIFS('Prácticas_Snowballing'!$AB$2:$AB$281,"T048",'Prácticas_Snowballing'!$AC$2:$AC$281,"SOFTWARE CONFIG. MGMT. > *") -> 0 | K57: =COUNTIFS('Prácticas_Revisiones'!$S$2:$S$282,"T048",'Prácticas_Revisiones'!$T$2:$T$282,"SOFTWARE ENG. PROCESS > *")+COUNTIFS('Prácticas_Snowballing'!$AB$2:$AB$281,"T048",'Prácticas_Snowballing'!$AC$2:$AC$281,"SOFTWARE ENG. PROCESS > *") -> 0 | L57: =COUNTIFS('Prácticas_Revisiones'!$S$2:$S$282,"T048",'Prácticas_Revisiones'!$T$2:$T$282,"SOFTWARE ENG. MODELS/METH. > *")+COUNTIFS('Prácticas_Snowballing'!$AB$2:$AB$281,"T048",'Prácticas_Snowballing'!$AC$2:$AC$281,"SOFTWARE ENG. MODELS/METH. > *") -> 0 | M57: =COUNTIFS('Prácticas_Revisiones'!$S$2:$S$282,"T048",'Prácticas_Revisiones'!$T$2:$T$282,"SOFTWARE QUALITY > *")+COUNTIFS('Prácticas_Snowballing'!$AB$2:$AB$281,"T048",'Prácticas_Snowballing'!$AC$2:$AC$281,"SOFTWARE QUALITY > *") -> 0 | N57: =COUNTIFS('Prácticas_Revisiones'!$S$2:$S$282,"T048",'Prácticas_Revisiones'!$T$2:$T$282,"SOFTWARE SECURITY > *")+COUNTIFS('Prácticas_Snowballing'!$AB$2:$AB$281,"T048",'Prácticas_Snowballing'!$AC$2:$AC$281,"SOFTWARE SECURITY > *") -> 0 | O57: =COUNTIFS('Prácticas_Revisiones'!$S$2:$S$282,"T048",'Prácticas_Revisiones'!$T$2:$T$282,"PROFESSIONAL PRACTICE > *")+COUNTIFS('Prácticas_Snowballing'!$AB$2:$AB$281,"T048",'Prácticas_Snowballing'!$AC$2:$AC$281,"PROFESSIONAL PRACTICE > *") -> 0 | P57: =COUNTIFS('Prácticas_Revisiones'!$S$2:$S$282,"T048",'Prácticas_Revisiones'!$T$2:$T$282,"SOFTWARE ENG. ECONOMICS > *")+COUNTIFS('Prácticas_Snowballing'!$AB$2:$AB$281,"T048",'Prácticas_Snowballing'!$AC$2:$AC$281,"SOFTWARE ENG. ECONOMICS > *") -> 0 | Q57: =COUNTIFS('Prácticas_Revisiones'!$S$2:$S$282,"T048",'Prácticas_Revisiones'!$T$2:$T$282,"SOFTWARE ENG. MANAGEMENT > *")+COUNTIFS('Prácticas_Snowballing'!$AB$2:$AB$281,"T048",'Prácticas_Snowballing'!$AC$2:$AC$281,"SOFTWARE ENG. MANAGEMENT > *") -> 0 | R57: =COUNTIFS('Prácticas_Revisiones'!$S$2:$S$282,"T048",'Prácticas_Revisiones'!$T$2:$T$282,"Sin área SWEBOK")+COUNTIFS('Prácticas_Snowballing'!$AB$2:$AB$281,"T048",'Prácticas_Snowballing'!$AC$2:$AC$281,"Sin área SWEBOK") -> 0 | S57: =SUM(C57:R57) -> 0
